Workbook

Sheet CLIENTE
A1: NOME_FANTASIA | B1: RAZÃO_SOCIAL | C1: CPF_CNPJ | D1: ESTADO | E1: TELEFONE | F1: E-MAIL
A4: ASSEMBLEIA LEGISLATIVA DO ESTADO DO CEARÁ | B4: ASSEMBLEIA LEGISLATIVA DO ESTADO DO CEARÁ | C4: 06.750.525/0001-20 | D4: CEARÁ | E4: (85) 99659-5679 | F4: jessika.sato@al.ce.gov.br infracoti@al.ce.gov.br
A5: COMANDO DA 10a REGIAO MILITAR | B5: COMANDO DA 10a REGIAO MILITAR | C5: 09.560.963/0001-14 | D5: CEARÁ | E5: (85) 3255-1648 | F5: cpl10rm@gmail.com
A6: COLEGIO MILITAR DE FORTALEZA | B6: CMFOR | C6: 10.216.602/0001-34 | D6: CEARÁ | E6: (85) 8535-3737 | F6: informatica@cmf.eb.mil.br
A7: ESCOLA DE APRENDIZEM DE MARINHEIROS DO CEARÁ | B7: ESCOLA DE APRENDIZEM DE MARINHEIROS DO CEARÁ | C7: 00.394.502/0116-93 | D7: CEARÁ | E7: (85)3288-4734 | F7: eloy.lima@marinha.mil.br gleidson@marinha.mil.br
A8: UNIVERSIDADE FEDERAL DO CEARÁ | B8: UNIVERSIDADE FEDERAL DO CEARÁ | C8: 07.272.636/0001-31 | D8: CEARÁ | E8: (85) 3366-7377 / 7378 | F8: dgcac@proplad.ufc.br marcosb@ufc.br
A9: INSTITUTO FEDERAL DE EDUCAÇÃO E TECNOLOGIA - IFCE CAMOCIM | B9: INSTITUTO FEDERAL DE EDUCAÇÃO E TECNOLOGIA - IFCE CAMOCIM | C9: 10.744.098/0024-31 | D9: CEARÁ | E9: (88) 9623-2025 | F9: yara.cristina@ifce.edu.br celestina@ifce.edu.br
A10: INSTITUTO FEDERAL DE EDUCAÇÃO E TECNOLOGIA - IFCE CAUCAIA | B10: INSTITUTO FEDERAL DE EDUCAÇÃO E TECNOLOGIA - IFCE CAUCAIA | C10: 10.744.098/0023-50 | D10: CEARÁ | E10: (85) 9106-5665 | F10: contratos.caucaia@ifce.edu.br
A11: INSTITUTO FEDERAL DE EDUCAÇÃO E TECNOLOGIA - IFCE ITAPIPOCA | B11: INSTITUTO FEDERAL DE EDUCAÇÃO E TECNOLOGIA - IFCE ITAPIPOCA | C11: 10.744.098/0028-65 | D11: CEARÁ | E11: (85) 9423-4521 | F11: assdap@ifce.edu.br, Nathalia.sousa@ifce.edu.br
A12: INSTITUTO FEDERAL DE EDUCAÇÃO E TECNOLOGIA - IFCE PARACURU | B12: INSTITUTO FEDERAL DE EDUCAÇÃO E TECNOLOGIA - IFCE PARACURU | C12: 10.744.098/0029-46 | D12: CEARÁ | E12: (85) 3401-2442 ou (85) 98193-2171 | F12: sac@paracuru.ifce.edu.br, marcelo.silva@ifce.edu.br
A13: INSTITUTO FEDERAL DE EDUCAÇÃO E TECNOLOGIA - IFCE JUAZEIRO DO NORTE | B13: INSTITUTO FEDERAL DE EDUCAÇÃO E TECNOLOGIA - IFCE JUAZEIRO DO NORTE | C13: 10.744.098/0005-79 | D13: CEARÁ | E13: (88) 2101-5305 | F13: cti.juazeiro@ifce.edu.br, isaacbrigido@ifce.edu.br, dap.jua@ifce.edu.br
A14: MINISTÉRIO DA AGRICULTURA E PECUÁRIA/SUPERINTENDÊNCIA FEDERAL DE AGRICULTURA E PECUÁRIA NO PARANÁ (SFA-PR/MAPA) | B14: MINISTÉRIO DA AGRICULTURA E PECUÁRIA/SUPERINTENDÊNCIA FEDERAL DE AGRICULTURA E PECUÁRIA NO PARANÁ (SFA-PR/MAPA) | C14: 01.628.251/0001-88 | D14: PARANÁ | E14: (48) 98410-7584 ou (41) 9272-1569 | F14: alex.borges@agro.gov.br, jair.matos@agro.gov.br
... A54: SEMCAS | B54: SECRETARIA MUNICIPAL DA CRIANÇA E ASSISTÊNCIA SOCIAL | C54: 06.307.102/0001-30 | D54: MARANHÃO | E54: (98) 99158-0854 | F54: semcas@saoluis.ma.gov.br
A55: PREFEITURA MUNICIPAL DE ARACATI - CASA CIVIL | B55: PREFEITURA MUNICIPAL DE ARACATI - CASA CIVIL | C55: 07.684.756/0001-46 | D55: CEARÁ | F55: julio-juca@hotmail.com, TITTO.SOL@aracati.ce.gov.br>
A56: PREF. MUNICIPAL DE CANINDE - AGRICULTURA | B56: PREFEITURA MUNICIPAL DE CANINDE | C56: 07.963.259/0001-87 | D56: CEARÁ | E56: (85) 8542-1298 | F56: Agricultura.Canindece@gmail.com
A57: PREFEITURA MUNICIPAL DE ARACATI - SEGURANÇA CIDADÃ | B57: PREFEITURA MUNICIPAL DE ARACATI - SEGURANÇA CIDADÃ | C57: 07.684.756/0001-46 | D57: CEARÁ | F57: TITTO.SOL@aracati.ce.gov.br, ARACATISEGURANCA@gmail.com
A58: PREFEITURA MUNICIPAL DE ARACATI - SEGURANÇA CIDADÃ | B58: PREFEITURA MUNICIPAL DE ARACATI - SEGURANÇA CIDADÃ | C58: 07.684.756/0001-46 | D58: CEARÁ | F58: TITTO.SOL@aracati.ce.gov.br, ARACATISEGURANCA@gmail.com
A59: MARANGUAPE - PREFEITURA MUNICIPAL DE MARANGUAPE | B59: PREFEITURA MUNICIPAL DE MARANGUAPE - GABINETE | C59: 07.963.051/0001-68 | D59: CEARÁ | E59: (85) 3369-9101 | F59: gabfinan.mpe@gmail.com
A60: PREFEITURA MUNICIPAL DE MOCOCA | B60: PREFEITURA MUNICIPAL DE MOCOCA | C60: 44.763.928/0001-01 | D60: SÃO PAULO | E60: (19) 3656-9800 | F60: financeiro@mococa.sp.gov.br
A61: PREFEITURA MUNICIPAL DE TIANGUA - SAUDE | B61: PREFEITURA MUNICIPAL DE TIANGUA - SAUDE | C61: 07.735.178/0001-20 | D61: CEARÁ | E61: (85) 3671-2288 / (85) 3671-2888 | F61: licitacao@tiangua.ce.gov.br
A62: PREF. MUNICIPAL DE ARACATI - DESENVOLVIMENTO SOCIAL | B62: PREF. MUNICIPAL DE ARACATI - DESENVOLVIMENTO SOCIAL | C62: 07.684.756/0001-46 | D62: CEARÁ | F62: assistenciasocialfinanceiro4@gmail.com assistenciasocialfinanceiro@gmail.com, TITTO.SOL@aracati.ce.gov.br
A63: MARANGUAPE - PREFEITURA MUNICIPAL DE MARANGUAPE | B63: PREFEITURA MUNICIPAL DE MARANGUAPE - SAUDE | C63: 07.963.051/0001-68 | D63: CEARÁ | E63: (85) 3369-9101 | F63: ADMSAUDEPMM@gmail.com
A64: MARANGUAPE - PREFEITURA MUNICIPAL DE MARANGUAPE | B64: PREFEITURA MUNICIPAL DE MARANGUAPE - SAFIN | C64: 07.963.051/0001-68 | D64: CEARÁ | E64: (85) 3369-9101 | F64: maranguapesafinfin@gmail.com
A65: PREF. MUNICIPAL DE ARACATI - CONTROLADORIA | B65: PREF. MUNICIPAL DE ARACATI - CONTROLADORIA | C65: 07.684.756/0001-46 | D65: CEARÁ | F65: controladoria@aracati.ce.gov.br>, TITTO.SOL@aracati.ce.gov.br
A66: PREFEITURA MUNICIPAL DE ITAREMA - SAUDE | B66: PREFEITURA MUNICIPAL DE ITAREMA - SAUDE | C66: 07.663.941/0001-54 | D66: CEARÁ | E66: (88) 3667-1133 / 3667-1340 | F66: compras@itarema.ce.gov.br, setordecomprasitarema@gmail.com, comprasitarema@gmail.com.br, comprasitarema@gmail.com.gov.br
A67: PREFEITURA MUNICIPAL DE ACOPIARA - PROCURADORIA | B67: PREFEITURA MUNICIPAL DE ACOPIARA - PROCURADORIA | C67: 07.847.379/0001-19 | D67: CEARÁ | E67: (88) 3565-1999 | F67: prefeitura@acopiara.ce.gov.br, pedroaarolim@hotmail.com, procuradoria@acopiara.ce.gov.br
A68: MARANGUAPE - PREFEITURA MUNICIPAL DE MARANGUAPE | B68: PREFEITURA MUNICIPAL DE MARANGUAPE - SEJUV | C68: 07.963.051/0001-68 | D68: CEARÁ | E68: (85) 3369-9101 | F68: Sejuv.pmm@hotmail.com
A69: MARANGUAPE - PREFEITURA MUNICIPAL DE MARANGUAPE | B69: PREFEITURA MUNICIPAL DE MARANGUAPE - TRAB ASSIST SOCIAL | C69: 07.963.051/0001-68 | D69: CEARÁ | E69: (85) 3369-9101 | F69: financeiro.stds@gmail.com
A70: MARANGUAPE - PREFEITURA MUNICIPAL DE MARANGUAPE | B70: PREFEITURA MUNICIPAL DE MARANGUAPE - TRAB ASSIST SOCIAL | C70: 07.963.051/0001-68 | D70: CEARÁ | E70: (85) 3369-9101 | F70: financeiro.stds@gmail.com
A71: PREFEITURA MUNICIPAL DE ACOPIARA - SAÚDE | B71: PREFEITURA MUNICIPAL DE ACOPIARA - SAÚDE | C71: 07.847.379/0001-19 | D71: CEARÁ | E71: (88) 3565-1999 | F71: prefeitura@acopiara.ce.gov.br, pedroaarolim@hotmail.com, saude@acopiara.ce.gov.br
A72: PREFEITURA MUNICIPAL DE ACOPIARA - TRANSPORTE E LOGISTICA | B72: PREFEITURA MUNICIPAL DE ACOPIARA - TRANSPORTE E LOGISTICA | C72: 07.847.379/0001-19 | D72: CEARÁ | E72: (88) 3565-1999 | F72: prefeitura@acopiara.ce.gov.br, pedroaarolim@hotmail.com, sttrans@acopiara.ce.gov.br
A73: PREFEITURA MUNICIPAL DE ACOPIARA - TRABALHO E DESENVOLVIMENTO SOCIAL | B73: PREFEITURA MUNICIPAL DE ACOPIARA - TRABALHO E DESENVOLVIMENTO SOCIAL | C73: 07.847.379/0001-19 | D73: CEARÁ | E73: (88) 3565-1999 | F73: prefeitura@acopiara.ce.gov.br, pedroaarolim@hotmail.com, stds@acopiara.ce.gov.br
A74: PREFEITURA MUNICIPAL DE ACOPIARA - TRABALHO E DESENVOLVIMENTO SOCIAL - PROGRAMAS | B74: PREFEITURA MUNICIPAL DE ACOPIARA - TRABALHO E DESENVOLVIMENTO SOCIAL - PROGRAMAS | C74: 07.847.379/0001-19 | D74: CEARÁ | E74: (88) 3565-1999 | F74: prefeitura@acopiara.ce.gov.br, pedroaarolim@hotmail.com, stds@acopiara.ce.gov.br
A75: SECRETARIA DO TRABALHO DO ESTADO DO CEARÁ - SET | B75: SECRETARIA DO TRABALHO DO ESTADO DO CEARÁ - SET | C75: 49.921.771/0001-00 | D75: CEARÁ | E75: (85) 3376-1100 | F75: simone.teles@trabalho.ce.gov.br jidlafe.rodrigues@trabalho.ce.gov.br, carlos.cesar@trabalho.ce.gov.br
A76: PREFEITURA MUNICIPAL DE PALMACIA - FUNDO MUNICIPAL DE ASSISTENCIA SOCIAL | B76: PREFEITURA MUNICIPAL DE PALMACIA - FUNDO MUNICIPAL DE ASSISTENCIA SOCIAL | C76: 07.711.666/0001-05 | D76: CEARÁ | E76: (85) 3924-6903 | F76: assistencia@palmacia.ce.gov.br, controladoria@palmacia.ce.gov.br, matheusgomeschagas@gmail.com
A77: PREFEITURA MUNICIPAL DE PALMACIA - EDUCAÇÃO | B77: PREFEITURA MUNICIPAL DE PALMACIA - EDUCAÇÃO | C77: 07.711.666/0001-05 | D77: CEARÁ | E77: (85) 3924-6901 / (85) 3924-6901 | F77: sme@palmacia.ce.gov.br, controladoria@palmacia.ce.gov.br, matheusgomeschagas@gmail.com
... A82: PREFEITURA MUNICIPAL DE PALMACIA - FINANÇAS | B82: PREFEITURA MUNICIPAL DE PALMACIA - FINANÇAS | C82: 07.711.666/0001-05 | D82: CEARÁ | E82: (85) 3924-6907 / (85) 3924-6907 | F82: matheusgomeschagas@gmail.com, controladoria@palmacia.ce.gov.br, smefinanca@palmacia.ce.gov.br
A83: PREFEITURA MUNICIPAL DE ARACATI - DESENVOLVIMENTO AGRÁRIO | B83: PREFEITURA MUNICIPAL DE ARACATI - DESENVOLVIMENTO AGRÁRIO | C83: 07.684.756/0001-46 | D83: CEARÁ
A84: PREFEITURA MUNICIPAL DE PALMACIA - OBRAS E MEIO AMBIENTE | B84: PREFEITURA MUNICIPAL DE PALMACIA - OBRAS E MEIO AMBIENTE | C84: 07.711.666/0001-05 | D84: CEARÁ | E84: (85) 3924-6907/ (85) 3924-6907 | F84: obras@palmacia.ce.gov.br, controladoria@palmacia.ce.gov.br, matheusgomeschagas@gmail.com
A85: PREFEITURA MUNICIPAL DE PALMACIA - SAÚDE | B85: PREFEITURA MUNICIPAL DE PALMACIA - SAÚDE | C85: 07.711.666/0001-05 | D85: CEARÁ | E85: (85) 9.9110-5699 / (85) 3924-6909 | F85: saude@palmacia.ce.gov.br, controladoria@palmacia.ce.gov.br, matheusgomeschagas@gmail.com
A86: MARANGUAPE - PREFEITURA MUNICIPAL DE MARANGUAPE | B86: HOSPITAL MUNICIPAL DR. AUGEU BRAGA HERBSTER | C86: 07.963.051/0001-68 | D86: CEARÁ | E86: (85) 3369-9101 | F86: hmabhbraga2021@gmail.com
A87: MARANGUAPE - PREFEITURA MUNICIPAL DE MARANGUAPE | B87: PREFEITURA MUNICIPAL DE MARANGUAPE - AGRICULTURA, PESCA E RECURSOS HÍDRICOS | F87: seagri.maranguape@yahoo.com
A88: MARANGUAPE - PREFEITURA MUNICIPAL DE MARANGUAPE | B88: PREFEITURA MUNICIPAL DE MARANGUAPE - EDUCAÇÃO | C88: 07.963.051/0001-68 | D88: CEARÁ | E88: (85) 3369-9101 | F88: coord.financ.educacao@gmail.com
A89: CÂMARA MUNICIPAL DE CAUCAIA | B89: CÂMARA MUNICIPAL DE CAUCAIA | C89: 72.324.635/0001-55 | D89: CEARÁ | E89: (85) 3342-1021 | F89: celutaf@yahoo.com.br, ronaldo_bandahesed@yahoo.com.br
A90: PREFEITURA MUNICIPAL DE ARACATI - DESENV ECON, TRAB E RENDA | B90: PREFEITURA MUNICIPAL DE ARACATI - DESENV ECON, TRAB E RENDA | C90: 07.684.756/0001-46 | D90: CEARÁ | F90: deyvid.qroz@gmail.com
A91: PREFEITURA MUNICIPAL DE CAUCAIA - TURISMO E CULTURA | B91: PREFEITURA MUNICIPAL DE CAUCAIA - TURISMO E CULTURA | C91: 07.616.162/0001-06 | D91: CEARÁ | F91: financeiro@setur.caucaia.ce.gov.br
A92: PREFEITURA MUNICIPAL DE CAUCAIA - ADMINISTRAÇÃO E RECURSOS HUMANOS | B92: PREFEITURA MUNICIPAL DE CAUCAIA - ADMINISTRAÇÃO E RECURSOS HUMANOS | C92: 07.616.162/0001-06 | D92: CEARÁ | E92: (85) 9.9762-0722 | F92: pgm@caucaia.ce.gov.br, secretaria.segov@caucaia.ce.gov.br, financeiro@sgg.caucaia.ce.gov.br, gilmaria@sead.caucaia.ce.gov.br, financeiro@pgm.caucaia.ce.gov.br
A93: PREFEITURA MUNICIPAL DE ARACATI - EDUCAÇÃO | B93: PREFEITURA MUNICIPAL DE ARACATI - EDUCAÇÃO | C93: 07.684.756/0001-46 | D93: CEARÁ | F93: atendimentoseplad@aracati.ce.gov.br, educacao@aracati.ce.gov.br, TITTO.SOL@aracati.ce.gov.br, pedro.henrique@aracati.ce.gov.br
A94: PREFEITURA MUNICIPAL DE CAUCAIA - AUTARQUIA MUNICIPAL DE TRÂNSITO | B94: PREFEITURA MUNICIPAL DE CAUCAIA - AUTARQUIA MUNICIPAL DE TRÂNSITO | C94: 05.577.643/0001-16 | D94: CEARÁ | E94: (85) 9.9762-0103 | F94: apoiofinanceiro@amt.caucaia.ce.gov.br
A95: PREFEITURA MUNICIPAL DE CANINDE - SECRETARIA DE ASSISTÊNCIA SOCIAL | B95: PREFEITURA MUNICIPAL DE CANINDE - SECRETARIA DE ASSISTÊNCIA SOCIAL | C95: 07.963.259/0001-87 | D95: CEARÁ | F95: acaosocialcaninde@yahoo.com.br
A96: PREFEITURA MUNICIPAL DE ARACATI - ESPORTE E LAZER | B96: PREFEITURA MUNICIPAL DE ARACATI - ESPORTE E LAZER | C96: 07.684.756/0001-46 | D96: CEARÁ | F96: beatriz.rocha@aracati.ce.gov.br, TITTO.SOL@aracati.ce.gov.br>, esporte@aracati.ce.gov.br
A97: PREFEITURA MUNICIPAL DE ARACATI - FINANÇAS | B97: PREFEITURA MUNICIPAL DE ARACATI - FINANÇAS | C97: 07.684.756/0001-46 | D97: CEARÁ | F97: karine.barbosa@aracati.ce.gov.br, TITTO.SOL@aracati.ce.gov.br, conasp.aracati@gmail.com
A98: PREFEITURA MUNICIPAL DE ARACATI - SEGURIDADE SOCIAL | B98: PREFEITURA MUNICIPAL DE ARACATI - SEGURIDADE SOCIAL | C98: 07.684.756/0001-46 | D98: CEARÁ | F98: gleiciene.costa@aracati.ce.gov.br, TITTO.SOL@aracati.ce.gov.br>, fmssaracati@aracati.ce.gov.br, gessika.costa@aracati.ce.gov.br
A99: PREFEITURA MUNICIPAL DE ARACATI - GABINETE DO PREFEITO | B99: PREFEITURA MUNICIPAL DE ARACATI - GABINETE DO PREFEITO | C99: 07.684.756/0001-46 | D99: CEARÁ | F99: TITTO.SOL@aracati.ce.gov.br, chefiadegabinete@aracati.ce.gov.br, karla.firmeza@aracati.ce.gov.br
A100: SEMIT | B100: SECRETARIA MUNICIPAL DE INFORMAÇÃO E TECNOLOGIA - SEMIT | C100: 06.307.102/0001-30 | D100: MARANHÃO | E100: (98) 99175 4895 | F100: gabinete@semit.saoluis.ma.gov.br
A101: PREFEITURA MUNICIPAL DE CAMOCIM - CONSERVAÇÃO E SERVIÇOS PUBLICOS | B101: PREFEITURA MUNICIPAL DE CAMOCIM - CONSERVAÇÃO E SERVIÇOS PUBLICOS | C101: 07.660.350/0001-23 | D101: CEARÁ | E101: (88) 3621-2123 / 3621-0024 | F101: semconsp@camocim.ce.gov.br
A102: PREFEITURA MUNICIPAL DE CAMOCIM - CULTURA | B102: PREFEITURA MUNICIPAL DE CAMOCIM - CULTURA | C102: 07.660.350/0001-23 | D102: CEARÁ | E102: (88) 3621-2123 / 3621-0024 | F102: ouvidoria@camocim.ce.gov.br comunicacao@camocim.ce.gov.br
A103: PREFEITURA MUNICIPAL DE CAMOCIM - DESENVOLVIMENTO SOCIAL E CIDADANIA | B103: PREFEITURA MUNICIPAL DE CAMOCIM - DESENVOLVIMENTO SOCIAL E CIDADANIA | C103: 07.660.350/0001-23 | D103: CEARÁ | E103: (88) 3621-2123 / 3621-0024 | F103: ouvidoria@camocim.ce.gov.br comunicacao@camocim.ce.gov.br
A104: PREFEITURA MUNICIPAL DE CAMOCIM - EDUCAÇÃO | B104: PREFEITURA MUNICIPAL DE CAMOCIM - EDUCAÇÃO | C104: 07.660.350/0001-23 | D104: CEARÁ | E104: (88) 3621-2123 / 3621-0024 | F104: ouvidoria@camocim.ce.gov.br comunicacao@camocim.ce.gov.br
A105: PREFEITURA MUNICIPAL DE CAMOCIM - ESPORTE E JUVENTUDE | B105: PREFEITURA MUNICIPAL DE CAMOCIM - ESPORTE E JUVENTUDE | C105: 07.660.350/0001-23 | D105: CEARÁ | E105: (88) 3621-2123 / 3621-0024 | F105: ouvidoria@camocim.ce.gov.br comunicacao@camocim.ce.gov.br
A106: PREFEITURA MUNICIPAL DE CAMOCIM - GABINETE DA PREFEITA | B106: PREFEITURA MUNICIPAL DE CAMOCIM - GABINETE DA PREFEITA | C106: 07.660.350/0001-23 | D106: CEARÁ | E106: (88) 3621-2123 / 3621-0024 | F106: ouvidoria@camocim.ce.gov.br comunicacao@camocim.ce.gov.br
A107: PREFEITURA MUNICIPAL DE CAMOCIM - GESTÃO ADMINISTRATIVA | B107: PREFEITURA MUNICIPAL DE CAMOCIM - GESTÃO ADMINISTRATIVA | C107: 07.660.350/0001-23 | D107: CEARÁ | E107: (88) 3621-2123 / 3621-0024 | F107: ouvidoria@camocim.ce.gov.br comunicacao@camocim.ce.gov.br
A108: PREFEITURA MUNICIPAL DE CAMOCIM - INFRAESTRUTURA | B108: PREFEITURA MUNICIPAL DE CAMOCIM - INFRAESTRUTURA | C108: 07.660.350/0001-23 | D108: CEARÁ | E108: (88) 3621-2123 / 3621-0024 | F108: ouvidoria@camocim.ce.gov.br comunicacao@camocim.ce.gov.br
A109: PREFEITURA MUNICIPAL DE CAMOCIM - PESCA, AGRICULTURA, RECURSOS HÍDRICOS E MEIO AMBIENTE | B109: PREFEITURA MUNICIPAL DE CAMOCIM - PESCA, AGRICULTURA, RECURSOS HÍDRICOS E MEIO AMBIENTE | C109: 07.660.350/0001-23 | D109: CEARÁ | E109: (88) 3621-2123 / 3621-0024 | F109: ouvidoria@camocim.ce.gov.br comunicacao@camocim.ce.gov.br
A110: PREFEITURA MUNICIPAL DE CAMOCIM - PROCURADORIA GERAL DO MUNICÍPIO | B110: PREFEITURA MUNICIPAL DE CAMOCIM - PROCURADORIA GERAL DO MUNICÍPIO | C110: 07.660.350/0001-23 | D110: CEARÁ | E110: (88) 3621-2123 / 3621-0024 | F110: ouvidoria@camocim.ce.gov.br comunicacao@camocim.ce.gov.br
A111: PREFEITURA MUNICIPAL DE CAMOCIM - SAÚDE | B111: PREFEITURA MUNICIPAL DE CAMOCIM - SAÚDE | C111: 07.660.350/0001-23 | D111: CEARÁ | E111: (88) 3621-2123 / 3621-0024 | F111: ouvidoria@camocim.ce.gov.br comunicacao@camocim.ce.gov.br
... A114: PREFEITURA MUNICIPAL DE CAUCAIA - CONTROLADORIA | B114: PREFEITURA MUNICIPAL DE CAUCAIA - CONTROLADORIA | C114: 07.616.162/0001-06 | D114: CEARÁ | E114: (85) 3342-8064 | F114: daf@cgm.caucaia.ce.gov.br, danilo.gurgel@cgm.caucaia.ce.gov.br, cgm@caucaia.ce.gov.br
A115: PREFEITURA MUNICIPAL DE CAUCAIA - DESENVOLVMENTO RURAL | B115: PREFEITURA MUNICIPAL DE CAUCAIA - DESENVOLVMENTO RURAL | C115: 07.616.162/0001-06 | D115: CEARÁ | F115: financeiro@sda.caucaia.ce.gov.br, financeiro@sdr.caucaia.ce.gov.br
A116: PREFEITURA MUNICIPAL DE CAUCAIA - DESENVOLVMENTO SOCIAL | B116: PREFEITURA MUNICIPAL DE CAUCAIA - DESENVOLVMENTO SOCIAL | C116: 07.616.162/0001-06 | D116: CEARÁ | F116: sas@caucaia.ce.gov.br
A117: PREFEITURA MUNICIPAL DE ARACATI - IQUAMA | B117: PREFEITURA MUNICIPAL DE ARACATI - IQUAMA | C117: 07.684.756/0001-46 | D117: CEARÁ | E117: (88) 3421-3428 | F117: ruanito.santos@aracati.ce.gov.br, TITTO.SOL@aracati.ce.gov.br>
A118: PREFEITURA MUNICIPAL DE ARACATI - MEIO AMBIENTE | B118: PREFEITURA MUNICIPAL DE ARACATI - MEIO AMBIENTE | C118: 07.684.756/0001-46 | D118: CEARÁ | E118: (88) 3421-3428 | F118: ruanito.santos@aracati.ce.gov.br, TITTO.SOL@aracati.ce.gov.br>
A119: PREFEITURA MUNICIPAL DE ARACATI - PLANEJAMENTO E ADMINISTRAÇÃO | B119: PREFEITURA MUNICIPAL DE ARACATI - PLANEJAMENTO E ADMINISTRAÇÃO | C119: 07.684.756/0001-46 | D119: CEARÁ | F119: TITTO.SOL@aracati.ce.gov.br>, atendimentoseplad@aracati.ce.gov.br, leia.convenios.aracati@gmail.com
A120: PREFEITURA MUNICIPAL DE ARACATI - PROCURADORIA | B120: PREFEITURA MUNICIPAL DE ARACATI - PROCURADORIA | C120: 07.684.756/0001-46 | D120: CEARÁ | F120: pgmaracati@aracati.ce.gov.br, georgia.moura@aracati.ce.gov.br>, TITTO.SOL@aracati.ce.gov.br>
A121: PREFEITURA MUNICIPAL DE CANINDE - CHEFIA DE GABINETE | B121: PREFEITURA MUNICIPAL DE CANINDE - CHEFIA DE GABINETE | C121: 07.963.259/0001-87 | D121: CEARÁ | F121: chefiadegabinetecaninde@gmail.com
A122: PREFEITURA MUNICIPAL DE CANINDE - CONTROLADORIA GERAL DO MUNICÍPIO | B122: PREFEITURA MUNICIPAL DE CANINDE - CONTROLADORIA GERAL DO MUNICÍPIO | C122: 07.963.259/0001-87 | D122: CEARÁ | F122: controladoriainternacaninde@gmail.com
A123: PREFEITURA MUNICIPAL DE CANINDE - SECRETARIA DE DESENVOLVIMENTO ECONÔMICO E TURISMO | B123: PREFEITURA MUNICIPAL DE CANINDE - SECRETARIA DE DESENVOLVIMENTO ECONÔMICO E TURISMO | C123: 07.963.259/0001-87 | D123: CEARÁ | F123: setuc.caninde@gmail.com
A124: PREFEITURA MUNICIPAL DE CANINDE - SECRETARIA MUNICIPAL DE DESENVOLVIMENTO URBANO, INFRAESTRUTURA E SERVIÇOS PÚBLICOS | B124: PREFEITURA MUNICIPAL DE CANINDE - SECRETARIA MUNICIPAL DE DESENVOLVIMENTO URBANO, INFRAESTRUTURA E SERVIÇOS PÚBLICOS | C124: 07.963.259/0001-87 | D124: CEARÁ | F124: seinfra.canindece@gmail.com
A125: PREFEITURA MUNICIPAL DE CANINDE - FUNDAÇÃO DE ESPORTE, CULTURA E PATRIMÔNIO | B125: PREFEITURA MUNICIPAL DE CANINDE - FUNDAÇÃO DE ESPORTE, CULTURA E PATRIMÔNIO | C125: 07.963.259/0001-87 | D125: CEARÁ | F125: contatofuntec@gmail.com
A126: PREFEITURA MUNICIPAL DE CANINDE - SECRETARIA DE PLANEJAMENTO, ADMINISTRAÇÃO E FINANÇAS | B126: PREFEITURA MUNICIPAL DE CANINDE - SECRETARIA DE PLANEJAMENTO, ADMINISTRAÇÃO E FINANÇAS | C126: 07.963.259/0001-87 | D126: CEARÁ | F126: secfinancascaninde@gmail.com
A127: PREFEITURA MUNICIPAL DE CANINDE - PROCURADORIA GERAL DO MUNICÍPIO | B127: PREFEITURA MUNICIPAL DE CANINDE - PROCURADORIA GERAL DO MUNICÍPIO | C127: 07.963.259/0001-87 | D127: CEARÁ | F127: procuradoria@caninde.ce.gov.br
A128: PREFEITURA MUNICIPAL DE CANINDE - SECRETARIA DE SAÚDE | B128: PREFEITURA MUNICIPAL DE CANINDE - SECRETARIA DE SAÚDE | C128: 07.963.259/0001-87 | D128: CEARÁ | F128: secretariadasaude2017@gmail.com
A129: PREFEITURA MUNICIPAL DE CANINDE - SECRETARIA DE SEGURANÇA PÚBLICA E TRÂNSITO | B129: PREFEITURA MUNICIPAL DE CANINDE - SECRETARIA DE SEGURANÇA PÚBLICA E TRÂNSITO | C129: 07.963.259/0001-87 | D129: CEARÁ | F129: smtscaninde@gmail.com
A130: PREFEITURA MUNICIPAL DE ARACATI - SAÚDE | B130: PREFEITURA MUNICIPAL DE ARACATI - SAÚDE | C130: 07.684.756/0001-46 | D130: CEARÁ | F130: TITTO.SOL@aracati.ce.gov.br, RAQUEL.SILVA@aracati.ce.gov.br, fsaudearacati@aracati.ce.gov.br, acemira.ribeiro@aracati.ce.gov.br
... A133: PREFEITURA MUNICIPAL DE ARACATI - DESENVOLVIMENTO SOCIAL | B133: PREFEITURA MUNICIPAL DE ARACATI - DESENVOLVIMENTO SOCIAL | C133: 07.684.756/0001-46 | D133: CEARÁ | F133: assistenciasocialfinanceiro4@gmail.com, assistenciasocialfinanceiro@gmail.com, TITTO.SOL@aracati.ce.gov.br, daniela.caretta@aracati.ce.gov.br
A134: PREFEITURA MUNICIPAL DE CAUCAIA - SECRETARIA DE GESTÃO E GOVERNO | B134: PREFEITURA MUNICIPAL DE CAUCAIA - SECRETARIA DE GESTÃO E GOVERNO | C134: 07.616.162/0001-06 | D134: CEARÁ | E134: (85) 3342-4410 | F134: ascom@caucaia.ce.gov.br
A135: ISGH | B135: INSTITUTO DE SAÚDE E GESTÃO HOSPITALAR | C135: 05.268.526/0001-70 | D135: CEARÁ | E135: (85) 3195-2722 | F135: erick.epr@isgh.org.br, contratos@isgh.org.br, luidgi.lmr@isgh.org.br
A136: ISGH | B136: INSTITUTO DE SAÚDE E GESTÃO HOSPITALAR | C136: 05.268.526/0001-70 | D136: CEARÁ | E136: (85) 3195-2722 | F136: erick.epr@isgh.org.br, contratos@isgh.org.br, luidgi.lmr@isgh.org.br
A137: ISGH | B137: INSTITUTO DE SAÚDE E GESTÃO HOSPITALAR | C137: 05.268.526/0001-70 | D137: CEARÁ | E137: (85) 3195-2722 | F137: erick.epr@isgh.org.br, contratos@isgh.org.br, luidgi.lmr@isgh.org.br
A138: ISGH | B138: INSTITUTO DE SAÚDE E GESTÃO HOSPITALAR | C138: 05.268.526/0001-70 | D138: CEARÁ | E138: (85) 3195-2722 | F138: erick.epr@isgh.org.br, contratos@isgh.org.br, luidgi.lmr@isgh.org.br
A139: ISGH | B139: INSTITUTO DE SAÚDE E GESTÃO HOSPITALAR | C139: 05.268.526/0001-70 | D139: CEARÁ | E139: (85) 3195-2722 | F139: erick.epr@isgh.org.br, contratos@isgh.org.br, luidgi.lmr@isgh.org.br
A140: PREFEITURA MUNICIPAL DE CAUCAIA - SECRETARIA MUNICIPAL DE PLANEJAMENTO URBANO E AMBIENTAL | B140: PREFEITURA MUNICIPAL DE CAUCAIA - SECRETARIA MUNICIPAL DE PLANEJAMENTO URBANO E AMBIENTAL | C140: 07.616.162/0001-06 | D140: CEARÁ | F140: administrativo.seplam@caucaia.ce.gov.br
A141: PREFEITURA MUNICIPAL DE CAUCAIA - SECRETARIA MUNICIPAL DE INFRAESTRUTURA | B141: PREFEITURA MUNICIPAL DE CAUCAIA - SECRETARIA MUNICIPAL DE INFRAESTRUTURA | C141: 07.616.162/0001-06 | D141: CEARÁ | F141: administracao@seinfra.caucaia.ce.gov.br>, seinfra@caucaia.ce.gov.br, eng.robson.caucaia@gmail.com
A142: PREFEITURA MUNICIPAL DE CAUCAIA - PROCURADORIA-GERAL DO MUNICÍPIO | B142: PREFEITURA MUNICIPAL DE CAUCAIA - PROCURADORIA-GERAL DO MUNICÍPIO | C142: 07.616.162/0001-06 | D142: CEARÁ | F142: pgm@caucaia.ce.gov.br, secretaria.segov@caucaia.ce.gov.br, financeiro@sgg.caucaia.ce.gov.br, gilmaria@sead.caucaia.ce.gov.br, FINANCEIRO@pgm.caucaia.ce.gov.br
A143: PREFEITURA MUNICIPAL DE CAUCAIA - SECRETARIA MUNICIPAL DE PATRIMÔNIO E TRANSPORTE | B143: PREFEITURA MUNICIPAL DE CAUCAIA - SECRETARIA MUNICIPAL DE PATRIMÔNIO E TRANSPORTE | C143: 07.616.162/0001-06 | D143: CEARÁ | F143: financeiro@spsp.caucaia.ce.gov.br
A144: PREFEITURA MUNICIPAL DE CAUCAIA - INSTITUTO DE PREVIDÊNCIA DO MUNICÍPIO | B144: PREFEITURA MUNICIPAL DE CAUCAIA - INSTITUTO DE PREVIDÊNCIA DO MUNICÍPIO | C144: 07.616.162/0001-06 | D144: CEARÁ | F144: financeiro@ipm.caucaia.ce.gov.br
A145: PREFEITURA MUNICIPAL DE CAUCAIA - INSTITUTO DO MEIO AMBIENTE DO MUNICÍPIO | B145: PREFEITURA MUNICIPAL DE CAUCAIA - INSTITUTO DO MEIO AMBIENTE DO MUNICÍPIO | C145: 07.616.162/0001-06 | D145: CEARÁ | F145: financeiro@imac.caucaia.ce.gov.br
A146: PREFEITURA MUNICIPAL DE CAUCAIA - GABINETE DO VICE PREFEITO | B146: PREFEITURA MUNICIPAL DE CAUCAIA - GABINETE DO VICE PREFEITO | C146: 07.616.162/0001-06 | D146: CEARÁ | F146: gabinete.vice@caucaia.ce.gov.br>, beatriz.gabvice@caucaia.ce.gov.br>
A147: PREFEITURA MUNICIPAL DE CAUCAIA - GABINETE DO PREFEITO | B147: PREFEITURA MUNICIPAL DE CAUCAIA - GABINETE DO PREFEITO | C147: 07.616.162/0001-06 | D147: CEARÁ | F147: chefedegabinete@gabinete.caucaia.ce.gov.br, financeiro@gabinete.caucaia.ce.gov.br>
A148: PREFEITURA MUNICIPAL DE CAUCAIA - SECRETARIA MUNICIPAL DE FINANÇAS, PLANEJAMENTO E ORÇAMENTO | B148: PREFEITURA MUNICIPAL DE CAUCAIA - SECRETARIA MUNICIPAL DE FINANÇAS, PLANEJAMENTO E ORÇAMENTO | C148: 07.616.162/0001-06 | D148: CEARÁ | F148: coafi@sefin.caucaia.ce.gov.br, angela.amancio@sefin.caucaia.ce.gov.br
A149: PREFEITURA MUNICIPAL DE CAUCAIA - SECRETARIA MUNICIPAL DE ESPORTE E JUVENTUDE | B149: PREFEITURA MUNICIPAL DE CAUCAIA - SECRETARIA MUNICIPAL DE ESPORTE E JUVENTUDE | C149: 07.616.162/0001-06 | D149: CEARÁ | F149: sejuv@caucaia.ce.gov.br, gaf@sejuv.caucaia.ce.gov.br
...

Sheet CONTRATOS
A1: ID | B1: APELIDO_CONTRATO | C1: NUMERO_CONTRATO | D1: ANTIGO_CONTRATO | E1: TIPO_CONTRATO | F1: STATUS_CONTRATO | G1: CONTRATADO | H1: CONTRATANTE | I1: OBJETO_DO_CONTRATO
A4: 3 | B4: ALECE | C4: 97-2025 | E4: LICITAÇÃO | F4: EM ANDAMENTO | G4: ALUCOM | H4: ASSEMBLEIA LEGISLATIVA DO ESTADO DO CEARÁ | I4: O objeto do presente instrumento é LOCAGOES DE MAQUINARIOS DE INFORMATICA COM INSTALAGAO, MANUTENGAOQ, SUPORTE E GESTAO DO AMBIENTE DE TI, E EXECUGAO , CONTINUADA DE ATIVIDADES REFERENTES A INCIDENTES E SOLICITAGOES DE SERVIGOS, COM SUPORTE, ASSISTENCIA TECNICA E DISPONIBILIZACAO DE CENTRAL DE SERVICOS, nas condições estabelecidas neste contrato e no Termo de Referéncia do edital e na proposta do CONTRATADO.
A5: 4 | B5: 10a REGIAO MILITAR | C5: 002/2024 | E5: LICITAÇÃO | F5: EM ANDAMENTO | G5: ALUCOM | H5: COMANDO DA 10a REGIAO MILITAR | I5: .O objeto do presente instrumento é a Contrataçao de soluçao de tecnologia da informaçao e comunicaçao de serviço de Outsourcing de impressao, por Sistema de Registro de Preços (SRP), com fornecimento de suprimentos, peças de reposiçao e manutençao, para equipamentos alocados nos diversos setores, do Comando da 10a Regiao Militar, CS/10 e SRO/10, que serao prestados nas condiçoes estabelecidas no Termo de Referencia, anexo do Edital
A6: 5 | B6: CMFOR | C6: 006/2023-SALC/CMF | E6: LICITAÇÃO | F6: EM ANDAMENTO | G6: ALUCOM | H6: COLEGIO MILITAR DE FORTALEZA | I6: O objeto do presente instrumento é a escolha da proposta mais vantajosa para a contratação de solução de tecnologia da informação e comunicação, de serviços comuns e continuados sem dedicação exclusiva de mão-de-obra, de impressão corporativa - outsourcing de impressão - modalidade franquia mensal de páginas mais excedente, sem fornecimento de papel; com fornecimento e disponibilidade, nas dependências da CONTRATANTE, de equipamentos de impressão corporativa em regime de comodato, para atender ao Colégio Militar de Fortaleza; conforme condições, quantidades e exigências estabelecidas neste instrumento e seus anexos.
A7: 6 | B7: ESCOLA DE APRENDIZEM DE MARINHEIROS DO CEARÁ | C7: 83601/2024-007/00 | E7: LICITAÇÃO | F7: EM ANDAMENTO | G7: ALUCOM | H7: ESCOLA DE APRENDIZEM DE MARINHEIROS DO CEARÁ | I7: O objeto do presente instrumento é a contratação de solução de tecnologia da informação e comunicação de serviço de Outsourcing de impressão, por Sistema de Registro de Preços (SRP), com fornecimento de suprimentos, peças de reposição e manutenção, para equipamentos alocados nos diversos setores da Escola de Aprendizes-Marinheiros do Ceará (EAMCE), que serão
A8: 7 | B8: UFC | C8: 08-2024 | E8: LICITAÇÃO | F8: EM ANDAMENTO | G8: ALUCOM | H8: UNIVERSIDADE FEDERAL DO CEARÁ | I8: O objeto do presente instrumento é a contratação de solução de tecnologia da informação e comunicação de de serviço de Outsourcing de impressão, por Sistema de Registro de Preços (SRP), com fornecimento de suprimentos, peças de reposição e manutenção, para equipamentos alocados nos diversos setores, nos Campi de Fortaleza e do interior do estado do Ceará, que serão prestados nas condições estabelecidas no Termo de Referência, anexo do Edital.
A9: 8 | B9: IFCE CAMOCIM | C9: 04/2024 | E9: LICITAÇÃO | F9: EM ANDAMENTO | G9: ALUCOM | H9: INSTITUTO FEDERAL DE EDUCAÇÃO E TECNOLOGIA - IFCE CAMOCIM | I9: O objeto do presente instrumento é a contratação de solução de tecnologia da informação e comunicação de serviço de outsourcing de impressão, com fornecimento de suprimentos, peças de reposição e manutenção, para equipamentos alocados no Instituto Federal de Educação, Ciência e Tecnologia do Ceará - campus Camocim, que serão prestados nas condições estabelecidas no Termo de Referência, anexo do Edital.
A10: 9 | B10: IFCE CAUCAIA | C10: 03-2024 | E10: LICITAÇÃO | F10: EM ANDAMENTO | G10: ALUCOM | H10: INSTITUTO FEDERAL DE EDUCAÇÃO E TECNOLOGIA - IFCE CAUCAIA | I10: O objeto do presente instrumento é a contratação de solução de tecnologia da informação e comunicação de serviço de Outsourcing de impressão, por Sistema de Registro de Preços (SRP), com fornecimento de suprimentos, peças de reposição e manutenção, para equipamentos alocados no IFCE Campus Caucaia, que serão prestados nas condições estabelecidas no Termo de Referência, anexo do Edital.
A11: 10 | B11: IFCE ITAPIPOCA | C11: 04/2024 | E11: LICITAÇÃO | F11: EM ANDAMENTO | G11: ALUCOM | H11: INSTITUTO FEDERAL DE EDUCAÇÃO E TECNOLOGIA - IFCE ITAPIPOCA | I11: O objeto do presente instrumento é a contratação de solução de tecnologia da informação e comunicação de serviço de Outsourcing de impressão, por Sistema de Registro de Preços (SRP), com fornecimento de suprimentos, peças de reposição e manutenção, para equipamentos alocados no Instituto Federal de Educação, Ciência e Tecnologia do Ceará - IFCE/Campus Itapipoca, que serão prestados nas condições estabelecidas no Termo de Referência anexo ao Edital do PregãoEletrônico Nº 52/2023.
A12: 11 | B12: IFCE PARACURU | C12: 02/2024 | E12: LICITAÇÃO | F12: EM ANDAMENTO | G12: ALUCOM | H12: INSTITUTO FEDERAL DE EDUCAÇÃO E TECNOLOGIA - IFCE PARACURU | I12: O objeto do presente instrumento é a contratação de solução de tecnologia da informação e comunicação de serviço de Outsourcing de impressão, por Sistema de Registro de Preços (SRP), com fornecimento de suprimentos, peças de reposição e manutenção, para equipamentos alocados nos diversos setores, no campus Paracuru
A13: 12 | B13: IFCE JUAZEIRO DO NORTE | C13: 05/2024 | E13: LICITAÇÃO | F13: EM ANDAMENTO | G13: ALUCOM | H13: INSTITUTO FEDERAL DE EDUCAÇÃO E TECNOLOGIA - IFCE JUAZEIRO DO NORTE | I13: O objeto do presente instrumento é a contratação de solução de tecnologia da informação e comunicação de serviço de Outsourcing de impressão, por Sistema de Registro de Preços (SRP), com fornecimento de suprimentos, peças de reposição e manutenção, para equipamentos alocados no Instituto Federal de Educação, Ciência e Tecnologia do Ceará (IFCE) - campus Juazeiro do Norte, que serão prestados nas condições estabelecidas no Termo de Referência anexo ao Edital do Pregão Eletrônico nº 52/2023.
A14: 13 | B14: MINISTÉRIO DA AGRICULTURA E PECUÁRIA/SUPERINTENDÊNCIA FEDERAL DE AGRICULTURA E PECUÁRIA NO PARANÁ (SFA-PR/MAPA) | C14: 10/2024 | E14: LICITAÇÃO | F14: EM ANDAMENTO | G14: ALUCOM | H14: MINISTÉRIO DA AGRICULTURA E PECUÁRIA/SUPERINTENDÊNCIA FEDERAL DE AGRICULTURA E PECUÁRIA NO PARANÁ (SFA-PR/MAPA) | I14: O objeto do presente instrumento é a Contratação de solução de tecnologia da informação e comunicação de outsourcing de impressão e digitalizaçãona modalidade franquia de página mais excedente, com fornecimento de equipamentos, soware de gerenciamento de impressão efe vamente realizadas,manutenção preven va e corre va dos equipamentos com subs tuição de peças, componentes e materiais u lizados na manutenção e fornecimento de insumosoriginais, exceto papel, para atender as necessidades de impressão e digitalização da Superintendência Federal de Agricultura e Pecuária no Paraná - SFA-PR, nascondições estabelecidas no Termo de Referência.
A15: 14 | B15: CAPITANIA DOS PORTOS DE SERGIPE | C15: 82320/202461/00 | E15: LICITAÇÃO | F15: EM ANDAMENTO | G15: ALUCOM | H15: CAPITANIA DOS PORTOS DE SERGIPE | I15: O objeto do presente instrumento é a contratação de empresa especializada na prestaçãode serviço de Outsourcing de impressão, por Sistema de Registro de Preços (SRP), comfornecimento de suprimentos, peças de reposição e manutenção, para equipamentos queserão alocados na Capitania dos Portos de Sergipe
... A38: 37 | B38: SEGER | C38: 026-2022 - SEGER | E38: LICITAÇÃO | F38: EM ANDAMENTO | G38: ALUCOM | H38: SECRETARIA MUNICIPAL DA GESTÃO REGIONAL - SEGER | I38: O presente contrato tem como fundamento a adesão ao Edital do Pregão Eletrônico tombado sob o n° 2021.08.02.01 em conformidade com a Lei Federal N° 8.666/93 - Lei das Licitações Públicas, c/c os termos da Lei Federal n° 10.520, de 17/07/2002., os preceitos do direito público, com suas alterações e, ainda, outras leis especiais necessárias ao cumprimento de seu objeto.
A39: 38 | B39: CEGOR | C39: Nº 26/2022 - SEGER – SUB-ROGADO CEGOR | D39: 37 | E39: SUB-ROGAÇÃO | F39: EM ANDAMENTO | G39: ALUCOM | H39: COORDENADORIA ESPECIAL DE APOIO À GOVERNANÇA DAS REGIONAIS – CEGOR | I39: O presente contrato tem como fundamento a adesão ao Edital do Pregão Eletrônico tombado sob o n° 2021.08.02.01 em conformidade com a Lei Federal N° 8.666/93 - Lei das Licitações Públicas, c/c os termos da Lei Federal n° 10.520, de 17/07/2002., os preceitos do direito público, com suas alterações e, ainda, outras leis especiais necessárias ao cumprimento de seu objeto.
A40: 39 | B40: DETRAN MA | C40: 06/2024-DETRAN/MA | E40: LICITAÇÃO | F40: EM ANDAMENTO | G40: ALUCOM | H40: DETRAN | I40: Locação de equipamentos de informática (desktops, notebooks, no breaks, entre outros) com instalação, manutenção, suporte e gestão do ambiente de TI, e execução continuada de atividades relativas a incidentes e solicitações de serviços, incluindo suporte, assistência técnica e disponibilização de central de serviços.
A41: 40 | B41: IPAM | C41: 0014/2022 | E41: LICITAÇÃO | F41: EM ANDAMENTO | G41: ALUCOM | H41: IPAM | I41: Contratação de empresa especializada na prestação de serviços, executados de forma contínua, de locação e manutenção preventiva e corretiva de equipamentos de informática.
A42: 41 | B42: PCDF | C42: 11/2025 | E42: LICITAÇÃO | F42: EM ANDAMENTO | G42: ALUCOM | H42: POLICIA CIVIL DO DISTRITO FEDERAL | I42: O objeto do presente instrumento é a contratação de solução de tecnologia da informação e comunicação por meio da prestação continuada de serviços de impressão, cópia e digitalização para a PCDF, na modalidade Outsourcing de Impressão, pelo prazo de 60 meses, nas condições estabelecidas no Termo de Referência.
A43: 42 | B43: HEMOCENTRO PB | C43: 0096-2024 | E43: LICITAÇÃO | F43: EM ANDAMENTO | G43: ALUCOM | H43: SECRETARIA DE ESTADO DA SAÚDE - HEMOCENTRO | I43: Contratação de EMPRESA ESPECIALIZADA EM PRESTAÇÃODE SERVIÇO DE OUTSOURCING DE IMPRESSÃO, conforme especificações e quantitativos estabelecidos no Edital do Pregão identificado no preâmbulo e na proposta vencedora.
A44: 43 | B44: ALEMA | C44: 49/2023 | E44: LICITAÇÃO | F44: EM ANDAMENTO | G44: ALUCOM | H44: ASSEMBLEIA LEGISLATIVA DO ESTADO DO MARANHÃO | I44: locação de equipamentos de informática (desktops, notebooks, no breaks, dentre outros) com instalação, manutenção, suporte e gestão do ambiente de TI, e execução continuada de atividades referentes à incidentes e solicitações de serviços, com suporte, assistência técnica e disponibilização de central de serviços, visando futuras contratações pela Assembleia Legislativa do Estado do Maranhão
A45: 44 | B45: SEAP-PB | C45: 0025/2024 | E45: LICITAÇÃO | F45: EM ANDAMENTO | G45: ALUCOM | H45: SECRETARIA DE ESTADO DA ADMINISTRAÇÃO PENITENCIÁRIA – SEAP-PB | I45: Contratação de serviços de outsurcing de impressão, em conformidade com as especificações, exigências e quantitativos, estabelecidos no Termo de Referência.
A46: 45 | B46: PCPB | C46: 0005/2024/PCPB | E46: LICITAÇÃO | F46: EM ANDAMENTO | G46: ALUCOM | H46: POLICIA CIVIL DA PARAIBA | I46: O objeto do presente instrumento é a contratação de serviços de outsourcing de impressão e digitalização corporativa, que serão prestados nas condições estabelecidas no Termo de Referência, anexo do Edital, visando atender às necessidades da Polícia Civil Do Estado Da Paraíba
A47: 46 | B47: SETUR | C47: nº 2024.000006.37101.01 | E47: LICITAÇÃO | F47: EM ANDAMENTO | G47: ALUCOM | H47: SETUR | I47: O presente Contrato tem por objeto a prestação de serviços de serviço de outsourcing de impressão, compreendendo disponibilização de equipamento(s) reprográfic (s)multifuncional(is) monocromático(s), assistência técnica, fornecimento de peças e demais insumos consumíveis
A48: 47 | B48: CITINOVA | C48: 005/2022 | E48: LICITAÇÃO | F48: EM ANDAMENTO | G48: ALUCOM | H48: FUNDACAO CITINOVA | I48: locações de equipamentos de informática, com suporte, assistência técnica e manutenção preventiva e corretiva in-loco, bem como atuação nos processos de gerenciamento de serviços, com base em melhores práticas definidas pela ITIL – Information Technology Infrastructure Library®, cujos serviços serão avaliados através de acordos de nível de serviço, para atender às necessidades administrativas da Fundação de Ciência, Tecnologia e Inovação – CITINOVA
A49: 48 | B49: RESENDE / SMA | C49: 17/2024 | E49: LICITAÇÃO | F49: EM ANDAMENTO | G49: ALUCOM | H49: RESENDE - SECRETARIA MUNICIPAL DE ADMINISTRAÇÃO / SMA | I49: CONTRATAÇÃO DE EMPRESA ESPECIALIZADA NO FORNECIMENTO DE SOLUÇÃO CONTINUADA SERVIÇOS OUTSOURCING (IMPRESSÃO E CÓPIA), INTEGRADA A SISTEMAS CORPORATIVOS E À REDE DA PREFEITURA MUNICIPAL DE RESENDE, COMPREENDENDO A CESSÃO DE DIREITO DE USO DE EQUIPAMENTOS NOVOS E DE PRIMEIRO USO (FRANQUIA MENSAL DE PÁGINAS MAIS EXCEDENTE), INCLUINDO A PRESTAÇÃO DE SERVIÇOS DE MANUTENÇÃO PREVENTIVA E CORRETIVA, FORNECIMENTO DE PEÇAS E CONSUMÍVEIS NECESSÁRIOS (EXCETO PAPEL), ASSIM COMO SISTEMA DE GESTÃO, CONTROLE E OPERACIONALIZAÇÃO DA SOLUÇÃO, VISANDO ATENDER ÀS NECESSIDADES DA PREFEITURA MUNICIPAL DE RESENDE, POR MEIO DA SECRETARIA MUNICIPAL DE ADMINISTRAÇÃO- SMA/ SUMTI, PELO PERÍODO DE 12 MESES
A50: 49 | B50: SECRETARIA MUNICIPAL DE SEGURANÇA COM CIDADANIA−SEMUSC - 007-2022 | C50: 007-2022 | E50: LICITAÇÃO | F50: EM ANDAMENTO | G50: ALUCOM | H50: SECRETARIA MUNICIPAL DE SEGURANÇA COM CIDADANIA−SEMUSC | I50: O objeto do contrato nº 007/2022-SEMUSC consiste na contratação de uma empresa especializada para a prestação de serviços de locação e manutenção de equipamentos de informática
A51: 50 | B51: CAMARA DE HORTOLANDIA | C51: 29-2023 | E51: LICITAÇÃO | F51: EM ANDAMENTO | G51: ALUCOM | H51: CAMARA MUNICIPAL DE HORTOLÂNDIA | I51: O objeto do presente instrumento é a contratação de serviço contínuo especializado de Impressão, cópias e digitalização corporativa, por meio de sistema Outsourcing,na modalidade de franquia de páginas mais excedente, incluindo fornecimento de equipamentos, manutenção preventiva e corretiva dos equipamentos, com fornecimento de peças e componentes originais, suprimentos, componentes, papel, softwares de gerenciamento e controle (bilhetagem) de cópias e impressões, suporte técnico remoto durante ohorário de expediente da Contratante e com visita técnica diária de segunda a sexta-feira,conforme especificação no Termo de Referência - Retificado, constante do Anexo Únicodeste Contrato.
... A86: 86 | B86: HOSPITAL MUNICIPAL DR. AUGEU BRAGA HERBSTER | C86: 09.25.03.03.001 | E86: LICITAÇÃO | F86: EM ANDAMENTO | G86: ALUCOM | H86: MARANGUAPE - PREFEITURA MUNICIPAL DE MARANGUAPE | I86: Locações de equipamentos de informática, com suporte, assistência técnica e manutenção preventiva e corretiva in-loco de interesse do Hospital Municipal Dr. Augeu Braga Herbster
A87: 87 | B87: PREFEITURA MUNICIPAL DE MARANGUAPE - AGRICULTURA, PESCA E RECURSOS HÍDRICOS | C87: 11.25.03.03.001 | E87: LICITAÇÃO | F87: EM ANDAMENTO | G87: ALUCOM | H87: MARANGUAPE - PREFEITURA MUNICIPAL DE MARANGUAPE
A88: 88 | B88: PREFEITURA MUNICIPAL DE MARANGUAPE - EDUCAÇÃO | C88: 04.25.03.03.001 | E88: LICITAÇÃO | F88: EM ANDAMENTO | G88: ALUCOM | H88: MARANGUAPE - PREFEITURA MUNICIPAL DE MARANGUAPE | I88: Locações de equipamentos de informática (20 notebooks e 70 micro desktops), incluindo suporte, assistência técnica e manutenção preventiva e corretiva in-loco para a Secretaria de Educação do Município de Maranguape-CE
A89: 89 | B89: CÂMARA MUNICIPAL DE CAUCAIA | C89: 042/2022 | E89: LICITAÇÃO | F89: EM ANDAMENTO | G89: ALUCOM | H89: CÂMARA MUNICIPAL DE CAUCAIA | I89: CONTRATAÇÕES DE SERVIÇOS DE LOCAÇÕES DE EQUIPAMENTOS DE INFORMÁTICA, COM SUPORTE, ASSISTÊNCIA TÉCNICA E MANUTENÇÃO PREVENTIVA E CORRETIVA IN-LOCO, JUNTO A CÂMARA MUNICIPAL DE CAUCAIA-CE, tudo conforme especificações contidas no Projeto Básico/Termo de Referência, constante do Anexo I do Edital.
A90: 90 | B90: PREFEITURA MUNICIPAL DE ARACATI - DESENV ECON, TRAB E RENDA | C90: 2022041303 | E90: LICITAÇÃO | F90: EM ANDAMENTO | G90: ALUCOM | H90: PREFEITURA MUNICIPAL DE ARACATI - DESENV ECON, TRAB E RENDA | I90: CONTRATAÇÃO DE SERVIÇOS DE LOCAÇÃO DE EQUIPAMENTOS DE INFORMÁTICA, COM SUPORTE, ASSISTÊNCIA TÉCNICA E MANUTENÇÃO PREVENTIVA E CORRETIVA IN LOCO, BEM COMO ATUAÇÃO NOS PROCESSOS DE GERENCIAMENTO DE SERVIÇOS.
A91: 91 | B91: PREFEITURA MUNICIPAL DE CAUCAIA - TURISMO E CULTURA | C91: 2021.08.02.01-11 | E91: LICITAÇÃO | F91: EM ANDAMENTO | G91: ALUCOM | H91: PREFEITURA MUNICIPAL DE CAUCAIA - TURISMO E CULTURA | I91: CONTRATAÇÃO DE SERVIÇOS DE LOCAÇÕES DE EQUIPAMENTOS DE INFORMÁTICA, COM SUPORTE, ASSISTÊNCIA TÉCNICA E MANUTENÇÃO PREVENTIVA E CORRETIVA IN-LOCO, BEM COMO ATUAÇÃO NOS PROCESSOS DE GERENCIAMENTO DE SERVIÇOS, COM BASE EM MELHORES PRÁTICAS DEFINIDAS PELA ITIL-INFORMATION TECHNOLOGY INFRASTRUCTURE LIBRARY, CUJOS SERVIÇOS SERÃO AVALIADOS ATRAVÉS DE ACORDOS DE NÍVEL DE SERVIÇO, PARA ATENDER AS NECESSIDADES DA SECRETARIA MUNICIPAL DE TURISMO E CULTURA DO MUNICÍPIO DE CAUCAIA-CE
A92: 92 | B92: PREFEITURA MUNICIPAL DE CAUCAIA - ADMINISTRAÇÃO E RECURSOS HUMANOS | C92: 2021.08.02.01-01 | E92: LICITAÇÃO | F92: EM ANDAMENTO | G92: ALUCOM | H92: PREFEITURA MUNICIPAL DE CAUCAIA - ADMINISTRAÇÃO E RECURSOS HUMANOS | I92: CONTRATAÇÃO DE SERVIÇOS DE LOCAÇÕES DE EQUIPAMENTOS DE INFORMÁTICA, COM SUPORTE, ASSISTÊNCIA TÉCNICA E MANUTENÇÃO PREVENTIVA E CORRETIVA IN-LOCO, BEM COMO ATUAÇÃO NOS PROCESSOS DE GERENCIAMENTO DE SERVIÇOS, COM BASE EM MELHORES PRÁTICAS DEFINIDAS PELA ITIL-INFORMATION TECHNOLOGY INFRASTRUCTURE LIBRARY, CUJOS SERVIÇOS SERÃO AVALIADOS ATRAVÉS DE ACORDOS DE NÍVEL DE SERVIÇO, PARA ATENDER AS NECESSIDADES DA SECRETARIA MUNICIPAL DE TURISMO E CULTURA DO MUNICÍPIO DE CAUCAIA-CE
A93: 93 | B93: PREFEITURA MUNICIPAL DE ARACATI - EDUCAÇÃO | C93: 20220413019 | E93: LICITAÇÃO | F93: EM ANDAMENTO | G93: ALUCOM | H93: PREFEITURA MUNICIPAL DE ARACATI - EDUCAÇÃO | I93: CONTRATAÇÃO DE SERVIÇOS DE LOCAÇÃO DE EQUIPAMENTOS DE INFORMÁTICA, COM SUPORTE, ASSISTÊNCIA TÉCNICA E MANUTENÇÃO PREVENTIVA E CORRETIVA IN LOCO, BEM COMO ATUAÇÃO NOS PROCESSOS DE GERENCIAMENTO DE SERVIÇOS.
A94: 94 | B94: PREFEITURA MUNICIPAL DE CAUCAIA - AUTARQUIA MUNICIPAL DE TRÂNSITO | C94: 2021.08.02.01-19 | E94: LICITAÇÃO | F94: EM ANDAMENTO | G94: ALUCOM | H94: PREFEITURA MUNICIPAL DE CAUCAIA - AUTARQUIA MUNICIPAL DE TRÂNSITO | I94: CONTRATAÇÃO DE SERVIÇOS DE LOCAÇÕES DE EQUIPAMENTOS DE INFORMÁTICA, COM SUPORTE, ASSISTÊNCIA TÉCNICA E MANUTENÇÃO PREVENTIVA E CORRETIVA IN-LOCO, BEM COMO ATUAÇÃO NOS PROCESSOS DE GERENCIAMENTO DE SERVIÇOS, COM BASE EM MELHORES PRÁTICAS DEFINIDAS PELA ITIL-INFORMATION TECHNOLOGY INFRASTRUCTURE LIBRARY, CUJOS SERVIÇOS SERÃO AVALIADOS ATRAVÉS DE ACORDOS DE NÍVEL DE SERVIÇO, PARA ATENDER AS NECESSIDADES DA SECRETARIA MUNICIPAL DE TURISMO E CULTURA DO MUNICÍPIO DE CAUCAIA-CE
A95: 95 | B95: PREFEITURA MUNICIPAL DE CANINDE - SECRETARIA DE ASSISTÊNCIA SOCIAL | C95: 20230929012 | E95: LICITAÇÃO | F95: EM ANDAMENTO | G95: ALUCOM | H95: PREFEITURA MUNICIPAL DE CANINDE - SECRETARIA DE ASSISTÊNCIA SOCIAL
A96: 96 | B96: PREFEITURA MUNICIPAL DE ARACATI - ESPORTE E LAZER | C96: 20220413005 | E96: LICITAÇÃO | F96: EM ANDAMENTO | G96: ALUCOM | H96: PREFEITURA MUNICIPAL DE ARACATI - ESPORTE E LAZER | I96: CONTRATAÇÃO DE SERVIÇOS DE LOCAÇÃO DE EQUIPAMENTOS DE INFORMÁTICA, COM SUPORTE, ASSISTÊNCIA TÉCNICA E MANUTENÇÃO PREVENTIVA E CORRETIVA IN LOCO, BEM COMO ATUAÇÃO NOS PROCESSOS DE GERENCIAMENTO DE SERVIÇOS.
A97: 97 | B97: PREFEITURA MUNICIPAL DE ARACATI - FINANÇAS | C97: 20220413004 | E97: LICITAÇÃO | F97: EM ANDAMENTO | G97: ALUCOM | H97: PREFEITURA MUNICIPAL DE ARACATI - FINANÇAS | I97: CONTRATAÇÃO DE SERVIÇOS DE LOCAÇÃO DE EQUIPAMENTOS DE INFORMÁTICA, COM SUPORTE, ASSISTÊNCIA TÉCNICA E MANUTENÇÃO PREVENTIVA E CORRETIVA IN LOCO, BEM COMO ATUAÇÃO NOS PROCESSOS DE GERENCIAMENTO DE SERVIÇOS.
A98: 98 | B98: PREFEITURA MUNICIPAL DE ARACATI - SEGURIDADE SOCIAL | C98: 20220413009 | E98: LICITAÇÃO | F98: EM ANDAMENTO | G98: ALUCOM | H98: PREFEITURA MUNICIPAL DE ARACATI - SEGURIDADE SOCIAL | I98: CONTRATAÇÃO DE SERVIÇOS DE LOCAÇÃO DE EQUIPAMENTOS DE INFORMÁTICA, COM SUPORTE, ASSISTÊNCIA TÉCNICA E MANUTENÇÃO PREVENTIVA E CORRETIVA IN LOCO, BEM COMO ATUAÇÃO NOS PROCESSOS DE GERENCIAMENTO DE SERVIÇOS.
A99: 99 | B99: PREFEITURA MUNICIPAL DE ARACATI - GABINETE DO PREFEITO | C99: 20220413007 | E99: LICITAÇÃO | F99: EM ANDAMENTO | G99: ALUCOM | H99: PREFEITURA MUNICIPAL DE ARACATI - GABINETE DO PREFEITO | I99: CONTRATAÇÃO DE SERVIÇOS DE LOCAÇÃO DE EQUIPAMENTOS DE INFORMÁTICA, COM SUPORTE, ASSISTÊNCIA TÉCNICA E MANUTENÇÃO PREVENTIVA E CORRETIVA IN LOCO, BEM COMO ATUAÇÃO NOS PROCESSOS DE GERENCIAMENTO DE SERVIÇOS.
A100: 100 | B100: SECRETARIA MUNICIPAL DE INFORMAÇÃO E TECNOLOGIA - SEMIT | C100: 01/2024 GAB/SEMIT | E100: LICITAÇÃO | F100: EM ANDAMENTO | G100: ALUCOM | H100: SEMIT | I100: O objeto do presente Termo de Contrato é a locação de equipamentos de informática (no breaks) com instalação, manutenção, suporte e gestão do ambiente de TI, e execução continuada de atividades referentes à incidentes e solicitações de serviços, com suporte, assistência técnica e disponibilização de central de serviços, visando futuras contratações pela Prefeitura Municipal de São Luís, através da Secretaria Municipal de Informação e Tecnologia – SEMIT, conforme especificações e quantitativos estabelecidos no Termo de Referência, anexo do Edital.
A101: 101 | B101: PREFEITURA MUNICIPAL DE CAMOCIM - CONSERVAÇÃO E SERVIÇOS PUBLICOS | C101: 2022.04.05.002-03 | E101: LICITAÇÃO | F101: EM ANDAMENTO | G101: ALUCOM | H101: PREFEITURA MUNICIPAL DE CAMOCIM - CONSERVAÇÃO E SERVIÇOS PUBLICOS | I101: O presente contrato tem por objeto a REGISTRO DE PREÇOS VISANDO FUTURAS E EVENTUAIS CONTRATAÇÕES DE SERVIÇOS DE LOCAÇÕES DE EQUIPAMENTOS DE INFORMÁTICA, COM SUPORTE, ASSISTÊNCIA TÉCNICA E MANUTENÇÃO PREVENTIVA E CORRETIVA IN-LOCO, BEM COMO ATUAÇÃO NOS PROCESSOS DE GERENCIAMENTO DE SERVIÇOS, COM BASE EM MELHORES PRÁTICAS DEFINIDAS PELA ITIL - BIBLIOTECA DE INFRAESTRUTURA DE TECNOLOGIA, CUJOS SERVIÇOS SERÃO AVALIADOS ATRAVÉS DE ACORDOS DE NÍVEL DE SERVIÇO, PARA ATENDER AS NECESSIDADES DAS DIVERSAS SECRETARIAS DO MUNICÍPIO DE CAMOCIM/CE.
A102: 102 | B102: PREFEITURA MUNICIPAL DE CAMOCIM - CULTURA | C102: 2022.04.05.002-07 | E102: LICITAÇÃO | F102: EM ANDAMENTO | G102: ALUCOM | H102: PREFEITURA MUNICIPAL DE CAMOCIM - CULTURA | I102: O presente contrato tem por objeto a REGISTRO DE PREÇOS VISANDO FUTURAS E EVENTUAIS CONTRATAÇÕES DE SERVIÇOS DE LOCAÇÕES DE EQUIPAMENTOS DE INFORMÁTICA, COM SUPORTE, ASSISTÊNCIA TÉCNICA E MANUTENÇÃO PREVENTIVA E CORRETIVA IN-LOCO, BEM COMO ATUAÇÃO NOS PROCESSOS DE GERENCIAMENTO DE SERVIÇOS, COM BASE EM MELHORES PRÁTICAS DEFINIDAS PELA ITIL - BIBLIOTECA DE INFRAESTRUTURA DE TECNOLOGIA, CUJOS SERVIÇOS SERÃO AVALIADOS ATRAVÉS DE ACORDOS DE NÍVEL DE SERVIÇO, PARA ATENDER AS NECESSIDADES DAS DIVERSAS SECRETARIAS DO MUNICÍPIO DE CAMOCIM/CE.
A103: 103 | B103: PREFEITURA MUNICIPAL DE CAMOCIM - DESENVOLVIMENTO SOCIAL E CIDADANIA | C103: 2022.04.05.002-05 | E103: LICITAÇÃO | F103: EM ANDAMENTO | G103: ALUCOM | H103: PREFEITURA MUNICIPAL DE CAMOCIM - DESENVOLVIMENTO SOCIAL E CIDADANIA | I103: O presente contrato tem por objeto a REGISTRO DE PREÇOS VISANDO FUTURAS E EVENTUAIS CONTRATAÇÕES DE SERVIÇOS DE LOCAÇÕES DE EQUIPAMENTOS DE INFORMÁTICA, COM SUPORTE, ASSISTÊNCIA TÉCNICA E MANUTENÇÃO PREVENTIVA E CORRETIVA IN-LOCO, BEM COMO ATUAÇÃO NOS PROCESSOS DE GERENCIAMENTO DE SERVIÇOS, COM BASE EM MELHORES PRÁTICAS DEFINIDAS PELA ITIL - BIBLIOTECA DE INFRAESTRUTURA DE TECNOLOGIA, CUJOS SERVIÇOS SERÃO AVALIADOS ATRAVÉS DE ACORDOS DE NÍVEL DE SERVIÇO, PARA ATENDER AS NECESSIDADES DAS DIVERSAS SECRETARIAS DO MUNICÍPIO DE CAMOCIM/CE.
A104: 104 | B104: PREFEITURA MUNICIPAL DE CAMOCIM - EDUCAÇÃO | C104: 2022.04.05.002-06 | E104: LICITAÇÃO | F104: EM ANDAMENTO | G104: ALUCOM | H104: PREFEITURA MUNICIPAL DE CAMOCIM - EDUCAÇÃO | I104: O presente contrato tem por objeto a REGISTRO DE PREÇOS VISANDO FUTURAS E EVENTUAIS CONTRATAÇÕES DE SERVIÇOS DE LOCAÇÕES DE EQUIPAMENTOS DE INFORMÁTICA, COM SUPORTE, ASSISTÊNCIA TÉCNICA E MANUTENÇÃO PREVENTIVA E CORRETIVA IN-LOCO, BEM COMO ATUAÇÃO NOS PROCESSOS DE GERENCIAMENTO DE SERVIÇOS, COM BASE EM MELHORES PRÁTICAS DEFINIDAS PELA ITIL - BIBLIOTECA DE INFRAESTRUTURA DE TECNOLOGIA, CUJOS SERVIÇOS SERÃO AVALIADOS ATRAVÉS DE ACORDOS DE NÍVEL DE SERVIÇO, PARA ATENDER AS NECESSIDADES DAS DIVERSAS SECRETARIAS DO MUNICÍPIO DE CAMOCIM/CE.
A105: 105 | B105: PREFEITURA MUNICIPAL DE CAMOCIM - ESPORTE E JUVENTUDE | C105: 2022.04.05.002-10 | E105: LICITAÇÃO | F105: EM ANDAMENTO | G105: ALUCOM | H105: PREFEITURA MUNICIPAL DE CAMOCIM - ESPORTE E JUVENTUDE | I105: O presente contrato tem por objeto a REGISTRO DE PREÇOS VISANDO FUTURAS E EVENTUAIS CONTRATAÇÕES DE SERVIÇOS DE LOCAÇÕES DE EQUIPAMENTOS DE INFORMÁTICA, COM SUPORTE, ASSISTÊNCIA TÉCNICA E MANUTENÇÃO PREVENTIVA E CORRETIVA IN-LOCO, BEM COMO ATUAÇÃO NOS PROCESSOS DE GERENCIAMENTO DE SERVIÇOS, COM BASE EM MELHORES PRÁTICAS DEFINIDAS PELA ITIL - BIBLIOTECA DE INFRAESTRUTURA DE TECNOLOGIA, CUJOS SERVIÇOS SERÃO AVALIADOS ATRAVÉS DE ACORDOS DE NÍVEL DE SERVIÇO, PARA ATENDER AS NECESSIDADES DAS DIVERSAS SECRETARIAS DO MUNICÍPIO DE CAMOCIM/CE.
A106: 106 | B106: PREFEITURA MUNICIPAL DE CAMOCIM - GABINETE DA PREFEITA | C106: 2022.04.05.002-08 | E106: LICITAÇÃO | F106: EM ANDAMENTO | G106: ALUCOM | H106: PREFEITURA MUNICIPAL DE CAMOCIM - GABINETE DA PREFEITA | I106: O presente contrato tem por objeto a REGISTRO DE PREÇOS VISANDO FUTURAS E EVENTUAIS CONTRATAÇÕES DE SERVIÇOS DE LOCAÇÕES DE EQUIPAMENTOS DE INFORMÁTICA, COM SUPORTE, ASSISTÊNCIA TÉCNICA E MANUTENÇÃO PREVENTIVA E CORRETIVA IN-LOCO, BEM COMO ATUAÇÃO NOS PROCESSOS DE GERENCIAMENTO DE SERVIÇOS, COM BASE EM MELHORES PRÁTICAS DEFINIDAS PELA ITIL - BIBLIOTECA DE INFRAESTRUTURA DE TECNOLOGIA, CUJOS SERVIÇOS SERÃO AVALIADOS ATRAVÉS DE ACORDOS DE NÍVEL DE SERVIÇO, PARA ATENDER AS NECESSIDADES DAS DIVERSAS SECRETARIAS DO MUNICÍPIO DE CAMOCIM/CE.
A107: 107 | B107: PREFEITURA MUNICIPAL DE CAMOCIM - GESTÃO ADMINISTRATIVA | C107: 2022.04.05.002-01 | E107: LICITAÇÃO | F107: EM ANDAMENTO | G107: ALUCOM | H107: PREFEITURA MUNICIPAL DE CAMOCIM - GESTÃO ADMINISTRATIVA | I107: O presente contrato tem por objeto a REGISTRO DE PREÇOS VISANDO FUTURAS E EVENTUAIS CONTRATAÇÕES DE SERVIÇOS DE LOCAÇÕES DE EQUIPAMENTOS DE INFORMÁTICA, COM SUPORTE, ASSISTÊNCIA TÉCNICA E MANUTENÇÃO PREVENTIVA E CORRETIVA IN-LOCO, BEM COMO ATUAÇÃO NOS PROCESSOS DE GERENCIAMENTO DE SERVIÇOS, COM BASE EM MELHORES PRÁTICAS DEFINIDAS PELA ITIL - BIBLIOTECA DE INFRAESTRUTURA DE TECNOLOGIA, CUJOS SERVIÇOS SERÃO AVALIADOS ATRAVÉS DE ACORDOS DE NÍVEL DE SERVIÇO, PARA ATENDER AS NECESSIDADES DAS DIVERSAS SECRETARIAS DO MUNICÍPIO DE CAMOCIM/CE.
... A138: 138 | B138: ISG - HELV - 95592-20 | C138: 95592-20 | E138: PESSOA JURÍDICA | F138: EM ANDAMENTO | G138: ALUCOM | H138: ISGH | I138: AS PARTES CELEBRARAM O CONTRATO DE LOCAÇÃO DE EQUIPAMENTOS DE INFORMÁTICA E MULTIMÍDIA, EM FAVOR DO HOSPITAL ESTADUAL LEONARDO DA VINCI - HELV, INSCRITO NO CNPJ/MF SOB O Nº 05.268.526/0019-08, SITUADO NA RUA ROCHA LIMA, Nº 1563, SALA 01, BAIRRO ALDEOTA, FORTALEZA - CE, CEP 60135-285.
A139: 139 | B139: ISG - HELV - 96210-20 | C139: 96210-20 | E139: PESSOA JURÍDICA | F139: EM ANDAMENTO | G139: ALUCOM | H139: ISGH
A140: 140 | B140: PREFEITURA MUNICIPAL DE CAUCAIA - SECRETARIA MUNICIPAL DE PLANEJAMENTO URBANO E AMBIENTAL | C140: 2021.08.02.01-10 | E140: LICITAÇÃO | F140: EM ANDAMENTO | G140: ALUCOM | H140: PREFEITURA MUNICIPAL DE CAUCAIA - SECRETARIA MUNICIPAL DE PLANEJAMENTO URBANO E AMBIENTAL | I140: CONTRATAÇOES DE SERVIÇOS DE LOCAÇOES DE,EQUIPAMENTOS DE INFORMÁTICA, COM SUPORTE, ASSISTENCIA TÉCNICA E MANUTENÇAO PREVENTIVA E CORRETIVA IN-LOCO, BEM COMO ATUAÇAO NOS PROCESSOS DE GERENCIAMENTO DE SERVIÇOS, COM BASE EM MELHORES PRÁTICAS DEFINIDAS PELA ITIL - INFORMATION TECHNOLOGY INFRASTRUCTURE LIBRARY®, CUJOS SERVIÇOS SERAO AVALIADOS ATRAVÉS DE ACORDOS DE NÍVEL DE SERVIÇO, PARA ATENDER AS NECESSIDADES DA SECRETARIA DE PLANEJAMENTO URBANO E AMBIENTALDO MUNICÍPIO DE CAUCAIA-CE
A141: 141 | B141: PREFEITURA MUNICIPAL DE CAUCAIA - SECRETARIA MUNICIPAL DE INFRAESTRUTURA | C141: 2021.08.02.01-17 | E141: LICITAÇÃO | F141: EM ANDAMENTO | G141: ALUCOM | H141: PREFEITURA MUNICIPAL DE CAUCAIA - SECRETARIA MUNICIPAL DE INFRAESTRUTURA | I141: CONTRATAÇÕES DE SERVIÇOS DE LOCAÇÕES DE EQUIPAMENTOS DE INFORMÁTICA, COM SUPORTE, ASSISTÊNCIA TÉCNICA E MANUTENÇÃO PREVENTIVA E CORRETIVA IN-LOCO, BEM COMO ATUAÇÃO NOS PROCESSOS DE GERENCIAMENTO DE SERVIÇOS, COM BASE EM MELHORES PRÁTICAS DEFINIDAS PELA ITIL – INFORMATION TECHNOLOGY INFRASTRUCTURE LIBRARY®, CUJOS SERVIÇOS SERÃO AVALIADOS ATRAVÉS DE ACORDOS DE NÍVEL DE SERVIÇO, PARA ATENDER AS NECESSIDADES DA SECRETARIA MUNICIPAL DE INFRAESTRUTURA DE PESSOAS E TECNOLOGIA DO MUNICÍPIO DE CAUCAIA-CE
A142: 142 | B142: PREFEITURA MUNICIPAL DE CAUCAIA - PROCURADORIA-GERAL DO MUNICÍPIO | C142: 2021.08.02.01-07 | E142: LICITAÇÃO | F142: EM ANDAMENTO | G142: ALUCOM | H142: PREFEITURA MUNICIPAL DE CAUCAIA - PROCURADORIA-GERAL DO MUNICÍPIO | I142: CONTRATAÇÕES DE SERVIÇOS DE LOCAÇÕES DE EQUIPAMENTOS DE INFORMÁTICA, COM SUPORTE, ASSISTÊNCIA TÉCNICA E MANUTENÇÃO PREVENTIVA E CORRETIVA IN-LOCO, BEM COMO ATUAÇÃO NOS PROCESSOS DE GERENCIAMENTO DE SERVIÇOS, COM BASE EM MELHORES PRÁTICAS DEFINIDAS PELA ITIL – INFORMATION TECHNOLOGY INFRASTRUCTURE LIBRARY®, CUJOS SERVIÇOS SERÃO AVALIADOS ATRAVÉS DE ACORDOS DE NÍVEL DE SERVIÇO, PARA ATENDER AS NECESSIDADES DA PROCURADORIA-GERAL DO MUNICÍPIO DE CAUCAIA-CE
A143: 143 | B143: PREFEITURA MUNICIPAL DE CAUCAIA - SECRETARIA MUNICIPAL DE PATRIMÔNIO E TRANSPORTE | C143: 2021.08.02.01 | E143: LICITAÇÃO | F143: EM ANDAMENTO | G143: ALUCOM | H143: PREFEITURA MUNICIPAL DE CAUCAIA - SECRETARIA MUNICIPAL DE PATRIMÔNIO E TRANSPORTE | I143: CONTRATAÇÕES DE SERVIÇOS DE LOCAÇÕES DE EQUIPAMENTOS DE INFORMÁTICA, COM SUPORTE, ASSISTÊNCIA TÉCNICA E MANUTENÇÃO PREVENTIVA E CORRETIVA IN-LOCO, BEM COMO ATUAÇÃO NOS PROCESSOS DE GERENCIAMENTO DE SERVIÇOS, COM BASE EM MELHORES PRÁTICAS DEFINIDAS PELA ITIL – INFORMATION TECHNOLOGY INFRASTRUCTURE LIBRARY®, CUJOS SERVIÇOS SERÃO AVALIADOS ATRAVÉS DE ACORDOS DE NÍVEL DE SERVIÇO, PARA ATENDER AS NECESSIDADES DA SECRETARIA MUNICIPAL DE PATRIMÔNIO E TRANSPORTE DO MUNICÍPIO DE CAUCAIA-CE
A144: 144 | B144: PREFEITURA MUNICIPAL DE CAUCAIA - INSTITUTO DE PREVIDÊNCIA DO MUNICÍPIO | C144: 2021.08.02.01-06 | E144: LICITAÇÃO | F144: EM ANDAMENTO | G144: ALUCOM | H144: PREFEITURA MUNICIPAL DE CAUCAIA - INSTITUTO DE PREVIDÊNCIA DO MUNICÍPIO | I144: CONTRATAÇÕES DE SERVIÇOS DE LOCAÇÕES DE EQUIPAMENTOS DE INFORMÁTICA, COM SUPORTE, ASSISTÊNCIA TÉCNICA E MANUTENÇÃO PREVENTIVA E CORRETIVA IN-LOCO, BEM COMO ATUAÇÃO NOS PROCESSOS DE GERENCIAMENTO DE SERVIÇOS, COM BASE EM MELHORES PRÁTICAS DEFINIDAS PELA ITIL – INFORMATION TECHNOLOGY INFRASTRUCTURE LIBRARY®, CUJOS SERVIÇOS SERÃO AVALIADOS ATRAVÉS DE ACORDOS DE NÍVEL DE SERVIÇO, PARA ATENDER AS NECESSIDADES DO INSTITUTO DE PREVIDENCIA DO MUNICÍPIO DE CAUCAIA-CE
A145: 145 | B145: PREFEITURA MUNICIPAL DE CAUCAIA - INSTITUTO DO MEIO AMBIENTE DO MUNICÍPIO | C145: 2021.08.02.01-05 | E145: LICITAÇÃO | F145: EM ANDAMENTO | G145: ALUCOM | H145: PREFEITURA MUNICIPAL DE CAUCAIA - INSTITUTO DO MEIO AMBIENTE DO MUNICÍPIO | I145: CONTRATAÇÕES DE SERVIÇOS DE LOCAÇÕES DE EQUIPAMENTOS DE INFORMÁTICA, COM SUPORTE, ASSISTÊNCIA TÉCNICA E MANUTENÇÃO PREVENTIVA E CORRETIVA IN-LOCO, BEM COMO ATUAÇÃO NOS PROCESSOS DE GERENCIAMENTO DE SERVIÇOS, COM BASE EM MELHORES PRÁTICAS DEFINIDAS PELA ITIL – INFORMATION TECHNOLOGY INFRASTRUCTURE LIBRARY®, CUJOS SERVIÇOS SERÃO AVALIADOS ATRAVÉS DE ACORDOS DE NÍVEL DE SERVIÇO, PARA ATENDER AS NECESSIDADES DO INSTITUTO DO MEIO AMBIENTE DO MUNICÍPIO DE CAUCAIA-CE
A146: 146 | B146: PREFEITURA MUNICIPAL DE CAUCAIA - GABINETE DO VICE PREFEITO | C146: 2021.08.02.01-04 | E146: LICITAÇÃO | F146: EM ANDAMENTO | G146: ALUCOM | H146: PREFEITURA MUNICIPAL DE CAUCAIA - GABINETE DO VICE PREFEITO | I146: CONTRATAÇÕES DE SERVIÇOS DE LOCAÇÕES DE EQUIPAMENTOS DE INFORMÁTICA, COM SUPORTE, ASSISTÊNCIA TÉCNICA E MANUTENÇÃO PREVENTIVA E CORRETIVA IN-LOCO, BEM COMO ATUAÇÃO NOS PROCESSOS DE GERENCIAMENTO DE SERVIÇOS, COM BASE EM MELHORES PRÁTICAS DEFINIDAS PELA ITIL – INFORMATION TECHNOLOGY INFRASTRUCTURE LIBRARY®, CUJOS SERVIÇOS SERÃO AVALIADOS ATRAVÉS DE ACORDOS DE NÍVEL DE SERVIÇO, PARA ATENDER AS NECESSIDADES DO GABINETE NO VICE-PREFEITO DO MUNICÍPIO DE CAUCAIA-CE
A147: 147 | B147: PREFEITURA MUNICIPAL DE CAUCAIA - GABINETE DO PREFEITO | C147: 2021.08.02.01-03 | E147: LICITAÇÃO | F147: EM ANDAMENTO | G147: ALUCOM | H147: PREFEITURA MUNICIPAL DE CAUCAIA - GABINETE DO PREFEITO | I147: CONTRATAÇÕES DE SERVIÇOS DE LOCAÇÕES DE EQUIPAMENTOS DE INFORMÁTICA, COM SUPORTE, ASSISTÊNCIA TÉCNICA E MANUTENÇÃO PREVENTIVA E CORRETIVA IN-LOCO, BEM COMO ATUAÇÃO NOS PROCESSOS DE GERENCIAMENTO DE SERVIÇOS, COM BASE EM MELHORES PRÁTICAS DEFINIDAS PELA ITIL – INFORMATION TECHNOLOGY INFRASTRUCTURE LIBRARY®, CUJOS SERVIÇOS SERÃO AVALIADOS ATRAVÉS DE ACORDOS DE NÍVEL DE SERVIÇO, PARA ATENDER AS NECESSIDADES DO GABINETE DO PREFEITO DO MUNICÍPIO DE CAUCAIA-CE
A148: 148 | B148: PREFEITURA MUNICIPAL DE CAUCAIA - SECRETARIA MUNICIPAL DE FINANÇAS, PLANEJAMENTO E ORÇAMENTO | C148: 2021.08.02.01-16 | E148: LICITAÇÃO | F148: EM ANDAMENTO | G148: ALUCOM | H148: PREFEITURA MUNICIPAL DE CAUCAIA - SECRETARIA MUNICIPAL DE FINANÇAS, PLANEJAMENTO E ORÇAMENTO | I148: CONTRATAÇÕES DE SERVIÇOS DE LOCAÇÕES DE EQUIPAMENTOS DE INFORMÁTICA, COM SUPORTE, ASSISTÊNCIA TÉCNICA E MANUTENÇÃO PREVENTIVA E CORRETIVA IN-LOCO, BEM COMO ATUAÇÃO NOS PROCESSOS DE GERENCIAMENTO DE SERVIÇOS, COM BASE EM MELHORES PRÁTICAS DEFINIDAS PELA ITIL – INFORMATION TECHNOLOGY INFRASTRUCTURE LIBRARY®, CUJOS SERVIÇOS SERÃO AVALIADOS ATRAVÉS DE ACORDOS DE NÍVEL DE SERVIÇO, PARA ATENDER AS NECESSIDADES DA SECRETARIA MUNICIPAL DE FINANÇAS, PLANEJAMENTO E ORÇAMENTO DO MUNICIPIO DE CAUCAIA-CE
A149: 149 | B149: PREFEITURA MUNICIPAL DE CAUCAIA - SECRETARIA MUNICIPAL DE ESPORTE E JUVENTUDE 2021.08.02.01-15 | C149: 2021.08.02.01-15 | E149: LICITAÇÃO | F149: EM ANDAMENTO | G149: ALUCOM | H149: PREFEITURA MUNICIPAL DE CAUCAIA - SECRETARIA MUNICIPAL DE ESPORTE E JUVENTUDE | I149: CONTRATAÇÕES DE SERVIÇOS DE LOCAÇÕES DE EQUIPAMENTOS DE INFORMÁTICA, COM SUPORTE, ASSISTÊNCIA TÉCNICA E MANUTENÇÃO PREVENTIVA E CORRETIVA IN-LOCO, BEM COMO ATUAÇÃO NOS PROCESSOS DE GERENCIAMENTO DE SERVIÇOS, COM BASE EM MELHORES PRÁTICAS DEFINIDAS PELA ITIL – INFORMATION TECHNOLOGY INFRASTRUCTURE LIBRARY®, CUJOS SERVIÇOS SERÃO AVALIADOS ATRAVÉS DE ACORDOS DE NÍVEL DE SERVIÇO, PARA ATENDER AS NECESSIDADES DA SECRETARIA MUNICIPAL DE ESPORTE E JUVENTUDE DO MUNICÍPIO DE CAUCAIA-CE
A150: 150 | B150: PREFEITURA MUNICIPAL DE CAUCAIA - SECRETARIA MUNICIPAL DE ESPORTE E JUVENTUDE 2021.08.02.01-09 | C150: 2021.08.02.01-09 | E150: LICITAÇÃO | F150: EM ANDAMENTO | G150: ALUCOM | H150: PREFEITURA MUNICIPAL DE CAUCAIA - SECRETARIA MUNICIPAL DE ESPORTE E JUVENTUDE | I150: CONTRATAÇÕES DE SERVIÇOS DE LOCAÇÕES DE EQUIPAMENTOS DE INFORMÁTICA, COM SUPORTE, ASSISTÊNCIA TÉCNICA E MANUTENÇÃO PREVENTIVA E CORRETIVA IN-LOCO, BEM COMO ATUAÇÃO NOS PROCESSOS DE GERENCIAMENTO DE SERVIÇOS, COM BASE EM MELHORES PRÁTICAS DEFINIDAS PELA ITIL – INFORMATION TECHNOLOGY INFRASTRUCTURE LIBRARY®, CUJOS SERVIÇOS SERÃO AVALIADOS ATRAVÉS DE ACORDOS DE NÍVEL DE SERVIÇO, PARA ATENDER AS NECESSIDADES DA SECRETARIA MUNICIPAL DE ESPORTE E JUVENTUDE DO MUNICÍPIO DE CAUCAIA-CE
A151: 151 | B151: PREFEITURA MUNICIPAL DE CAUCAIA - SECRETARIA MUNICIPAL DE EDUCAÇÃO, CIÊNCIA E TECNOLOGIA 2021.07.29.01-01 | C151: 2021.07.29.01-01 | E151: LICITAÇÃO | F151: EM ANDAMENTO | G151: ALUCOM | H151: PREFEITURA MUNICIPAL DE CAUCAIA - SECRETARIA MUNICIPAL DE EDUCAÇÃO, CIÊNCIA E TECNOLOGIA | I151: CONTRATAÇÕES DE SERVIÇOS DE LOCAÇÕES DE EQUIPAMENTOS DE INFORMÁTICA, COM SUPORTE, ASSISTÊNCIA TÉCNICA E MANUTENÇÃO PREVENTIVA E CORRETIVA IN-LOCO, BEM COMO ATUAÇÃO NOS PROCESSOS DE GERENCIAMENTO DE SERVIÇOS, COM BASE EM MELHORES PRÁTICAS DEFINIDAS PELA ITIL – INFORMATION TECHNOLOGY INFRASTRUCTURE LIBRARY, CUJOS SERVIÇOS SERÃO AVALIADOS ATRAVÉS DE ACORDOS DE NÍVEL DE SERVIÇO, PARA ATENDER AS NECESSIDADES DA SECRETARIA MUNICIPAL DE EDUCAÇÃO, CIÊNCIA E TECNOLOGIA DO MUNICIPIO DE CAUCAIA - CE
A152: 152 | B152: PREFEITURA MUNICIPAL DE CAUCAIA - SECRETARIA MUNICIPAL DE EDUCAÇÃO, CIÊNCIA E TECNOLOGIA 2021.08.02.01-20 | C152: 2021.08.02.01-20 | E152: LICITAÇÃO | F152: EM ANDAMENTO | G152: ALUCOM | H152: PREFEITURA MUNICIPAL DE CAUCAIA - SECRETARIA MUNICIPAL DE EDUCAÇÃO, CIÊNCIA E TECNOLOGIA | I152: CONTRATAÇÕES DE SERVIÇOS DE LOCAÇÕES DE EQUIPAMENTOS DE INFORMÁTICA, COM SUPORTE, ASSISTÊNCIA TÉCNICA E MANUTENÇÃO PREVENTIVA E CORRETIVA IN-LOCO, BEM COMO ATUAÇÃO NOS PROCESSOS DE GERENCIAMENTO DE SERVIÇOS, COM BASE EM MELHORES PRÁTICAS DEFINIDAS PELA ITIL – INFORMATION TECHNOLOGY INFRASTRUCTURE LIBRARY, CUJOS SERVIÇOS SERÃO AVALIADOS ATRAVÉS DE ACORDOS DE NÍVEL DE SERVIÇO, PARA ATENDER AS NECESSIDADES DA SECRETARIA MUNICIPAL DE EDUCAÇÃO, CIÊNCIA E TECNOLOGIA DO MUNICIPIO DE CAUCAIA - CE
A153: 153 | B153: ISG - HELV - 102150-21 | C153: 102150-21 | E153: PESSOA JURÍDICA | F153: EM ANDAMENTO | G153: ALUCOM | H153: ISGH
A154: 154 | B154: ISG - HGWA | C154: 180078-25 | E154: PESSOA JURÍDICA | F154: EM ANDAMENTO | G154: ALUCOM | H154: ISGH
A155: 155 | B155: TOP TRANSPORTES | C155: 2022.03.01.01 | E155: PESSOA JURÍDICA | F155: EM ANDAMENTO | G155: ALUCOM | H155: TOP TRANSPORTES
A156: 156 | B156: ANA KALINCA | C156: 2023.04.01.01 | E156: PESSOA JURÍDICA | F156: EM ANDAMENTO | G156: ALUCOM | H156: ANA KALINCA
A157: 157 | B157: PREFEITURA MUNICIPAL DE CAUCAIA - SECRETARIA DE SEGURANÇA PÚBLICA DE CAUCAIA | C157: 2021.11.12.01 | E157: LICITAÇÃO | F157: EM ANDAMENTO | G157: ALUCOM | H157: PREFEITURA MUNICIPAL DE CAUCAIA - SECRETARIA DE SEGURANÇA PÚBLICA DE CAUCAIA | I157: CONTRATAÇÕES DE SERVIÇOS DE LOCAÇÕES DE EQUIPAMENTOS DE INFORMÁTICA, COM SUPORTE, ASSISTÊNCIA TÉCNICA E MANUTENÇÃO PREVENTIVA E CORRETIVA IN-LOCO, BEM COMO ATUAÇÃO NOS PROCESSOS DE GERENCIAMENTO DE SERVIÇOS, COM BASE EM MELHORES PRÁTICAS DEFINIDAS PELA ITIL – INFORMATION TECHNOLOGY INFRASTRUCTURE LIBRARY, CUJOS SERVIÇOS SERÃO AVALIADOS ATRAVÉS DE ACORDOS DE NÍVEL DE SERVIÇO, PARA ATENDER AS NECESSIDADES DA SECRETARIA DE SEGURANÇA PÚBLICA DO MUNICIPIO DE CAUCAIA - CE
A158: 158 | B158: ESCOLA PREPARATORIA DE CADETES DO EXERCITO | C158: 001-2023 | E158: LICITAÇÃO | F158: EM ANDAMENTO | G158: IP SERVIÇOS | H158: EsPCEx | I158: O OBJETO DO PRESENTE INSTRUMENTO É A CONTRATAÇÃO DE SERVIÇOS DE TECNOLOGIA DA INFORMAÇÃO E COMUNICAÇÃO DE OUTSOURCING DE IMPRESSÃO E CÓPIA, COMPREENDENDO A CESSÃO DE DIREITO DE USO DE EQUIPAMENTOS FUNCIONAIS, COM O FORNECIMENTO DE INSUMOS DIRETOS E INDIRETOS PARA A IMPRESSÃO, CÓPIA (EXCETO PAPEL), DIGITALIZAÇÃO DE DOCUMENTOS, GERENCIAMENTO DO AMBIENTE DE IMPRESSÃO, FORNECIMENTO DE RELATÓRIO DE CONTABILIZAÇÃO, ALÉM DE MANUTENÇÃO E SUPORTE TÉCNICO, COM EXECUÇÃO MEDIANTE O REGIME DE EMPREITADA POR PREÇO UNITÁRIO ESTIMATIVO, QUE SERÃO PRESTADOS NAS CONDIÇÕES ESTABELECIDAS NO TERMO DE REFERÊNCIA, ANEXO DO EDITAL.
A159: 159 | B159: FUNASA | C159: 002-2023 | E159: LICITAÇÃO | F159: EM ANDAMENTO | G159: IP SERVIÇOS | H159: FUNASA
A160: 160 | B160: 20º RCB | C160: 003-2024 | E160: LICITAÇÃO | F160: EM ANDAMENTO | G160: IP SERVIÇOS | H160: 20º RCB
A161: 161 | B161: COREN DF | C161: 006-2023 | E161: LICITAÇÃO | F161: EM ANDAMENTO | G161: IP SERVIÇOS | H161: COREN DF
A162: 162 | B162: PRIMEIRO CENTRO INTEGRADO DE DEFESA AÉREA E CONTROLE DE TRÁFEGO AÉREO - CINDACT 1 | C162: 067/GAPDF-CINDACTA I/2023 | E162: LICITAÇÃO | F162: EM ANDAMENTO | G162: IP SERVIÇOS | H162: CINDACTA I | I162: O objeto do presente instrumento é a contratação serviço de outsourcing de impressão, na modalidade de Franquia com excedente de páginas, com fornecimento de multifuncionais digitais para impressões e cópias monocromáticas, fornecimento de insumos, exceto papel, além de assistência técnica especializada, reposição de peças originais e sistema de gerenciamento de impressão, para suprir a demanda dos destacamentos subordinados ao CINDACTA I: Destacamento de Controle do Espaço Aéreo de Barra do Garça - DTCEA-BW, Destacamento de Controle do Espaço Aéreo de Cachimbo - DTCEA-CC, Destacamento de Controle do Espaço Aéreo de Chapada dos Guimarães - DTCEA-GI, Destacamento de Controle do Espaço Aéreo de Tanabi - DTCEA-TNB, Destacamento de Controle do Espaço Aéreo de Sinope - DTCEA-SI, Destacamento de Controle do Espaço Aéreo de Porto Esperidião - DTCEA-EP e Destacamento de Controle do Espaço Aéreo de São Felix do Araguaia - DTCEA-FA, conforme condições, quantidades e exigências estabelecidas nesse Termo de Referência e seus anexos.
A163: 163 | B163: CRN1 DF | C163: 06-2024 | E163: LICITAÇÃO | F163: EM ANDAMENTO | G163: IP SERVIÇOS | H163: CRN1 | I163: O OBJETO DO PRESENTE INSTRUMENTO É A CONTRATAÇÃO DE SERVIÇOS COMUNS DE LOCAÇÃO DE IMPRESSORAS MULTIFUNCIONAL LASER MONOCROMÁTICA (OUTSOURCING), COM SERVIÇOS DE IMPRESSÃO, DIGITALIZAÇÃO E REPRODUÇÃO DE CÓPIAS, COM FORNECIMENTO DE EQUIPAMENTOS E INSUMOS (EXCETO PAPEL), INCLUSIVE SUPORTE, MANUTENÇÃO E DISPONIBILIZAÇÃO DE SISTEMA DE GERENCIAMENTO PARA CONTROLE DE CÓPIAS NO ÂMBITO DO CRN-1, NAS CONDIÇÕES ESTABELECIDAS NO TERMO DE REFERÊNCIA.
A164: 164 | B164: CENTRO DE LANÇAMENTO DE ALCÂNTARA - CLA | C164: 005/CLA/2024 | E164: LICITAÇÃO | F164: EM ANDAMENTO | G164: IP SERVIÇOS | H164: CLA | I164: O objeto da presente licitação é a escolha de proposta mais vantajosa para a contratação deempresa especializada na Prestação de Serviço Continuado de IMPRESSÃO CORPORATIVA (Outsourcingde Impressão), na modalidade de franquia mensal mais excedente, compreendendo o fornecimento,instalação, configuração e a cessão de uso dos equipamentos de impressão, contemplando impressão,cópia e digitalização (sem ônus), agregando a prestação de serviços de manutenção preventiva e corretiva,reposição de peças, suprimentos e insumos (exceto papel), e sistema para gerenciamento e monitoramentodos equipamentos, destinados a diversos setores do Centro de Lançamento de Alcântara, e demaisunidades apoiadas em São Luís-MA, Raposa-MA e Alcântara-MA, conforme condições, quantidades eexigências estabelecidas neste Aviso de Contratação Direta e seus anexos.
A165: 165 | B165: CISNORDESTE | C165: 18-2024 | E165: LICITAÇÃO | F165: EM ANDAMENTO | G165: IP SERVIÇOS | H165: CISNORDESTE SC
A166: 166 | B166: CREF | C166: 041-2024 | E166: LICITAÇÃO | F166: EM ANDAMENTO | G166: IP SERVIÇOS | H166: CREF
A167: 167 | B167: PREFEITURA MUNICIPAL DE TAUÁ - SECRETARIA DE DIREITOS HUMANOS, CIDADANIA E DIVERSIDADE | C167: 12.12.015/2025-SDHCD | E167: LICITAÇÃO | F167: EM ANDAMENTO | G167: ALUCOM | H167: PREFEITURA MUNICIPAL DE TAUÁ - SECRETARIA DE DIREITOS HUMANOS, CIDADANIA E DIVERSIDADE | I167: REGISTRO DE PREÇO PARA FUTURAS E EVENTUAIS SERVIÇOS DE LOCAÇÕES DE EQUIPAMENTOS DE INFORMÁTICA, COM SUPORTE, ASSISTÊNCIA TÉCNICA E MANUTENÇÃO PREVENTIVA E CORRETIVA INLOCO para atender as necessidades da Secretaria de Direitos Humanos, Cidadania e Diversidade do Município de Tauá-CE
A168: 168 | B168: SECRETARIA EXTRAORDINÁRIA DE REPRESENTAÇÃO DO GOVERNO DO ESTADO DO AMAPÁ EM BRASÍLIA – SEAB | C168: 010/2024-SEAB | E168: LICITAÇÃO | F168: EM ANDAMENTO | G168: IP SERVIÇOS | H168: SECRETARIA EXTRAORDINÁRIA DE REPRESENTAÇÃO DO GOVERNO DO ESTADO DO AMAPÁ EM BRASÍLIA – SEAB | I168: contratação de empresa especializada para a prestação de serviços de Outsourcing incluindo fornecimento de equipamentos de impressão, monocromáticas e policromáticas, cópias, digitalização, com fornecimento de assistência técnica para a manutenção corretiva e preventiva, incluindo substituição de peças, insumos, suprimentos e materiais de consumo, como cartuchos de tonner, revelador e cilindro, para atender as necessidades da Secretaria Extraordinária de Representação do Governo do Estado do Amapá em Brasília – SEAB.
A169: 169 | B169: SECRETARIA DO DESENVOLVIMENTO ECONÔMICO - SDE | C169: 02 / 2025 | E169: LICITAÇÃO | F169: EM ANDAMENTO | G169: IP SERVIÇOS | H169: SECRETARIA DO DESENVOLVIMENTO ECONÔMICO - SDE | I169: Contratação de empresa especializada para fornecimento de serviços de Impressão, suporte cópia, digitalização, caracterizados como “ outsourcing de impressão”, com fornecimento de equipamentos reprográficos digitais, sendo 2 ( dois) equipamentos monocromáticos com impressão tipo A4, 2(dois) equipamentos policromáticos com impressão tipo A4 e 1 equipamento policromáticos com impressão tipo A3, compreendendo, ainda, a alocação de técnicos residentes, a entrega/instalação e assistência técnica, fornecimento de suprimentos (exceto papel), além do fornecimento de sistema de gerenciamento de cópias/impressões e o treinamento para operação técnico por 12 meses.
A170: 170 | B170: SUPERINTENDÊNCIA ESTADUAL DO MINISTÉRIO DA SAÚDE NO CEARÁ - SEMS/CE | C170: 3/2024 | E170: LICITAÇÃO | F170: EM ANDAMENTO | G170: IP SERVIÇOS | H170: SUPERINTENDÊNCIA ESTADUAL DO MINISTÉRIO DA SAÚDE NO CEARÁ - SEMS/CE | I170: contratação de empresa especializada em prestação de serviços de Outsourcing de Impressão para atender às necessidades da Superintendência Estadual do Ministério da Saúde no Ceará, nas condições estabelecidas no Termo de Referência.
A171: 171 | B171: MARANHÃO PARCEIRIAS - MAPA | C171: 15/2023/MAPA | E171: LICITAÇÃO | F171: EM ANDAMENTO | G171: IP SERVIÇOS | H171: MARANHÃO PARCEIRIAS - MAPA | I171: prestação de serviços de outsourcing de impressão, cópia e digitalização com fornecimento de suprimentos, equipamentos e de sistema de gerenciamento, manutenção preventiva e corretiva, e serviços de operacionalização da solução de impressão, exceto papel e grampos, para atender as necessidades da Maranhão Parcerias – MAPA.
A172: 172 | B172: REPRESENTAÇÃO DO MUNICÍPIO DE PALMAS - SECRETARIA MUNICIPAL DO GABINETE DO PREFEITO EM BRASILIA | C172: 041/2025 | E172: LICITAÇÃO | F172: EM ANDAMENTO | G172: IP SERVIÇOS | H172: REPRESENTAÇÃO DO MUNICÍPIO DE PALMAS - SECRETARIA MUNICIPAL DO GABINETE DO PREFEITO EM BRASILIA | I172: O presente Instrumento tem por objeto a contratação de empresa especializada na prestação de serviços de outsourcing de impressão departamental, com fornecimento de multifuncional e impressora, incluindo papel, toners, peças, insumos e assistência técnica, para atender as demandas da Secretaria Extraordinária de Representação em Brasília, subordinada à Secretaria do Gabinete do Prefeito, conforme condições, quantidades e exigências estabelecidas no Termo de Referência
A173: 173 | B173: VICE-PREFEITURA DE SÃO LUIS - GAVIC | C173: 052/2024/GAVIC | E173: LICITAÇÃO | F173: EM ANDAMENTO | G173: IP SERVIÇOS | H173: VICE-PREFEITURA DE SÃO LUIS - GAVIC | I173: Locação de impressoras, suporte e manutenção, para atender as demandas do Gabinete da Vice-Prefeitura - GAVIC
A174: 174 | B174: SECRETARIA MUNICIPAL DE INOVAÇÃO, SUSTENTABILIDADE E PROJETOS ESPECIAIS – SEMISPE | C174: 007/2024 | E174: LICITAÇÃO | F174: EM ANDAMENTO | G174: IP SERVIÇOS | H174: SECRETARIA MUNICIPAL DE INOVAÇÃO, SUSTENTABILIDADE E PROJETOS ESPECIAIS – SEMISPE | I174: locação de impressoras multifuncionais para atender as necessidades de serviços, programas e órgãos vinculados a Secretaria Municipal de Inovação, Sustentabilidade e Projetos Especiais – SEMISPE.
A175: 175 | B175: CÂMARA MUNICIPAL DE CASCAVEL | C175: 1504/2025.1 | E175: LICITAÇÃO | F175: EM ANDAMENTO | G175: IP SERVIÇOS | H175: CÂMARA MUNICIPAL DE CASCAVEL | I175: CONTRATAÇÃO DE EMPRESA PARA PRESTAÇÃO DE SERVIÇOS DE LOCAÇÃO DE IMPRESSORAS COM SERVIÇOS DE MANUTENÇÃO CORRETIVA E PREVENTIVA, SOB RESPONSABILIDADE DA CÂMARA MUNICIPAL DE CASCAVEL/CE
A176: 176 | B176: SECRETARIA MUNICIPAL DE SEGURANÇA COM CIDADANIA−048/2024/SEMUSC | C176: 048/2024/SEMUSC | E176: LICITAÇÃO | F176: EM ANDAMENTO | G176: IP SERVIÇOS | H176: SECRETARIA MUNICIPAL DE SEGURANÇA COM CIDADANIA−SEMUSC | I176: O presente Contrato obedece aos termos do TERMO DE REFERÊNCIA No 25/2024/SEMUSC, da Proposta da Contratada, e da Lei no 14.133/2021, art. 75, inciso II (atualizados pelo Decreto no. 11.871 de 29 de dezembro de 2023).
A177: 177 | B177: PREFEITURA MUNICIPAL DE TAUÁ - SECRETARIA DE SEGURANÇA CIDADÃ | C177: 12.01.001/2026-SSC | E177: LICITAÇÃO | F177: EM ANDAMENTO | G177: ALUCOM | H177: PREFEITURA MUNICIPAL DE TAUÁ - SECRETARIA DE SEGURANÇA CIDADÃ | I177: REGISTRO DE PREÇO PARA FUTURAS E EVENTUAIS SERVIÇOS DE LOCAÇÕES DE EQUIPAMENTOS DE INFORMÁTICA, COM SUPORTE, ASSISTÊNCIA TÉCNICA E MANUTENÇÃO PREVENTIVA E CORRETIVA IN-LOCO para atender as necessidades da Secretaria da Segurança Cidadã do Município de Tauá-CE, nas condições estabelecidas no Termo de Referência.
A178: 178 | B178: GOVERNO MUNICIPAL DE CANINDÉ - SECRETARIA DO MEIO AMBIENTE | C178: 20250423001 | E178: LICITAÇÃO | F178: EM ANDAMENTO | G178: IP SERVIÇOS | H178: GOVERNO MUNICIPAL DE CANINDÉ - SECRETARIA DO MEIO AMBIENTE | I178: Constitui o objeto do presente contrato a CONTRATAÇÃO DOS SERVIÇOS DE LOCAÇÃO DE IMPRESSORA PARA ATENDER AS NECESSIDADES DA SECRETARIA DE MEIO AMBIENTE DO MUNICÍPIO DE CANINDÉ/CE
... A200: 200 | B200: ÂMBITO PÚBLICO ASSESSORIA EM LICITACOES E GESTAO PUBLICA LTDA | C200: 2024.0903.01-IP | E200: PESSOA JURÍDICA | F200: EM ANDAMENTO | G200: IP SERVIÇOS | H200: ÂMBITO PÚBLICO ASSESSORIA EM LICITACOES E GESTAO PUBLICA LTDA | I200: Serviço de locação de equipamentos de informática, com suporte, assistência técnica e manutenção preventiva e corretiva, visando atender satisfatoriamente a demanda da ÂMBITO PÚBLICO ASSESSORIA EM LICITACOES E GESTAO PUBLICA LTDA no Município Fortaleza/CE, na quantidade e especificação descritas abaixo, em boas condições de uso e conservação.
A201: 201 | B201: CONEXAO CONSTRUTORA EMPREENDIMENTOS E SOLUCOES LTDA | C201: 025/2025. | E201: PESSOA JURÍDICA | F201: EM ANDAMENTO | G201: IP SERVIÇOS | H201: CONEXAO CONSTRUTORA
A202: 202 | B202: QUEIROZ EDUCACIONAL LTDA | C202: 002/2026 - IP | E202: PESSOA JURÍDICA | F202: EM ANDAMENTO | G202: IP SERVIÇOS | H202: QUEIROZ EDUCACIONAL LTDA | I202: Por esta avença, a CONTRATADA fornece ao CONTRATANTE o serviço de locação de equipamentos de informática, com suporte, assistência técnica e manutenção preventiva e corretiva, visando atender satisfatoriamente a demanda da QUEIROZ EDUCACIONAL LTDA, no Município de Mossoró/RN, na quantidade e especificações descritas abaixo, em boas condições de uso e conservação.
A203: 203 | B203: S Z SERVICOS COMERCIO E DISTRIBUICAO | C203: 024/2025. | E203: PESSOA JURÍDICA | F203: EM ANDAMENTO | G203: IP SERVIÇOS | H203: S Z SERVICOS COMERCIO E DISTRIBUICAO LTDA, | I203: Por esta avença, a CONTRATADA fornece ao CONTRATANTE, os Serviços de locação de equipamentos de informática, incluindo instalação, suporte técnico e manutenção preventiva e corretiva, visando atender de forma satisfatória ao S Z SERVICOS COMERCIO E DISTRIBUICAO LTDA, na quantidade e especificação descritas abaixo, em boas condições de uso e conservação.
A204: 204 | B204: CASA TELES COMERCIO DE MOVEIS LTDA | C204: 027-2025 | E204: PESSOA JURÍDICA | F204: EM ANDAMENTO | G204: IP SERVIÇOS | H204: CASA TELES COMERCIO DE MOVEIS LTDA | I204: Por esta avença, a CONTRATADA fornece ao CONTRATANTE o serviço de locação de equipamentos de informática, com suporte, assistência técnica e manutenção preventiva e corretiva, visando atender satisfatoriamente a demanda da CASA TELES COMERCIO DE MOVEIS LTDA, na quantidade e especificações descritas abaixo, em boas condições de uso
A205: 205 | B205: Fundação Edson Queiroz | C205: 018/2025. | E205: PESSOA JURÍDICA | F205: ENCERRADO | G205: IP SERVIÇOS | H205: Fundação Edson Queiroz - UNIFOR | I205: Por esta avença, a CONTRATADA fornece ao CONTRATANTE, os Serviços de locação de equipamentos de informática, incluindo instalação, suporte técnico e manutenção preventiva e corretiva, visando atender de forma satisfatória ao Fundação Edson Queiroz, na quantidade e especificação descritas abaixo, em boas condições
A206: 206 | B206: TORRES ASSESSORIA EM LICITAÇÕES E GESTÃO PUBLICA LTDA, | C206: 020-2025-IP | E206: PESSOA JURÍDICA | F206: EM ANDAMENTO | G206: IP SERVIÇOS | H206: TORRES ASSESSORIA EM LICITAÇÕES E GESTÃO PUBLICA LTDA, | I206: Por esta avença, a CONTRATADA fornece ao CONTRATANTE o serviço de locação de equipamentos de informática, com suporte, assistência técnica e manutenção preventiva e corretiva, visando atender satisfatoriamente a demanda da empresa TORRES ASSESSORIA EM LICITAÇÕES E GESTÃO PUBLICA LTDA, na quantidade e especificações descritas abaixo,
A207: 207 | B207: COMERCIAL DE MEDICAMENTOS CAVALCANTE LTDA - FARMÁCIA PREMIUM | C207: 001-2026 - IP | E207: PESSOA JURÍDICA | F207: EM ANDAMENTO | G207: IP SERVIÇOS | H207: COMERCIAL DE MEDICAMENTOS CAVALCANTE LTDA - FARMÁCIA PREMIUM | I207: Por esta avença, a CONTRATADA fornece ao CONTRATANTE o serviço de locação de equipamentos de informática, com suporte, assistência técnica e manutenção preventiva e corretiva, visando atender satisfatoriamente a demanda da empresa COMERCIAL DE MEDICAMENTOS CAVALCANTE LTDA, na quantidade e especificações descritas abaixo, em boas
A208: 208 | B208: PREFEITURA MUNICIPAL DE TAUÁ - SECRETARIA DE GOVERNO | C208: 1301001/2026 – SEGOV | E208: LICITAÇÃO | F208: EM ANDAMENTO | G208: ALUCOM | H208: PREFEITURA MUNICIPAL DE TAUÁ - SECRETARIA DE GOVERNO | I208: objeto do presente instrumento é REGISTRO DE PREÇO PARA FUTURAS E EVENTUAIS SERVIÇOS DE LOCAÇÕES DE EQUIPAMENTOS DE INFORMÁTICA, COM SUPORTE, ASSISTÊNCIA TÉCNICA E MANUTENÇÃO PREVENTIVA E CORRETIVA IN-LOCO Para atender as necessidades da Secretaria Municipal de Governo, do Município de Tauá-Ceará., nas condições estabelecidas no Termo de Referência.
A209: 209 | B209: SOCIEDADE PAULISTA DE MEDICINA VETERINÁRIA | C209: 2024.0110.01-IP | E209: PESSOA JURÍDICA | F209: EM ANDAMENTO | G209: IP SERVIÇOS | H209: SOCIEDADE PAULISTA DE MEDICINA | I209: . Por esta avença, a CONTRATADA fornece ao CONTRATANTE, os serviços de Serviço de locação de equipamentos de informática, com suporte, assistência técnica e manutenção preventiva e corretiva, visando atender satisfatoriamente a demanda da SOCIEDADE PAULISTA DE MEDICINA VETERINÁRIA, no Município de Crato/CE, na quantidade e especificação descritas abaixo, em boas condições de uso e conservação.
...

Sheet EVENTO
A1: ID | B1: TIPO | C1: CONTRATO
A7: 6 | B7: CADASTRO | C7: ALECE
A8: 7 | B8: ADITIVO DE QUANTIDADE | C8: ALECE
A9: 8 | B9: CADASTRO | C9: 10a REGIAO MILITAR
A10: 9 | B10: ADITIVO DE REAJUSTE E PRAZO | C10: 10a REGIAO MILITAR
A11: 10 | B11: CADASTRO | C11: CMFOR
A12: 11 | B12: ADITIVO DE REAJUSTE E PRAZO | C12: CMFOR
A13: 12 | B13: ADITIVO DE REAJUSTE E PRAZO | C13: CMFOR
A14: 13 | B14: CADASTRO | C14: ESCOLA DE APRENDIZEM DE MARINHEIROS DO CEARÁ
A15: 14 | B15: ADITIVO DE REAJUSTE E PRAZO | C15: ESCOLA DE APRENDIZEM DE MARINHEIROS DO CEARÁ
A16: 15 | B16: CADASTRO | C16: UFC
A17: 16 | B17: ADITIVO DE PRAZO | C17: UFC
A18: 17 | B18: APOSTILAMENTO | C18: UFC
... A731: 732 | B731: ADITIVO DE PRAZO | C731: MUNICIPIO DE GRANJA - CÂMARA MUNICIPAL DE GRANJA
A732: 733
A733: 734
A734: 735
A735: 736
A736: 737
A737: 738
A738: 739
A739: 740
A740: 741
A741: 742
A742: 743
A743: 744
... A998: 999

Sheet INFORMAÇÕES
A1: EVENTO | B1: TIPO_EVENTO | C1: CONTRATO | D1: DATA_INICIAL | E1: DURAÇÃO (MESES) | F1: DURAÇÃO_MAXIMA (MESES) | G1: DATA_FINAL | H1: DATA_FINAL_MAXIMA | I1: VALOR TOTAL
B2: =IFERROR(VLOOKUP($A2,EVENTO!$A$2:$C$4999,2,FALSE),"") | C2: =IFERROR(VLOOKUP($A2,EVENTO!$A$2:$C$4999,3,FALSE),"")
B3: =IFERROR(VLOOKUP($A3,EVENTO!$A$2:$C$4999,2,FALSE),"") | C3: =IFERROR(VLOOKUP($A3,EVENTO!$A$2:$C$4999,3,FALSE),"")
B4: =IFERROR(VLOOKUP($A4,EVENTO!$A$2:$C$4999,2,FALSE),"") | C4: =IFERROR(VLOOKUP($A4,EVENTO!$A$2:$C$4999,3,FALSE),"")
A5: 6 | B5: =IFERROR(VLOOKUP($A5,EVENTO!$A$2:$C$4999,2,FALSE),"") -> CADASTRO | C5: =IFERROR(VLOOKUP($A5,EVENTO!$A$2:$C$4999,3,FALSE),"") -> ALECE | D5: 45918 | E5: 12 | F5: 120 | G5: 46251 | H5: 49538 | I5: 1557184.6
A6: 7 | B6: =IFERROR(VLOOKUP($A6,EVENTO!$A$2:$C$4999,2,FALSE),"") -> ADITIVO DE QUANTIDADE | C6: =IFERROR(VLOOKUP($A6,EVENTO!$A$2:$C$4999,3,FALSE),"") -> ALECE | D6: 45992 | E6: 9 | F6: 120 | G6: 46286 | H6: 49538 | I6: 312999.6
A7: 8 | B7: =IFERROR(VLOOKUP($A7,EVENTO!$A$2:$C$4999,2,FALSE),"") -> CADASTRO | C7: =IFERROR(VLOOKUP($A7,EVENTO!$A$2:$C$4999,3,FALSE),"") -> 10a REGIAO MILITAR | D7: 45336 | E7: 12 | F7: 48 | G7: 45702 | H7: 46797 | I7: 34044
A8: 9 | B8: =IFERROR(VLOOKUP($A8,EVENTO!$A$2:$C$4999,2,FALSE),"") -> ADITIVO DE REAJUSTE E PRAZO | C8: =IFERROR(VLOOKUP($A8,EVENTO!$A$2:$C$4999,3,FALSE),"") -> 10a REGIAO MILITAR | D8: 45703 | E8: 12 | F8: 36 | G8: 46067 | H8: 46797 | I8: 35311.2
A9: 10 | B9: =IFERROR(VLOOKUP($A9,EVENTO!$A$2:$C$4999,2,FALSE),"") -> CADASTRO | C9: =IFERROR(VLOOKUP($A9,EVENTO!$A$2:$C$4999,3,FALSE),"") -> CMFOR | D9: 45197 | E9: 12 | F9: 120 | G9: 45563 | H9: 48850 | I9: 35341.2
A10: 11 | B10: =IFERROR(VLOOKUP($A10,EVENTO!$A$2:$C$4999,2,FALSE),"") -> ADITIVO DE REAJUSTE E PRAZO | C10: =IFERROR(VLOOKUP($A10,EVENTO!$A$2:$C$4999,3,FALSE),"") -> CMFOR | D10: 45564 | E10: 12 | F10: 120 | G10: 45928 | H10: 48850 | I10: 36816.96
A11: 12 | B11: =IFERROR(VLOOKUP($A11,EVENTO!$A$2:$C$4999,2,FALSE),"") -> ADITIVO DE REAJUSTE E PRAZO | C11: =IFERROR(VLOOKUP($A11,EVENTO!$A$2:$C$4999,3,FALSE),"") -> CMFOR | D11: 45929 | E11: 12 | F11: 120 | G11: 46293 | H11: 48850 | I11: 39051.72
A12: 13 | B12: =IFERROR(VLOOKUP($A12,EVENTO!$A$2:$C$4999,2,FALSE),"") -> CADASTRO | C12: =IFERROR(VLOOKUP($A12,EVENTO!$A$2:$C$4999,3,FALSE),"") -> ESCOLA DE APRENDIZEM DE MARINHEIROS DO CEARÁ | D12: 45331 | E12: 12 | F12: 60 | G12: 45330 | H12: 47157 | I12: 6000
A13: 14 | B13: =IFERROR(VLOOKUP($A13,EVENTO!$A$2:$C$4999,2,FALSE),"") -> ADITIVO DE REAJUSTE E PRAZO | C13: =IFERROR(VLOOKUP($A13,EVENTO!$A$2:$C$4999,3,FALSE),"") -> ESCOLA DE APRENDIZEM DE MARINHEIROS DO CEARÁ | D13: 45710 | E13: 12 | F13: 60 | G13: 46075 | H13: 47157 | I13: 6384
A14: 15 | B14: =IFERROR(VLOOKUP($A14,EVENTO!$A$2:$C$4999,2,FALSE),"") -> CADASTRO | C14: =IFERROR(VLOOKUP($A14,EVENTO!$A$2:$C$4999,3,FALSE),"") -> UFC | D14: 45314 | E14: 12 | F14: 60 | G14: 45679 | H14: 47140 | I14: 182773.68
A15: 16 | B15: =IFERROR(VLOOKUP($A15,EVENTO!$A$2:$C$4999,2,FALSE),"") -> ADITIVO DE PRAZO | C15: =IFERROR(VLOOKUP($A15,EVENTO!$A$2:$C$4999,3,FALSE),"") -> UFC | D15: 45681 | E15: 12 | F15: 60 | G15: 46046 | H15: 47140 | I15: 182773.68
A16: 17 | B16: =IFERROR(VLOOKUP($A16,EVENTO!$A$2:$C$4999,2,FALSE),"") -> APOSTILAMENTO | C16: =IFERROR(VLOOKUP($A16,EVENTO!$A$2:$C$4999,3,FALSE),"") -> UFC | D16: 45658 | E16: 12 | F16: 60 | G16: 46022 | H16: 47140 | I16: 191604.02
... A29: 30 | B29: =IFERROR(VLOOKUP($A29,EVENTO!$A$2:$C$4999,2,FALSE),"") -> CADASTRO | C29: =IFERROR(VLOOKUP($A29,EVENTO!$A$2:$C$4999,3,FALSE),"") -> CAPITANIA DOS PORTOS DE SERGIPE | D29: 45516 | E29: 12 | F29: 60 | G29: 45882 | H29: 47343 | I29: 21480
A30: 31 | B30: =IFERROR(VLOOKUP($A30,EVENTO!$A$2:$C$4999,2,FALSE),"") -> ADITIVO DE REAJUSTE E PRAZO | C30: =IFERROR(VLOOKUP($A30,EVENTO!$A$2:$C$4999,3,FALSE),"") -> CAPITANIA DOS PORTOS DE SERGIPE | D30: 45883 | E30: 12 | F30: 60 | G30: 46247 | H30: 47343 | I30: 22667.84 | AA30: /
A31: 32 | B31: =IFERROR(VLOOKUP($A31,EVENTO!$A$2:$C$4999,2,FALSE),"") -> CADASTRO | C31: =IFERROR(VLOOKUP($A31,EVENTO!$A$2:$C$4999,3,FALSE),"") -> IFRN CAMPUS CEARÁ-MIRIM | D31: 45429 | E31: 12 | F31: 60 | G31: 45794 | H31: 47255 | I31: 15798
A32: 33 | B32: =IFERROR(VLOOKUP($A32,EVENTO!$A$2:$C$4999,2,FALSE),"") -> ADITIVO DE REAJUSTE E PRAZO | C32: =IFERROR(VLOOKUP($A32,EVENTO!$A$2:$C$4999,3,FALSE),"") -> IFRN CAMPUS CEARÁ-MIRIM | D32: 45794 | E32: 12 | F32: 60 | G32: 46159 | H32: 47255 | I32: 16705.2
A33: 34 | B33: =IFERROR(VLOOKUP($A33,EVENTO!$A$2:$C$4999,2,FALSE),"") -> CADASTRO | C33: =IFERROR(VLOOKUP($A33,EVENTO!$A$2:$C$4999,3,FALSE),"") -> IFRN CAMPUS NATAL | D33: 45597 | E33: 12 | F33: 60 | G33: 45961 | H33: 47422 | I33: 24900
A34: 35 | B34: =IFERROR(VLOOKUP($A34,EVENTO!$A$2:$C$4999,2,FALSE),"") -> ADITIVO DE REAJUSTE E PRAZO | C34: =IFERROR(VLOOKUP($A34,EVENTO!$A$2:$C$4999,3,FALSE),"") -> IFRN CAMPUS NATAL | D34: 46326 | E34: 12 | F34: 60 | G34: 46326 | H34: 47422 | I34: 26091.51
A35: 36 | B35: =IFERROR(VLOOKUP($A35,EVENTO!$A$2:$C$4999,2,FALSE),"") -> CADASTRO | C35: =IFERROR(VLOOKUP($A35,EVENTO!$A$2:$C$4999,3,FALSE),"") -> TRE RJ | D35: 45355 | E35: 24 | F35: 60 | G35: 46084 | H35: 47180 | I35: 1540816.5
A36: 37 | B36: =IFERROR(VLOOKUP($A36,EVENTO!$A$2:$C$4999,2,FALSE),"") -> CADASTRO | C36: =IFERROR(VLOOKUP($A36,EVENTO!$A$2:$C$4999,3,FALSE),"") -> DELEGACIA DA CAPITANIA DE SÃO FRANCISCO DO SUL | D36: 45677 | E36: 24 | F36: 60 | G36: 46406 | H36: 47502 | I36: 28430.4
A37: 38 | B37: =IFERROR(VLOOKUP($A37,EVENTO!$A$2:$C$4999,2,FALSE),"") -> CADASTRO | C37: =IFERROR(VLOOKUP($A37,EVENTO!$A$2:$C$4999,3,FALSE),"") -> DELEGACIA DA CAPITANIA DOS PORTOS EM ITAJAÍ | D37: 45696 | E37: 48 | F37: 60 | G37: 47156 | H37: 47521 | I37: 883987.2
A38: 39 | B38: =IFERROR(VLOOKUP($A38,EVENTO!$A$2:$C$4999,2,FALSE),"") -> CADASTRO | C38: =IFERROR(VLOOKUP($A38,EVENTO!$A$2:$C$4999,3,FALSE),"") -> SUPERINTENDÊNCIA FEDERAL DE AGRICULTURA E PECUARIA NO ESTADO DE SANTA CATARINA - SFA-SC | D38: 45536 | E38: 48 | F38: 60 | G38: 46996 | H38: 47361 | I38: 140517.12
A39: 40 | B39: =IFERROR(VLOOKUP($A39,EVENTO!$A$2:$C$4999,2,FALSE),"") -> CADASTRO | C39: =IFERROR(VLOOKUP($A39,EVENTO!$A$2:$C$4999,3,FALSE),"") -> UFSC | D39: 45429 | E39: 48 | F39: 60 | G39: 46890 | H39: 47255 | I39: 4774152
A40: 41 | B40: =IFERROR(VLOOKUP($A40,EVENTO!$A$2:$C$4999,2,FALSE),"") -> CADASTRO | C40: =IFERROR(VLOOKUP($A40,EVENTO!$A$2:$C$4999,3,FALSE),"") -> BASE ADMINISTRATIVA DO QUARTEL-GENERAL DO EXÉRCITO | D40: 45785 | E40: 12 | F40: 120 | G40: 46149 | H40: 49436 | I40: 40128
A41: 42 | B41: =IFERROR(VLOOKUP($A41,EVENTO!$A$2:$C$4999,2,FALSE),"") -> CADASTRO | C41: =IFERROR(VLOOKUP($A41,EVENTO!$A$2:$C$4999,3,FALSE),"") -> MCID | D41: 45785 | E41: 12 | F41: 120 | G41: 46149 | H41: 49436 | I41: 74412.71
A42: 43 | B42: =IFERROR(VLOOKUP($A42,EVENTO!$A$2:$C$4999,2,FALSE),"") -> CADASTRO | C42: =IFERROR(VLOOKUP($A42,EVENTO!$A$2:$C$4999,3,FALSE),"") -> COTER | D42: 45839 | E42: 60 | F42: 120 | G42: 47664 | H42: 49490 | I42: 616118.4
... A68: 69 | B68: =IFERROR(VLOOKUP($A68,EVENTO!$A$2:$C$4999,2,FALSE),"") -> CADASTRO | C68: =IFERROR(VLOOKUP($A68,EVENTO!$A$2:$C$4999,3,FALSE),"") -> DETRAN MA | D68: 45506 | E68: 12 | F68: 60 | G68: 45870 | H68: 47331 | I68: 1855597.2
A69: 70 | B69: =IFERROR(VLOOKUP($A69,EVENTO!$A$2:$C$4999,2,FALSE),"") -> CADASTRO | C69: =IFERROR(VLOOKUP($A69,EVENTO!$A$2:$C$4999,3,FALSE),"") -> IPAM | D69: 44746 | E69: 12 | F69: 48 | G69: 45111 | H69: 46207 | I69: R$ 95.061,60
A70: 74 | B70: =IFERROR(VLOOKUP($A70,EVENTO!$A$2:$C$4999,2,FALSE),"") -> CADASTRO | C70: =IFERROR(VLOOKUP($A70,EVENTO!$A$2:$C$4999,3,FALSE),"") -> PCDF | D70: 45723 | E70: 60 | F70: 120 | G70: 47548 | H70: 49374 | I70: 10433984
A71: 71 | B71: =IFERROR(VLOOKUP($A71,EVENTO!$A$2:$C$4999,2,FALSE),"") -> ADITIVO DE QUANTIDADE E PRAZO | C71: =IFERROR(VLOOKUP($A71,EVENTO!$A$2:$C$4999,3,FALSE),"") -> IPAM | D71: 45111 | E71: 12 | F71: 48 | G71: 45477 | H71: 46207 | I71: 101550.96
A72: 75 | B72: =IFERROR(VLOOKUP($A72,EVENTO!$A$2:$C$4999,2,FALSE),"") -> CADASTRO | C72: =IFERROR(VLOOKUP($A72,EVENTO!$A$2:$C$4999,3,FALSE),"") -> HEMOCENTRO PB | D72: 45383 | E72: 12 | F72: 60 | G72: 45746 | H72: 47207 | I72: 25872
A73: 76 | B73: =IFERROR(VLOOKUP($A73,EVENTO!$A$2:$C$4999,2,FALSE),"") -> CADASTRO | C73: =IFERROR(VLOOKUP($A73,EVENTO!$A$2:$C$4999,3,FALSE),"") -> ALEMA | D73: 45190 | E73: 12 | F73: 60 | G73: 45555 | H73: 47016 | I73: 4083177.6
A74: 72 | B74: =IFERROR(VLOOKUP($A74,EVENTO!$A$2:$C$4999,2,FALSE),"") -> ADITIVO DE PRAZO | C74: =IFERROR(VLOOKUP($A74,EVENTO!$A$2:$C$4999,3,FALSE),"") -> IPAM | D74: 45477 | E74: 12 | F74: 48 | G74: 45842 | H74: 46207 | I74: 101550.96
A75: 77 | B75: =IFERROR(VLOOKUP($A75,EVENTO!$A$2:$C$4999,2,FALSE),"") -> ADITIVO DE REAJUSTE E PRAZO | C75: =IFERROR(VLOOKUP($A75,EVENTO!$A$2:$C$4999,3,FALSE),"") -> HEMOCENTRO PB | D75: 45748 | E75: 12 | F75: 60 | G75: 46111 | H75: 47207 | I75: 29568
A76: 73 | B76: =IFERROR(VLOOKUP($A76,EVENTO!$A$2:$C$4999,2,FALSE),"") -> ADITIVO DE REAJUSTE E PRAZO | C76: =IFERROR(VLOOKUP($A76,EVENTO!$A$2:$C$4999,3,FALSE),"") -> IPAM | D76: 45842 | E76: 12 | F76: 48 | G76: 46207 | H76: 46207 | I76: 110.989.44
A77: 78 | B77: =IFERROR(VLOOKUP($A77,EVENTO!$A$2:$C$4999,2,FALSE),"") -> CADASTRO | C77: =IFERROR(VLOOKUP($A77,EVENTO!$A$2:$C$4999,3,FALSE),"") -> SEAP-PB | D77: 45376 | E77: 12 | F77: 60 | G77: 45740 | H77: 47201 | I77: 58028
A78: 79 | B78: =IFERROR(VLOOKUP($A78,EVENTO!$A$2:$C$4999,2,FALSE),"") -> ADITIVO DE PRAZO | C78: =IFERROR(VLOOKUP($A78,EVENTO!$A$2:$C$4999,3,FALSE),"") -> ALEMA | D78: 45557 | E78: 12 | F78: 60 | G78: 45921 | H78: 47016 | I78: 4083177.6
A79: 80 | B79: =IFERROR(VLOOKUP($A79,EVENTO!$A$2:$C$4999,2,FALSE),"") -> ADITIVO DE REAJUSTE E PRAZO | C79: =IFERROR(VLOOKUP($A79,EVENTO!$A$2:$C$4999,3,FALSE),"") -> ALEMA | D79: 45922 | E79: 12 | F79: 60 | G79: 46286 | H79: 47016 | I79: 4262429.1
A80: 81 | B80: =IFERROR(VLOOKUP($A80,EVENTO!$A$2:$C$4999,2,FALSE),"") -> CADASTRO | C80: =IFERROR(VLOOKUP($A80,EVENTO!$A$2:$C$4999,3,FALSE),"") -> PCPB | D80: 45300 | E80: 48 | F80: 60 | G80: 46760 | H80: 47126 | I80: 1950450.7
A81: 82 | B81: =IFERROR(VLOOKUP($A81,EVENTO!$A$2:$C$4999,2,FALSE),"") -> ADITIVO DE QUANTIDADE E PRAZO | C81: =IFERROR(VLOOKUP($A81,EVENTO!$A$2:$C$4999,3,FALSE),"") -> SEAP-PB | D81: 45737 | E81: 12 | F81: 60 | G81: 46102 | H81: 47201 | I81: 68697.12
A82: 83 | B82: =IFERROR(VLOOKUP($A82,EVENTO!$A$2:$C$4999,2,FALSE),"") -> CADASTRO | C82: =IFERROR(VLOOKUP($A82,EVENTO!$A$2:$C$4999,3,FALSE),"") -> SETUR | D82: 45324 | E82: 48 | F82: 48 | G82: 46785 | H82: 46785 | I82: R$ 91.999,68
A83: 84 | B83: =IFERROR(VLOOKUP($A83,EVENTO!$A$2:$C$4999,2,FALSE),"") -> CADASTRO | C83: =IFERROR(VLOOKUP($A83,EVENTO!$A$2:$C$4999,3,FALSE),"") -> CITINOVA | D83: 44820 | E83: 12 | F83: 60 | G83: 45184 | H83: 46645 | I83: 278475.12
A84: 85 | B84: =IFERROR(VLOOKUP($A84,EVENTO!$A$2:$C$4999,2,FALSE),"") -> CADASTRO | C84: =IFERROR(VLOOKUP($A84,EVENTO!$A$2:$C$4999,3,FALSE),"") -> RESENDE / SMA | D84: 45369 | E84: 12 | F84: 60 | G84: 45734 | H84: 47195 | I84: 297358.08
A85: 86 | B85: =IFERROR(VLOOKUP($A85,EVENTO!$A$2:$C$4999,2,FALSE),"") -> CADASTRO | C85: =IFERROR(VLOOKUP($A85,EVENTO!$A$2:$C$4999,3,FALSE),"") -> SECRETARIA MUNICIPAL DE SEGURANÇA COM CIDADANIA−SEMUSC - 007-2022 | D85: 44749 | E85: 12 | F85: 48 | G85: 45114 | H85: 46210 | I85: R$ 89.200.80
A86: 87 | B86: =IFERROR(VLOOKUP($A86,EVENTO!$A$2:$C$4999,2,FALSE),"") -> ADITIVO DE PRAZO | C86: =IFERROR(VLOOKUP($A86,EVENTO!$A$2:$C$4999,3,FALSE),"") -> SECRETARIA MUNICIPAL DE SEGURANÇA COM CIDADANIA−SEMUSC - 007-2022 | D86: 45114 | E86: 12 | F86: 48 | G86: 45481 | H86: 46210 | I86: R$ 89.200.80
A87: 88 | B87: =IFERROR(VLOOKUP($A87,EVENTO!$A$2:$C$4999,2,FALSE),"") -> ADITIVO DE PRAZO | C87: =IFERROR(VLOOKUP($A87,EVENTO!$A$2:$C$4999,3,FALSE),"") -> SECRETARIA MUNICIPAL DE SEGURANÇA COM CIDADANIA−SEMUSC - 007-2022 | D87: 45481 | E87: 12 | F87: 48 | G87: 45847 | H87: 46210 | I87: R$ 89.200.80
A88: 89 | B88: =IFERROR(VLOOKUP($A88,EVENTO!$A$2:$C$4999,2,FALSE),"") -> APOSTILAMENTO | C88: =IFERROR(VLOOKUP($A88,EVENTO!$A$2:$C$4999,3,FALSE),"") -> SECRETARIA MUNICIPAL DE SEGURANÇA COM CIDADANIA−SEMUSC - 007-2022 | D88: 45881 | E88: 12 | F88: 48 | G88: 46210 | H88: 46210 | I88: R$ 94.932,96
A89: 90 | B89: =IFERROR(VLOOKUP($A89,EVENTO!$A$2:$C$4999,2,FALSE),"") -> ADITIVO DE PRAZO | C89: =IFERROR(VLOOKUP($A89,EVENTO!$A$2:$C$4999,3,FALSE),"") -> SECRETARIA MUNICIPAL DE SEGURANÇA COM CIDADANIA−SEMUSC - 007-2022 | D89: 45847 | E89: 12 | F89: 48 | G89: 46210 | H89: 46210 | I89: R$ 94.932,96
A90: 91 | B90: =IFERROR(VLOOKUP($A90,EVENTO!$A$2:$C$4999,2,FALSE),"") -> CADASTRO | C90: =IFERROR(VLOOKUP($A90,EVENTO!$A$2:$C$4999,3,FALSE),"") -> CAMARA DE HORTOLANDIA | D90: 45271 | E90: 12 | F90: 60 | G90: 45636 | H90: 47097 | I90: 175980
A91: 92 | B91: =IFERROR(VLOOKUP($A91,EVENTO!$A$2:$C$4999,2,FALSE),"") -> ADITIVO DE REAJUSTE E PRAZO | C91: =IFERROR(VLOOKUP($A91,EVENTO!$A$2:$C$4999,3,FALSE),"") -> CAMARA DE HORTOLANDIA | D91: 45637 | E91: 12 | F91: 60 | G91: 46001 | H91: 47097 | I91: 183838.56
A92: 93 | B92: =IFERROR(VLOOKUP($A92,EVENTO!$A$2:$C$4999,2,FALSE),"") -> ADITIVO DE REAJUSTE E PRAZO | C92: =IFERROR(VLOOKUP($A92,EVENTO!$A$2:$C$4999,3,FALSE),"") -> CAMARA DE HORTOLANDIA | D92: 46002 | E92: 12 | F92: 60 | G92: 46366 | H92: 47097 | I92: 191523.71
A93: 94 | B93: =IFERROR(VLOOKUP($A93,EVENTO!$A$2:$C$4999,2,FALSE),"") -> ADITIVO DE PRAZO | C93: =IFERROR(VLOOKUP($A93,EVENTO!$A$2:$C$4999,3,FALSE),"") -> RESENDE / SMA | D93: 45734 | E93: 12 | F93: 60 | G93: 46099 | H93: 47195 | I93: 297358.08
A94: 95 | B94: =IFERROR(VLOOKUP($A94,EVENTO!$A$2:$C$4999,2,FALSE),"") -> CADASTRO | C94: =IFERROR(VLOOKUP($A94,EVENTO!$A$2:$C$4999,3,FALSE),"") -> FMS PB | D94: 45188 | E94: 12 | F94: 60 | G94: 45554 | H94: 47015 | I94: R$ 490.742.28
A95: 98 | B95: =IFERROR(VLOOKUP($A95,EVENTO!$A$2:$C$4999,2,FALSE),"") -> ADITIVO DE REAJUSTE E PRAZO | C95: =IFERROR(VLOOKUP($A95,EVENTO!$A$2:$C$4999,3,FALSE),"") -> CITINOVA | D95: 45185 | E95: 12 | F95: 60 | G95: 45550 | H95: 46645 | I95: 316735.56
A96: 99 | B96: =IFERROR(VLOOKUP($A96,EVENTO!$A$2:$C$4999,2,FALSE),"") -> ADITIVO DE REAJUSTE E PRAZO | C96: =IFERROR(VLOOKUP($A96,EVENTO!$A$2:$C$4999,3,FALSE),"") -> CITINOVA | D96: 45551 | E96: 12 | F96: 60 | G96: 45915 | H96: 46645 | I96: 328834.86
A97: 100 | B97: =IFERROR(VLOOKUP($A97,EVENTO!$A$2:$C$4999,2,FALSE),"") -> ADITIVO DE PRAZO | C97: =IFERROR(VLOOKUP($A97,EVENTO!$A$2:$C$4999,3,FALSE),"") -> CITINOVA | D97: 45916 | E97: 12 | F97: 60 | G97: 46280 | H97: 46645 | I97: 328834.86
A98: 96 | B98: =IFERROR(VLOOKUP($A98,EVENTO!$A$2:$C$4999,2,FALSE),"") -> ADITIVO DE PRAZO | C98: =IFERROR(VLOOKUP($A98,EVENTO!$A$2:$C$4999,3,FALSE),"") -> FMS PB | D98: 45554 | E98: 12 | F98: 60 | G98: 45919 | H98: 47015 | I98: R$ 490.742.28
A99: 97 | B99: =IFERROR(VLOOKUP($A99,EVENTO!$A$2:$C$4999,2,FALSE),"") -> ADITIVO DE PRAZO | C99: =IFERROR(VLOOKUP($A99,EVENTO!$A$2:$C$4999,3,FALSE),"") -> FMS PB | D99: 45919 | E99: 12 | F99: 60 | G99: 46284 | H99: 47015 | I99: R$ 490.742.28
A100: 101 | B100: =IFERROR(VLOOKUP($A100,EVENTO!$A$2:$C$4999,2,FALSE),"") -> CADASTRO | C100: =IFERROR(VLOOKUP($A100,EVENTO!$A$2:$C$4999,3,FALSE),"") -> SEMCAS - 017-2022 | D100: 44806 | E100: 12 | F100: 48 | G100: 45171 | H100: 46267 | I100: R$ 672.870,48
A101: 102 | B101: =IFERROR(VLOOKUP($A101,EVENTO!$A$2:$C$4999,2,FALSE),"") -> ADITIVO DE PRAZO | C101: =IFERROR(VLOOKUP($A101,EVENTO!$A$2:$C$4999,3,FALSE),"") -> SEMCAS - 017-2022 | D101: 45171 | E101: 12 | F101: 48 | G101: 45537 | H101: 46267 | I101: R$ 672.870,48
A102: 103 | B102: =IFERROR(VLOOKUP($A102,EVENTO!$A$2:$C$4999,2,FALSE),"") -> ADITIVO DE QUANTIDADE | C102: =IFERROR(VLOOKUP($A102,EVENTO!$A$2:$C$4999,3,FALSE),"") -> SEMCAS - 017-2022 | D102: 45400 | E102: 12 | F102: 48 | G102: 45537 | H102: 46267 | I102: R$ 837.681,48
A103: 105 | B103: =IFERROR(VLOOKUP($A103,EVENTO!$A$2:$C$4999,2,FALSE),"") -> CADASTRO | C103: =IFERROR(VLOOKUP($A103,EVENTO!$A$2:$C$4999,3,FALSE),"") -> SEMCAS - 019-2022 | D103: 44824 | E103: 12 | F103: 48 | G103: 45188 | H103: 46284 | I103: 206164.8
A104: 104 | B104: =IFERROR(VLOOKUP($A104,EVENTO!$A$2:$C$4999,2,FALSE),"") -> ADITIVO DE PRAZO | C104: =IFERROR(VLOOKUP($A104,EVENTO!$A$2:$C$4999,3,FALSE),"") -> SEMCAS - 017-2022 | D104: 45537 | E104: 12 | F104: 48 | G104: 45902 | H104: 46267 | I104: R$ 837.681,48
A105: 106 | B105: =IFERROR(VLOOKUP($A105,EVENTO!$A$2:$C$4999,2,FALSE),"") -> ADITIVO DE REAJUSTE E PRAZO | C105: =IFERROR(VLOOKUP($A105,EVENTO!$A$2:$C$4999,3,FALSE),"") -> SEMCAS - 019-2022 | D105: 45902 | E105: 12 | F105: 48 | G105: 46267 | H105: 46267 | I105: R$ 860.032,58
A106: 107 | B106: =IFERROR(VLOOKUP($A106,EVENTO!$A$2:$C$4999,2,FALSE),"") -> ADITIVO DE PRAZO | C106: =IFERROR(VLOOKUP($A106,EVENTO!$A$2:$C$4999,3,FALSE),"") -> SEMCAS - 019-2022 | D106: 45189 | E106: 12 | F106: 48 | G106: 45555 | H106: 46285 | I106: 206164.8
A107: 108 | B107: =IFERROR(VLOOKUP($A107,EVENTO!$A$2:$C$4999,2,FALSE),"") -> ADITIVO DE PRAZO | C107: =IFERROR(VLOOKUP($A107,EVENTO!$A$2:$C$4999,3,FALSE),"") -> SEMCAS - 019-2022 | D107: 45555 | E107: 12 | F107: 48 | G107: 45920 | H107: 46285 | I107: 206164.8
A108: 109 | B108: =IFERROR(VLOOKUP($A108,EVENTO!$A$2:$C$4999,2,FALSE),"") -> ADITIVO DE PRAZO | C108: =IFERROR(VLOOKUP($A108,EVENTO!$A$2:$C$4999,3,FALSE),"") -> SEMCAS - 019-2022 | D108: 45920 | E108: 12 | F108: 48 | G108: 46285 | H108: 46285 | I108: 212421.6
A109: 110 | B109: =IFERROR(VLOOKUP($A109,EVENTO!$A$2:$C$4999,2,FALSE),"") -> CADASTRO | C109: =IFERROR(VLOOKUP($A109,EVENTO!$A$2:$C$4999,3,FALSE),"") -> PREFEITURA MUNICIPAL DE ARACATI - CASA CIVIL | D109: 44664 | E109: 12 | F109: 60 | G109: 45029 | H109: 46490 | I109: R$ 177.670,20
A110: 111 | B110: =IFERROR(VLOOKUP($A110,EVENTO!$A$2:$C$4999,2,FALSE),"") -> ADITIVO DE PRAZO | C110: =IFERROR(VLOOKUP($A110,EVENTO!$A$2:$C$4999,3,FALSE),"") -> PREFEITURA MUNICIPAL DE ARACATI - CASA CIVIL | D110: 45029 | E110: 12 | F110: 60 | G110: 45395 | H110: 46490 | I110: R$ 177.670,20
A111: 112 | B111: =IFERROR(VLOOKUP($A111,EVENTO!$A$2:$C$4999,2,FALSE),"") -> ADITIVO DE PRAZO | C111: =IFERROR(VLOOKUP($A111,EVENTO!$A$2:$C$4999,3,FALSE),"") -> PREFEITURA MUNICIPAL DE ARACATI - CASA CIVIL | D111: 45396 | E111: 9 | F111: 60 | G111: 45657 | H111: 46490 | I111: R$ 133.252.65
A112: 115 | B112: =IFERROR(VLOOKUP($A112,EVENTO!$A$2:$C$4999,2,FALSE),"") -> ADITIVO DE PRAZO | C112: =IFERROR(VLOOKUP($A112,EVENTO!$A$2:$C$4999,3,FALSE),"") -> UFC | D112: 46047 | E112: 12 | F112: 60 | G112: 46412 | H112: 47140 | I112: 191604.02
A113: 116 | B113: =IFERROR(VLOOKUP($A113,EVENTO!$A$2:$C$4999,2,FALSE),"") -> CADASTRO | C113: =IFERROR(VLOOKUP($A113,EVENTO!$A$2:$C$4999,3,FALSE),"") -> PREF. MUNICIPAL DE CANINDE - AGRICULTURA | D113: 45198 | E113: 12 | F113: 60 | G113: 45563 | H113: 47024 | I113: 8428.44
A114: 113 | B114: =IFERROR(VLOOKUP($A114,EVENTO!$A$2:$C$4999,2,FALSE),"") -> ADITIVO DE PRAZO | C114: =IFERROR(VLOOKUP($A114,EVENTO!$A$2:$C$4999,3,FALSE),"") -> PREFEITURA MUNICIPAL DE ARACATI - CASA CIVIL | D114: 45658 | E114: 6 | F114: 60 | G114: 45838 | H114: 46490 | I114: 85240
A115: 114 | B115: =IFERROR(VLOOKUP($A115,EVENTO!$A$2:$C$4999,2,FALSE),"") -> ADITIVO DE PRAZO | C115: =IFERROR(VLOOKUP($A115,EVENTO!$A$2:$C$4999,3,FALSE),"") -> PREFEITURA MUNICIPAL DE ARACATI - CASA CIVIL | D115: 45839 | E115: 4 | F115: 60 | G115: 45961 | H115: 46490 | I115: 58415.6
A116: 117 | B116: =IFERROR(VLOOKUP($A116,EVENTO!$A$2:$C$4999,2,FALSE),"") -> ADITIVO DE PRAZO | C116: =IFERROR(VLOOKUP($A116,EVENTO!$A$2:$C$4999,3,FALSE),"") -> PREFEITURA MUNICIPAL DE ARACATI - CASA CIVIL | D116: 45962 | E116: 3 | F116: 60 | G116: 46053 | H116: 46490 | I116: 43819.17
A117: 118 | B117: =IFERROR(VLOOKUP($A117,EVENTO!$A$2:$C$4999,2,FALSE),"") -> ADITIVO DE PRAZO | C117: =IFERROR(VLOOKUP($A117,EVENTO!$A$2:$C$4999,3,FALSE),"") -> PREF. MUNICIPAL DE CANINDE - AGRICULTURA | D117: 45565 | E117: 12 | F117: 60 | G117: 45930 | H117: 47024 | I117: 8428.44
A118: 119 | B118: =IFERROR(VLOOKUP($A118,EVENTO!$A$2:$C$4999,2,FALSE),"") -> ADITIVO DE PRAZO | C118: =IFERROR(VLOOKUP($A118,EVENTO!$A$2:$C$4999,3,FALSE),"") -> PREF. MUNICIPAL DE CANINDE - AGRICULTURA | D118: 45565 | E118: 2 | F118: 60 | G118: 45992 | H118: 47024 | I118: 8428.44
A119: 120 | B119: =IFERROR(VLOOKUP($A119,EVENTO!$A$2:$C$4999,2,FALSE),"") -> CADASTRO | C119: =IFERROR(VLOOKUP($A119,EVENTO!$A$2:$C$4999,3,FALSE),"") -> PREF. MUNICIPAL DE ARACATI - SEGURANÇA CIDADÃ - 017-2022 | D119: 44664 | E119: 12 | F119: 60 | G119: 45029 | H119: 46490 | I119: 108712.92
A120: 121 | B120: =IFERROR(VLOOKUP($A120,EVENTO!$A$2:$C$4999,2,FALSE),"") -> ADITIVO DE PRAZO | C120: =IFERROR(VLOOKUP($A120,EVENTO!$A$2:$C$4999,3,FALSE),"") -> PREF. MUNICIPAL DE ARACATI - SEGURANÇA CIDADÃ - 017-2022 | D120: 45030 | E120: 12 | F120: 60 | G120: 45396 | H120: 46490 | I120: 108712.92
A121: 122 | B121: =IFERROR(VLOOKUP($A121,EVENTO!$A$2:$C$4999,2,FALSE),"") -> ADITIVO DE PRAZO | C121: =IFERROR(VLOOKUP($A121,EVENTO!$A$2:$C$4999,3,FALSE),"") -> PREF. MUNICIPAL DE ARACATI - SEGURANÇA CIDADÃ - 017-2022 | D121: 45396 | E121: 9 | F121: 60 | G121: 45657 | H121: 46490 | I121: 77897.43
A122: 123 | B122: =IFERROR(VLOOKUP($A122,EVENTO!$A$2:$C$4999,2,FALSE),"") -> ADITIVO DE PRAZO | C122: =IFERROR(VLOOKUP($A122,EVENTO!$A$2:$C$4999,3,FALSE),"") -> PREF. MUNICIPAL DE ARACATI - SEGURANÇA CIDADÃ - 017-2022 | D122: 45658 | E122: 6 | F122: 60 | G122: 45838 | H122: 46490 | I122: 51931.62
A123: 124 | B123: =IFERROR(VLOOKUP($A123,EVENTO!$A$2:$C$4999,2,FALSE),"") -> ADITIVO DE PRAZO | C123: =IFERROR(VLOOKUP($A123,EVENTO!$A$2:$C$4999,3,FALSE),"") -> PREF. MUNICIPAL DE ARACATI - SEGURANÇA CIDADÃ - 017-2022 | D123: 45839 | E123: 4 | F123: 60 | G123: 45961 | H123: 46490 | I123: 34621.08
... A180: 181 | B180: =IFERROR(VLOOKUP($A180,EVENTO!$A$2:$C$4999,2,FALSE),"") -> CADASTRO | C180: =IFERROR(VLOOKUP($A180,EVENTO!$A$2:$C$4999,3,FALSE),"") -> Hospital Municipal Dr. Augeu Braga Herbster | D180: 45719 | E180: 12 | F180: 120 | G180: 45718 | H180: 49370 | I180: 22221.24
B181: =IFERROR(VLOOKUP($A181,EVENTO!$A$2:$C$4999,2,FALSE),"") | C181: =IFERROR(VLOOKUP($A181,EVENTO!$A$2:$C$4999,3,FALSE),"")
A182: 183 | B182: =IFERROR(VLOOKUP($A182,EVENTO!$A$2:$C$4999,2,FALSE),"") -> CADASTRO | C182: =IFERROR(VLOOKUP($A182,EVENTO!$A$2:$C$4999,3,FALSE),"") -> PREFEITURA MUNICIPAL DE ARACATI - DESENVOLVIMENTO AGRÁRIO | D182: 44664 | E182: 12 | F182: 60 | G182: 45029 | H182: 46490 | I182: 111011.28
A183: 189 | B183: =IFERROR(VLOOKUP($A183,EVENTO!$A$2:$C$4999,2,FALSE),"") -> CADASTRO | C183: =IFERROR(VLOOKUP($A183,EVENTO!$A$2:$C$4999,3,FALSE),"") -> PREFEITURA MUNICIPAL DE MARANGUAPE - EDUCAÇÃO | D183: 45719 | E183: 12 | F183: 120 | G183: 45718 | H183: 49370 | I183: 120634.8
A184: 190 | B184: =IFERROR(VLOOKUP($A184,EVENTO!$A$2:$C$4999,2,FALSE),"") -> CADASTRO | C184: =IFERROR(VLOOKUP($A184,EVENTO!$A$2:$C$4999,3,FALSE),"") -> CÂMARA MUNICIPAL DE CAUCAIA | D184: 44820 | E184: 12 | F184: 60 | G184: 45184 | H184: 46645 | I184: 137007.96
A185: 191 | B185: =IFERROR(VLOOKUP($A185,EVENTO!$A$2:$C$4999,2,FALSE),"") -> ADITIVO DE PRAZO | C185: =IFERROR(VLOOKUP($A185,EVENTO!$A$2:$C$4999,3,FALSE),"") -> CÂMARA MUNICIPAL DE CAUCAIA | D185: 45184 | E185: 12 | F185: 60 | G185: 45550 | H185: 46645 | I185: 137007.96
A186: 192 | B186: =IFERROR(VLOOKUP($A186,EVENTO!$A$2:$C$4999,2,FALSE),"") -> ADITIVO DE PRAZO | C186: =IFERROR(VLOOKUP($A186,EVENTO!$A$2:$C$4999,3,FALSE),"") -> CÂMARA MUNICIPAL DE CAUCAIA | D186: 45548 | E186: 12 | F186: 60 | G186: 45913 | H186: 46645 | I186: 137007.96
A187: 193 | B187: =IFERROR(VLOOKUP($A187,EVENTO!$A$2:$C$4999,2,FALSE),"") -> ADITIVO DE PRAZO | C187: =IFERROR(VLOOKUP($A187,EVENTO!$A$2:$C$4999,3,FALSE),"") -> CÂMARA MUNICIPAL DE CAUCAIA | D187: 45912 | E187: 12 | F187: 60 | G187: 46277 | H187: 46645 | I187: 137007.96
A188: 184 | B188: =IFERROR(VLOOKUP($A188,EVENTO!$A$2:$C$4999,2,FALSE),"") -> ADITIVO DE PRAZO | C188: =IFERROR(VLOOKUP($A188,EVENTO!$A$2:$C$4999,3,FALSE),"") -> PREFEITURA MUNICIPAL DE ARACATI - DESENVOLVIMENTO AGRÁRIO | D188: 45029 | E188: 12 | F188: 60 | G188: 45395 | H188: 46490 | I188: 111011.28
A189: 185 | B189: =IFERROR(VLOOKUP($A189,EVENTO!$A$2:$C$4999,2,FALSE),"") -> ADITIVO DE PRAZO | C189: =IFERROR(VLOOKUP($A189,EVENTO!$A$2:$C$4999,3,FALSE),"") -> PREFEITURA MUNICIPAL DE ARACATI - DESENVOLVIMENTO AGRÁRIO | D189: 45658 | E189: 6 | F189: 60 | G189: 45838 | H189: 46490 | I189: 55505.67
A190: 186 | B190: =IFERROR(VLOOKUP($A190,EVENTO!$A$2:$C$4999,2,FALSE),"") -> ADITIVO DE PRAZO | C190: =IFERROR(VLOOKUP($A190,EVENTO!$A$2:$C$4999,3,FALSE),"") -> PREFEITURA MUNICIPAL DE ARACATI - DESENVOLVIMENTO AGRÁRIO | D190: 45839 | E190: 4 | F190: 60 | G190: 45961 | H190: 46490 | I190: 37003.76
A191: 187 | B191: =IFERROR(VLOOKUP($A191,EVENTO!$A$2:$C$4999,2,FALSE),"") -> ADITIVO DE PRAZO | C191: =IFERROR(VLOOKUP($A191,EVENTO!$A$2:$C$4999,3,FALSE),"") -> PREFEITURA MUNICIPAL DE ARACATI - DESENVOLVIMENTO AGRÁRIO | D191: 45962 | E191: 3 | F191: 60 | G191: 46053 | H191: 46490 | I191: 27752.82
A192: 194 | B192: =IFERROR(VLOOKUP($A192,EVENTO!$A$2:$C$4999,2,FALSE),"") -> CADASTRO | C192: =IFERROR(VLOOKUP($A192,EVENTO!$A$2:$C$4999,3,FALSE),"") -> PREFEITURA MUNICIPAL DE ARACATI - DESENV ECON, TRAB E RENDA | D192: 44664 | E192: 12 | F192: 60 | G192: 45029 | H192: 46490 | I192: 143199
A193: 182 | B193: =IFERROR(VLOOKUP($A193,EVENTO!$A$2:$C$4999,2,FALSE),"") -> CADASTRO | C193: =IFERROR(VLOOKUP($A193,EVENTO!$A$2:$C$4999,3,FALSE),"") -> PREFEITURA MUNICIPAL DE MARANGUAPE - AGRICULTURA, PESCA E RECURSOS HÍDRICOS | D193: 45719 | E193: 12 | F193: 120 | G193: 45718 | H193: 49370 | I193: 13333.2
...

Sheet ITENS
A1: EVENTO | B1: TIPO_EVENTO | C1: CONTRATO | D1: APELIDO | E1: DESCRICAO | F1: QUANTIDADE | G1: VALOR_UNITARIO
B2: =IFERROR(VLOOKUP($A2,EVENTO!$A$2:$C$4999,2,FALSE),"") | C2: =IFERROR(VLOOKUP($A2,EVENTO!$A$2:$C$4999,3,FALSE),"")
B3: =IFERROR(VLOOKUP($A3,EVENTO!$A$2:$C$4999,2,FALSE),"") | C3: =IFERROR(VLOOKUP($A3,EVENTO!$A$2:$C$4999,3,FALSE),"")
B4: =IFERROR(VLOOKUP($A4,EVENTO!$A$2:$C$4999,2,FALSE),"") | C4: =IFERROR(VLOOKUP($A4,EVENTO!$A$2:$C$4999,3,FALSE),"")
B5: =IFERROR(VLOOKUP($A5,EVENTO!$A$2:$C$4999,2,FALSE),"") | C5: =IFERROR(VLOOKUP($A5,EVENTO!$A$2:$C$4999,3,FALSE),"")
B6: =IFERROR(VLOOKUP($A6,EVENTO!$A$2:$C$4999,2,FALSE),"") | C6: =IFERROR(VLOOKUP($A6,EVENTO!$A$2:$C$4999,3,FALSE),"")
A7: 6 | B7: =IFERROR(VLOOKUP($A7,EVENTO!$A$2:$C$4999,2,FALSE),"") -> CADASTRO | C7: =IFERROR(VLOOKUP($A7,EVENTO!$A$2:$C$4999,3,FALSE),"") -> ALECE | D7: NOBREAK 700 VA | E7: FORCE LINE 0010400008 – UPS MAX SECURITY 700VA 115V | F7: 30 | G7: 42.25
A8: 6 | B8: =IFERROR(VLOOKUP($A8,EVENTO!$A$2:$C$4999,2,FALSE),"") -> CADASTRO | C8: =IFERROR(VLOOKUP($A8,EVENTO!$A$2:$C$4999,3,FALSE),"") -> ALECE | D8: NOBREAK 1,5 KVA | E8: FORCE LINE UPS OFFICE SECURITY PLUS 1500VA | F8: 20 | G8: 141.49
A9: 6 | B9: =IFERROR(VLOOKUP($A9,EVENTO!$A$2:$C$4999,2,FALSE),"") -> CADASTRO | C9: =IFERROR(VLOOKUP($A9,EVENTO!$A$2:$C$4999,3,FALSE),"") -> ALECE | D9: NOBREAK 3 KVA | E9: SMS POWER VISION NG 3000 VA | F9: 7 | G9: 390.98
A10: 6 | B10: =IFERROR(VLOOKUP($A10,EVENTO!$A$2:$C$4999,2,FALSE),"") -> CADASTRO | C10: =IFERROR(VLOOKUP($A10,EVENTO!$A$2:$C$4999,3,FALSE),"") -> ALECE | D10: NOBREAK 30 KVA | E10: NOBREAK 30 KVA TRIFÁSICO SCHNEIDER CLASSIC DSP | F10: 2 | G10: 3430.81
A11: 6 | B11: =IFERROR(VLOOKUP($A11,EVENTO!$A$2:$C$4999,2,FALSE),"") -> CADASTRO | C11: =IFERROR(VLOOKUP($A11,EVENTO!$A$2:$C$4999,3,FALSE),"") -> ALECE | D11: MONITOR | E11: DELL PRO 27 PLUS - P2724DEB | F11: 20 | G11: 73.78
A12: 6 | B12: =IFERROR(VLOOKUP($A12,EVENTO!$A$2:$C$4999,2,FALSE),"") -> CADASTRO | C12: =IFERROR(VLOOKUP($A12,EVENTO!$A$2:$C$4999,3,FALSE),"") -> ALECE | D12: NOTEBOOK TIPO 1 | E12: LENOVO E14 G2, I3-1115G, 256SSD, 8GB RAM | F12: 50 | G12: 249
A13: 6 | B13: =IFERROR(VLOOKUP($A13,EVENTO!$A$2:$C$4999,2,FALSE),"") -> CADASTRO | C13: =IFERROR(VLOOKUP($A13,EVENTO!$A$2:$C$4999,3,FALSE),"") -> ALECE | D13: NOTEBOOK TIPO 2 | E13: DELL LATITUDE 3450 + I7-1355U + 32GB RAM | F13: 10 | G13: 389
A14: 6 | B14: =IFERROR(VLOOKUP($A14,EVENTO!$A$2:$C$4999,2,FALSE),"") -> CADASTRO | C14: =IFERROR(VLOOKUP($A14,EVENTO!$A$2:$C$4999,3,FALSE),"") -> ALECE | D14: MICROCOMPUTADOR TIPO 1 | E14: LENOVO THINKCENTRE M70S, I5-10400, 8GB, SSD 512GB, WINDOWS 10 PRO, MOUSE E TECLADO USB LENOVO + MONITOR 21.5" LENOVO THINKVISION S22E-19 | F14: 200 | G14: 278.85
A15: 6 | B15: =IFERROR(VLOOKUP($A15,EVENTO!$A$2:$C$4999,2,FALSE),"") -> CADASTRO | C15: =IFERROR(VLOOKUP($A15,EVENTO!$A$2:$C$4999,3,FALSE),"") -> ALECE | D15: MICROCOMPUTADOR TIPO 2 | E15: LENOVO THINKCENTRE_M70S, I7-10700, 8GB, SSD 512GB, WINDOWS 10 PRO, MOUSE E TECLADO USB LENOVO + MONITOR 21.5" LENOVO THINKVISION T22I-20 | F15: 85 | G15: 330.2
A16: 6 | B16: =IFERROR(VLOOKUP($A16,EVENTO!$A$2:$C$4999,2,FALSE),"") -> CADASTRO | C16: =IFERROR(VLOOKUP($A16,EVENTO!$A$2:$C$4999,3,FALSE),"") -> ALECE | D16: MICROCOMPUTADOR TIPO 3 | E16: LENOVO WORDKSTATION P340 TWR, XEON W-1250, 32GB, SSD 256GB, GPU DIDICADA 2GB DDR5, MOUSE E TECLADO USB LENOVO + MONITOR 24,5 LENOVO LEGION Y25-25 | F16: 20 | G16: 720.85
A17: 7 | B17: =IFERROR(VLOOKUP($A17,EVENTO!$A$2:$C$4999,2,FALSE),"") -> ADITIVO DE QUANTIDADE | C17: =IFERROR(VLOOKUP($A17,EVENTO!$A$2:$C$4999,3,FALSE),"") -> ALECE | D17: NOBREAK 700 VA | E17: FORCE LINE 0010400008 – UPS MAX SECURITY 700VA 115V | F17: 30 | G17: 42.25
A18: 7 | B18: =IFERROR(VLOOKUP($A18,EVENTO!$A$2:$C$4999,2,FALSE),"") -> ADITIVO DE QUANTIDADE | C18: =IFERROR(VLOOKUP($A18,EVENTO!$A$2:$C$4999,3,FALSE),"") -> ALECE | D18: NOBREAK 1,5 KVA | E18: FORCE LINE UPS OFFICE SECURITY PLUS 1500VA | F18: 20 | G18: 141.49
... A21: 7 | B21: =IFERROR(VLOOKUP($A21,EVENTO!$A$2:$C$4999,2,FALSE),"") -> ADITIVO DE QUANTIDADE | C21: =IFERROR(VLOOKUP($A21,EVENTO!$A$2:$C$4999,3,FALSE),"") -> ALECE | D21: MONITOR | E21: DELL PRO 27 PLUS - P2724DEB | F21: 20 | G21: 73.78
A22: 7 | B22: =IFERROR(VLOOKUP($A22,EVENTO!$A$2:$C$4999,2,FALSE),"") -> ADITIVO DE QUANTIDADE | C22: =IFERROR(VLOOKUP($A22,EVENTO!$A$2:$C$4999,3,FALSE),"") -> ALECE | D22: NOTEBOOK TIPO 1 | E22: LENOVO E14 G2, I3-1115G, 256SSD, 8GB RAM | F22: =50+40 -> 90 | G22: 249
A23: 7 | B23: =IFERROR(VLOOKUP($A23,EVENTO!$A$2:$C$4999,2,FALSE),"") -> ADITIVO DE QUANTIDADE | C23: =IFERROR(VLOOKUP($A23,EVENTO!$A$2:$C$4999,3,FALSE),"") -> ALECE | D23: NOTEBOOK TIPO 2 | E23: DELL LATITUDE 3450 + I7-1355U + 32GB RAM | F23: 10 | G23: 389
A24: 7 | B24: =IFERROR(VLOOKUP($A24,EVENTO!$A$2:$C$4999,2,FALSE),"") -> ADITIVO DE QUANTIDADE | C24: =IFERROR(VLOOKUP($A24,EVENTO!$A$2:$C$4999,3,FALSE),"") -> ALECE | D24: MICROCOMPUTADOR TIPO 1 | E24: LENOVO THINKCENTRE M70S, I5-10400, 8GB, SSD 512GB, WINDOWS 10 PRO, MOUSE E TECLADO USB LENOVO + MONITOR 21.5" LENOVO THINKVISION S22E-19 | F24: =200+80 -> 280 | G24: 278.85
A25: 7 | B25: =IFERROR(VLOOKUP($A25,EVENTO!$A$2:$C$4999,2,FALSE),"") -> ADITIVO DE QUANTIDADE | C25: =IFERROR(VLOOKUP($A25,EVENTO!$A$2:$C$4999,3,FALSE),"") -> ALECE | D25: MICROCOMPUTADOR TIPO 2 | E25: LENOVO THINKCENTRE_M70S, I7-10700, 8GB, SSD 512GB, WINDOWS 10 PRO, MOUSE E TECLADO USB LENOVO + MONITOR 21.5" LENOVO THINKVISION T22I-20 | F25: 85 | G25: 330.2
A26: 7 | B26: =IFERROR(VLOOKUP($A26,EVENTO!$A$2:$C$4999,2,FALSE),"") -> ADITIVO DE QUANTIDADE | C26: =IFERROR(VLOOKUP($A26,EVENTO!$A$2:$C$4999,3,FALSE),"") -> ALECE | D26: MICROCOMPUTADOR TIPO 3 | E26: LENOVO WORDKSTATION P340 TWR, XEON W-1250, 32GB, SSD 256GB, GPU DIDICADA 2GB DDR5, MOUSE E TECLADO USB LENOVO + MONITOR 24,5 LENOVO LEGION Y25-25 | F26: 20 | G26: 720.85
A27: 8 | B27: =IFERROR(VLOOKUP($A27,EVENTO!$A$2:$C$4999,2,FALSE),"") -> CADASTRO | C27: =IFERROR(VLOOKUP($A27,EVENTO!$A$2:$C$4999,3,FALSE),"") -> 10a REGIAO MILITAR | D27: IMPRESSORA MONOCROMÁTICO – PÁGINAS A4 | E27: KYOCERA ECOSYSMA5500ifx + OCR | F27: 40
A28: 8 | B28: =IFERROR(VLOOKUP($A28,EVENTO!$A$2:$C$4999,2,FALSE),"") -> CADASTRO | C28: =IFERROR(VLOOKUP($A28,EVENTO!$A$2:$C$4999,3,FALSE),"") -> 10a REGIAO MILITAR | D28: IMPRESSORA POLICROMÁTICO – PÁGINAS – A4 | E28: KYOCERA ECOSYS MA3500cix + OCR | F28: 80
A29: 8 | B29: =IFERROR(VLOOKUP($A29,EVENTO!$A$2:$C$4999,2,FALSE),"") -> CADASTRO | C29: =IFERROR(VLOOKUP($A29,EVENTO!$A$2:$C$4999,3,FALSE),"") -> 10a REGIAO MILITAR | D29: IMPRESSORA MONOCROMÁTICO – PÁGINAS A3 | E29: KYOCERA TASKALFA 2554CI + DP-7160 + OCR | F29: 1
A30: 10 | B30: =IFERROR(VLOOKUP($A30,EVENTO!$A$2:$C$4999,2,FALSE),"") -> CADASTRO | C30: =IFERROR(VLOOKUP($A30,EVENTO!$A$2:$C$4999,3,FALSE),"") -> CMFOR | D30: IMPRESSÃO CORPORATIVA OU OUTSOURCING DE IMPRESSÃO, COM O FORNECIMENTO DE EQUIPAMENTOS | E30: KYOCERA M2640IDW + PF1100 | F30: 14
A31: 10 | B31: =IFERROR(VLOOKUP($A31,EVENTO!$A$2:$C$4999,2,FALSE),"") -> CADASTRO | C31: =IFERROR(VLOOKUP($A31,EVENTO!$A$2:$C$4999,3,FALSE),"") -> CMFOR | D31: IMPRESSÃO CORPORATIVA OU OUTSOURCING DE IMPRESSÃO, COM O FORNECIMENTO DE EQUIPAMENTOS | E31: KYOCERA TASKALFA 5004I | F31: 3
A32: 13 | B32: =IFERROR(VLOOKUP($A32,EVENTO!$A$2:$C$4999,2,FALSE),"") -> CADASTRO | C32: =IFERROR(VLOOKUP($A32,EVENTO!$A$2:$C$4999,3,FALSE),"") -> ESCOLA DE APRENDIZEM DE MARINHEIROS DO CEARÁ | D32: IMPRESSORA POLICROMÁTICO – PÁGINAS – A4 | E32: KYOCERA ECOSYS M6230cidn | F32: 2
A33: 15 | B33: =IFERROR(VLOOKUP($A33,EVENTO!$A$2:$C$4999,2,FALSE),"") -> CADASTRO | C33: =IFERROR(VLOOKUP($A33,EVENTO!$A$2:$C$4999,3,FALSE),"") -> UFC | D33: IMPRESSORA MONOCROMÁTICO – PÁGINAS A4 | E33: KYOCERA ECOSYSMA5500ifx + OCR | F33: 149
A34: 15 | B34: =IFERROR(VLOOKUP($A34,EVENTO!$A$2:$C$4999,2,FALSE),"") -> CADASTRO | C34: =IFERROR(VLOOKUP($A34,EVENTO!$A$2:$C$4999,3,FALSE),"") -> UFC | D34: IMPRESSORA POLICROMÁTICO – PÁGINAS – A4 | E34: KYOCERA ECOSYS MA3500cix + OCR | F34: 1
A35: 15 | B35: =IFERROR(VLOOKUP($A35,EVENTO!$A$2:$C$4999,2,FALSE),"") -> CADASTRO | C35: =IFERROR(VLOOKUP($A35,EVENTO!$A$2:$C$4999,3,FALSE),"") -> UFC | D35: IMPRESSORA MONOCROMÁTICO – PÁGINAS A3 | E35: KYOCERA TASKALFA 2554CI + DP-7160 + OCR | F35: 5
A36: 18 | B36: =IFERROR(VLOOKUP($A36,EVENTO!$A$2:$C$4999,2,FALSE),"") -> CADASTRO | C36: =IFERROR(VLOOKUP($A36,EVENTO!$A$2:$C$4999,3,FALSE),"") -> IFCE CAMOCIM | D36: IMPRESSORA MONOCROMÁTICO – PÁGINAS A4 | E36: KYOCERA ECOSYSMA5500ifx + OCR | F36: 3
A37: 18 | B37: =IFERROR(VLOOKUP($A37,EVENTO!$A$2:$C$4999,2,FALSE),"") -> CADASTRO | C37: =IFERROR(VLOOKUP($A37,EVENTO!$A$2:$C$4999,3,FALSE),"") -> IFCE CAMOCIM | D37: IMPRESSORA POLICROMÁTICO – PÁGINAS – A4 | E37: KYOCERA ECOSYS MA3500cix + OCR | F37: 1
A38: 20 | B38: =IFERROR(VLOOKUP($A38,EVENTO!$A$2:$C$4999,2,FALSE),"") -> CADASTRO | C38: =IFERROR(VLOOKUP($A38,EVENTO!$A$2:$C$4999,3,FALSE),"") -> IFCE CAUCAIA | D38: IMPRESSORA MONOCROMÁTICO – PÁGINAS A4 | E38: KYOCERA ECOSYSMA5500ifx + OCR | F38: 5
... A54: 34 | B54: =IFERROR(VLOOKUP($A54,EVENTO!$A$2:$C$4999,2,FALSE),"") -> CADASTRO | C54: =IFERROR(VLOOKUP($A54,EVENTO!$A$2:$C$4999,3,FALSE),"") -> IFRN CAMPUS NATAL | D54: IMPRESSORA MONOCROMÁTICO – PÁGINAS A3 | E54: KYOCERA TASKALFA 2554CI + DP-7160 + OCR | F54: 1
A55: 36 | B55: =IFERROR(VLOOKUP($A55,EVENTO!$A$2:$C$4999,2,FALSE),"") -> CADASTRO | C55: =IFERROR(VLOOKUP($A55,EVENTO!$A$2:$C$4999,3,FALSE),"") -> TRE RJ | D55: MULTIFUNCIONAL POLICROMÁTICA | E55: Kyocera Ecosys MA4000cix | F55: 60 | G55: 224.93
A56: 36 | B56: =IFERROR(VLOOKUP($A56,EVENTO!$A$2:$C$4999,2,FALSE),"") -> CADASTRO | C56: =IFERROR(VLOOKUP($A56,EVENTO!$A$2:$C$4999,3,FALSE),"") -> TRE RJ | D56: IMPRESSORA MONOCROMÁTICA | E56: kyocera Ecosys P2235dn | F56: 110 | G56: 203.94
A57: 36 | B57: =IFERROR(VLOOKUP($A57,EVENTO!$A$2:$C$4999,2,FALSE),"") -> CADASTRO | C57: =IFERROR(VLOOKUP($A57,EVENTO!$A$2:$C$4999,3,FALSE),"") -> TRE RJ | D57: IMPRESSORA POLICROMÁTICA | E57: Kyocera TASKalfa 3554ci | F57: 4 | G57: 763.6
A58: 36 | B58: =IFERROR(VLOOKUP($A58,EVENTO!$A$2:$C$4999,2,FALSE),"") -> CADASTRO | C58: =IFERROR(VLOOKUP($A58,EVENTO!$A$2:$C$4999,3,FALSE),"") -> TRE RJ | D58: IMPRESSORA MONOCROMÁTICA (período eleitoral) | E58: kyocera Ecosys P2235dn | F58: 40 | G58: 219.2
A59: 36 | B59: =IFERROR(VLOOKUP($A59,EVENTO!$A$2:$C$4999,2,FALSE),"") -> CADASTRO | C59: =IFERROR(VLOOKUP($A59,EVENTO!$A$2:$C$4999,3,FALSE),"") -> TRE RJ | D59: IMPRESSORA TÉRMICA DE CARTÕES | E59: Zebra zc300 | F59: 1 | G59: 276.42
A60: 37 | B60: =IFERROR(VLOOKUP($A60,EVENTO!$A$2:$C$4999,2,FALSE),"") -> CADASTRO | C60: =IFERROR(VLOOKUP($A60,EVENTO!$A$2:$C$4999,3,FALSE),"") -> DELEGACIA DA CAPITANIA DE SÃO FRANCISCO DO SUL | D60: IMPRESSORA MONOCROMÁTICO – PÁGINAS A4 | E60: Epson WorkForce Pro WF- M5899 | F60: 4
A61: 37 | B61: =IFERROR(VLOOKUP($A61,EVENTO!$A$2:$C$4999,2,FALSE),"") -> CADASTRO | C61: =IFERROR(VLOOKUP($A61,EVENTO!$A$2:$C$4999,3,FALSE),"") -> DELEGACIA DA CAPITANIA DE SÃO FRANCISCO DO SUL | D61: IMPRESSORA POLICROMÁTICO – PÁGINAS – A4 | E61: KYOCERA ECOSYS MA3500cix | F61: 1
A62: 38 | B62: =IFERROR(VLOOKUP($A62,EVENTO!$A$2:$C$4999,2,FALSE),"") -> CADASTRO | C62: =IFERROR(VLOOKUP($A62,EVENTO!$A$2:$C$4999,3,FALSE),"") -> DELEGACIA DA CAPITANIA DOS PORTOS EM ITAJAÍ | D62: IMPRESSORA MONOCROMÁTICO – PÁGINAS A4 | E62: Epson WorkForce Pro WF-M5899 | F62: 6
A63: 38 | B63: =IFERROR(VLOOKUP($A63,EVENTO!$A$2:$C$4999,2,FALSE),"") -> CADASTRO | C63: =IFERROR(VLOOKUP($A63,EVENTO!$A$2:$C$4999,3,FALSE),"") -> DELEGACIA DA CAPITANIA DOS PORTOS EM ITAJAÍ | D63: IMPRESSORA POLICROMÁTICO – PÁGINAS – A4 | E63: Epson Workforce WF-C5890 | F63: 1
A64: 39 | B64: =IFERROR(VLOOKUP($A64,EVENTO!$A$2:$C$4999,2,FALSE),"") -> CADASTRO | C64: =IFERROR(VLOOKUP($A64,EVENTO!$A$2:$C$4999,3,FALSE),"") -> SUPERINTENDÊNCIA FEDERAL DE AGRICULTURA E PECUARIA NO ESTADO DE SANTA CATARINA - SFA-SC | D64: IMPRESSORA MONOCROMÁTICO – PÁGINAS A4 | E64: ECOSYS_MA5500ifx | F64: 28
A65: 39 | B65: =IFERROR(VLOOKUP($A65,EVENTO!$A$2:$C$4999,2,FALSE),"") -> CADASTRO | C65: =IFERROR(VLOOKUP($A65,EVENTO!$A$2:$C$4999,3,FALSE),"") -> SUPERINTENDÊNCIA FEDERAL DE AGRICULTURA E PECUARIA NO ESTADO DE SANTA CATARINA - SFA-SC | D65: IMPRESSORA POLICROMÁTICO – PÁGINAS – A4 | E65: Kyocera_ECOSYS_MA3500cix | F65: 4
A66: 40 | B66: =IFERROR(VLOOKUP($A66,EVENTO!$A$2:$C$4999,2,FALSE),"") -> CADASTRO | C66: =IFERROR(VLOOKUP($A66,EVENTO!$A$2:$C$4999,3,FALSE),"") -> UFSC | D66: IMPRESSORA MONOCROMÁTICO – PÁGINAS A4 | E66: ECOSYS_MA4500ix + OCR + Card Authentication kit | F66: 375
A67: 40 | B67: =IFERROR(VLOOKUP($A67,EVENTO!$A$2:$C$4999,2,FALSE),"") -> CADASTRO | C67: =IFERROR(VLOOKUP($A67,EVENTO!$A$2:$C$4999,3,FALSE),"") -> UFSC | D67: IMPRESSORA MONOCROMÁTICO – PÁGINAS A3 | E67: TASKalfa MZ3200i + OCR + Card Authentication Kit + DF-7120 + AK-740 + DP-7140 | F67: 3
A68: 40 | B68: =IFERROR(VLOOKUP($A68,EVENTO!$A$2:$C$4999,2,FALSE),"") -> CADASTRO | C68: =IFERROR(VLOOKUP($A68,EVENTO!$A$2:$C$4999,3,FALSE),"") -> UFSC | D68: IMPRESSORA POLICROMÁTICO – PÁGINAS – A4 | E68: Kyocera_ECOSYS_MA3500cix + OCR + Card Authentication Kit | F68: 28
A69: 40 | B69: =IFERROR(VLOOKUP($A69,EVENTO!$A$2:$C$4999,2,FALSE),"") -> CADASTRO | C69: =IFERROR(VLOOKUP($A69,EVENTO!$A$2:$C$4999,3,FALSE),"") -> UFSC | D69: IMPRESSORA POLICROMÁTICO – PÁGINAS – A3 | E69: Kyocera TASKALFA 2554CI DP-7140 + OCR + Card Authentication Kit | F69: 36
A70: 40 | B70: =IFERROR(VLOOKUP($A70,EVENTO!$A$2:$C$4999,2,FALSE),"") -> CADASTRO | C70: =IFERROR(VLOOKUP($A70,EVENTO!$A$2:$C$4999,3,FALSE),"") -> UFSC | D70: IMPRESSORA POLICROMÁTICO – PÁGINAS – A3 COM DF-7100 | E70: Kyocera TASKALFA 2554CI DP-7140 + DF-7100 + OCR + Card Authentication Kit | F70: 2
A71: 41 | B71: =IFERROR(VLOOKUP($A71,EVENTO!$A$2:$C$4999,2,FALSE),"") -> CADASTRO | C71: =IFERROR(VLOOKUP($A71,EVENTO!$A$2:$C$4999,3,FALSE),"") -> BASE ADMINISTRATIVA DO QUARTEL-GENERAL DO EXÉRCITO | D71: IMPRESSORA MONOCROMÁTICO – PÁGINAS A4 | E71: EPSON WF-M5899 | F71: 16
... A76: 42 | B76: =IFERROR(VLOOKUP($A76,EVENTO!$A$2:$C$4999,2,FALSE),"") -> CADASTRO | C76: =IFERROR(VLOOKUP($A76,EVENTO!$A$2:$C$4999,3,FALSE),"") -> MCID | D76: IMPRESSORA POLICROMÁTICO – PÁGINAS – A3 | E76: EPSON WF- C878 | F76: 7
A77: 43 | B77: =IFERROR(VLOOKUP($A77,EVENTO!$A$2:$C$4999,2,FALSE),"") -> CADASTRO | C77: =IFERROR(VLOOKUP($A77,EVENTO!$A$2:$C$4999,3,FALSE),"") -> COTER | D77: IMPRESSORA POLICROMATICA– PÁGINAS A4 - NÃO MULTIFUNCIONAL | E77: Kyocera ECOSYS PA3500cx | F77: 2 | G77: 168
A78: 43 | B78: =IFERROR(VLOOKUP($A78,EVENTO!$A$2:$C$4999,2,FALSE),"") -> CADASTRO | C78: =IFERROR(VLOOKUP($A78,EVENTO!$A$2:$C$4999,3,FALSE),"") -> COTER | D78: IMPRESSORA MONOCROMÁTICO – PÁGINAS A4 | E78: Kyocera ECOSYS MA5500ix + Scan Extension Kit | F78: 48 | G78: 104.91
A79: 43 | B79: =IFERROR(VLOOKUP($A79,EVENTO!$A$2:$C$4999,2,FALSE),"") -> CADASTRO | C79: =IFERROR(VLOOKUP($A79,EVENTO!$A$2:$C$4999,3,FALSE),"") -> COTER | D79: IMPRESSORA POLICROMÁTICO – PÁGINAS – A4 | E79: Kyocera MA3500cix + Scan Extension Kit + PF-5150 | F79: 8 | G79: 340.12
A80: 43 | B80: =IFERROR(VLOOKUP($A80,EVENTO!$A$2:$C$4999,2,FALSE),"") -> CADASTRO | C80: =IFERROR(VLOOKUP($A80,EVENTO!$A$2:$C$4999,3,FALSE),"") -> COTER | D80: IMPRESSORA POLICROMÁTICO – PÁGINAS – A3 | E80: Kyocera TASKalfa_3554ci + Scan Extension Kit + DP-7160 | F80: 4 | G80: 359.5
A81: 44 | B81: =IFERROR(VLOOKUP($A81,EVENTO!$A$2:$C$4999,2,FALSE),"") -> ADITIVO DE QUANTIDADE | C81: =IFERROR(VLOOKUP($A81,EVENTO!$A$2:$C$4999,3,FALSE),"") -> COTER | D81: IMPRESSORA POLICROMATICA– PÁGINAS A4 - NÃO MULTIFUNCIONAL | E81: Kyocera ECOSYS PA3500cx | F81: 2 | G81: 168
A82: 44 | B82: =IFERROR(VLOOKUP($A82,EVENTO!$A$2:$C$4999,2,FALSE),"") -> ADITIVO DE QUANTIDADE | C82: =IFERROR(VLOOKUP($A82,EVENTO!$A$2:$C$4999,3,FALSE),"") -> COTER | D82: IMPRESSORA MONOCROMÁTICO – PÁGINAS A4 | E82: Kyocera ECOSYS MA5500ix + Scan Extension Kit | F82: 48 | G82: 104.91
A83: 44 | B83: =IFERROR(VLOOKUP($A83,EVENTO!$A$2:$C$4999,2,FALSE),"") -> ADITIVO DE QUANTIDADE | C83: =IFERROR(VLOOKUP($A83,EVENTO!$A$2:$C$4999,3,FALSE),"") -> COTER | D83: IMPRESSORA POLICROMÁTICO – PÁGINAS – A4 | E83: Kyocera MA3500cix + Scan Extension Kit + PF-5150 | F83: 9 | G83: 340.12
A84: 44 | B84: =IFERROR(VLOOKUP($A84,EVENTO!$A$2:$C$4999,2,FALSE),"") -> ADITIVO DE QUANTIDADE | C84: =IFERROR(VLOOKUP($A84,EVENTO!$A$2:$C$4999,3,FALSE),"") -> COTER | D84: IMPRESSORA POLICROMÁTICO – PÁGINAS – A3 | E84: Kyocera TASKalfa_3554ci + Scan Extension Kit + DP-7160 | F84: 5 | G84: 359.5
A85: 45 | B85: =IFERROR(VLOOKUP($A85,EVENTO!$A$2:$C$4999,2,FALSE),"") -> CADASTRO | C85: =IFERROR(VLOOKUP($A85,EVENTO!$A$2:$C$4999,3,FALSE),"") -> CONSELHO FEDERAL DE FARMÁCIA | D85: IMPRESSORA MONOCROMÁTICO – PÁGINAS A4 | E85: Epson WF-M5899 | F85: 6
A86: 45 | B86: =IFERROR(VLOOKUP($A86,EVENTO!$A$2:$C$4999,2,FALSE),"") -> CADASTRO | C86: =IFERROR(VLOOKUP($A86,EVENTO!$A$2:$C$4999,3,FALSE),"") -> CONSELHO FEDERAL DE FARMÁCIA | D86: IMPRESSORA POLICROMÁTICO – PÁGINAS – A4 | E86: Kyocera ECOSYS_MA3500cix | F86: 5
A87: 46 | B87: =IFERROR(VLOOKUP($A87,EVENTO!$A$2:$C$4999,2,FALSE),"") -> CADASTRO | C87: =IFERROR(VLOOKUP($A87,EVENTO!$A$2:$C$4999,3,FALSE),"") -> MCTI | D87: IMPRESSORA MONOCROMÁTICO – PÁGINAS A4 | E87: Kyocera ECOSYS_MA5500ix + Scan Extension Kit + Card Authentication Kit + Leitor de Cartão + gabinete | F87: 18
A88: 46 | B88: =IFERROR(VLOOKUP($A88,EVENTO!$A$2:$C$4999,2,FALSE),"") -> CADASTRO | C88: =IFERROR(VLOOKUP($A88,EVENTO!$A$2:$C$4999,3,FALSE),"") -> MCTI | D88: IMPRESSORA POLICROMÁTICO – PÁGINAS – A4 | E88: Kyocera ECOSYS_MA3500cix + Scan Extension Kit + Card Authentication Kit + Leitor de Cartão + Gabinete | F88: 26
A89: 46 | B89: =IFERROR(VLOOKUP($A89,EVENTO!$A$2:$C$4999,2,FALSE),"") -> CADASTRO | C89: =IFERROR(VLOOKUP($A89,EVENTO!$A$2:$C$4999,3,FALSE),"") -> MCTI | D89: IMPRESSORA POLICROMÁTICO/ MONOCROMATICA – PÁGINAS – A3 | E89: Kyocera TASKalfa_3554ci + scan extension kit + Card Authentication Kit + Leitor de Cartão + DP-7140 + Gabinete | F89: 10
A90: 47 | B90: =IFERROR(VLOOKUP($A90,EVENTO!$A$2:$C$4999,2,FALSE),"") -> CADASTRO | C90: =IFERROR(VLOOKUP($A90,EVENTO!$A$2:$C$4999,3,FALSE),"") -> MTE | D90: IMPRESSORA MONOCROMÁTICO – PÁGINAS A4 | E90: KYOCERA ECOSYS MA5500IFX + SCAN EXTENSION KIT | F90: 766
A91: 47 | B91: =IFERROR(VLOOKUP($A91,EVENTO!$A$2:$C$4999,2,FALSE),"") -> CADASTRO | C91: =IFERROR(VLOOKUP($A91,EVENTO!$A$2:$C$4999,3,FALSE),"") -> MTE | D91: IMPRESSORA POLICROMÁTICO – PÁGINAS – A4 | E91: KYOCERA ECOSYS MA3500CIX + 1X PF-5150 + SCAN EXTENSION KIT | F91: 196
A92: 47 | B92: =IFERROR(VLOOKUP($A92,EVENTO!$A$2:$C$4999,2,FALSE),"") -> CADASTRO | C92: =IFERROR(VLOOKUP($A92,EVENTO!$A$2:$C$4999,3,FALSE),"") -> MTE | D92: IMPRESSORA POLICROMÁTICO/ MONOCROMATICA – PÁGINAS – A3 | E92: KYOCERA TASKALFA 3554CI + DP-7160 + SCAN EXTENSION KIT | F92: 60
A93: 48 | B93: =IFERROR(VLOOKUP($A93,EVENTO!$A$2:$C$4999,2,FALSE),"") -> CADASTRO | C93: =IFERROR(VLOOKUP($A93,EVENTO!$A$2:$C$4999,3,FALSE),"") -> MT | D93: IMPRESSORA MONOCROMÁTICO – PÁGINAS A4 | E93: KYOCERA ECOSYS MA4500ix+OCR | F93: 50
A94: 48 | B94: =IFERROR(VLOOKUP($A94,EVENTO!$A$2:$C$4999,2,FALSE),"") -> CADASTRO | C94: =IFERROR(VLOOKUP($A94,EVENTO!$A$2:$C$4999,3,FALSE),"") -> MT | D94: IMPRESSORA POLICROMÁTICO – PÁGINAS – A4 | E94: KYOCERA ECOSYS MA3500cix+OCR | F94: 20
A95: 48 | B95: =IFERROR(VLOOKUP($A95,EVENTO!$A$2:$C$4999,2,FALSE),"") -> CADASTRO | C95: =IFERROR(VLOOKUP($A95,EVENTO!$A$2:$C$4999,3,FALSE),"") -> MT | D95: IMPRESSORA POLICROMÁTICO/ MONOCROMATICA – PÁGINAS – A3 | E95: KYOCERA ECOSYS M8124CIDN+OCR | F95: 11
A96: 50 | B96: =IFERROR(VLOOKUP($A96,EVENTO!$A$2:$C$4999,2,FALSE),"") -> CADASTRO | C96: =IFERROR(VLOOKUP($A96,EVENTO!$A$2:$C$4999,3,FALSE),"") -> MINISTÉRIO DA DEFESA - COMANDO DA AERONÁUTICA - GRUPAMENTO DE APOIO DE BRASÍLIA | D96: IMPRESSORA MONOCROMÁTICO – PÁGINAS A4 | E96: KYOCERA ECOSYS MA4500IX | F96: 47
... A112: 58 | B112: =IFERROR(VLOOKUP($A112,EVENTO!$A$2:$C$4999,2,FALSE),"") -> ADITIVO DE QUANTIDADE | C112: =IFERROR(VLOOKUP($A112,EVENTO!$A$2:$C$4999,3,FALSE),"") -> 1o GRUPAMENTO DE ENGENHARIA | D112: IMPRESSORA POLICROMÁTICO – PÁGINAS – A4 | E112: KYOCERA ECOSYS M6235cidn | F112: 3
A113: 59 | B113: =IFERROR(VLOOKUP($A113,EVENTO!$A$2:$C$4999,2,FALSE),"") -> CADASTRO | C113: =IFERROR(VLOOKUP($A113,EVENTO!$A$2:$C$4999,3,FALSE),"") -> COLEGIO MILITAR DE SÃO PAULO | D113: IMPRESSORA MONOCROMÁTICO – PÁGINAS A4 | E113: KYOCERA ECOSYS M2040dn | F113: 3 | G113: 390
A114: 59 | B114: =IFERROR(VLOOKUP($A114,EVENTO!$A$2:$C$4999,2,FALSE),"") -> CADASTRO | C114: =IFERROR(VLOOKUP($A114,EVENTO!$A$2:$C$4999,3,FALSE),"") -> COLEGIO MILITAR DE SÃO PAULO | D114: IMPRESSORA POLICROMÁTICO – PÁGINAS – A4 | E114: XEROX VERSALINK C505 | F114: 2 | G114: 960
A115: 60 | B115: =IFERROR(VLOOKUP($A115,EVENTO!$A$2:$C$4999,2,FALSE),"") -> ADITIVO DE REAJUSTE E PRAZO | C115: =IFERROR(VLOOKUP($A115,EVENTO!$A$2:$C$4999,3,FALSE),"") -> COLEGIO MILITAR DE SÃO PAULO | D115: IMPRESSORA MONOCROMÁTICO – PÁGINAS A4 | E115: KYOCERA ECOSYS M2040dn | F115: 3 | G115: 399.668
A116: 60 | B116: =IFERROR(VLOOKUP($A116,EVENTO!$A$2:$C$4999,2,FALSE),"") -> ADITIVO DE REAJUSTE E PRAZO | C116: =IFERROR(VLOOKUP($A116,EVENTO!$A$2:$C$4999,3,FALSE),"") -> COLEGIO MILITAR DE SÃO PAULO | D116: IMPRESSORA POLICROMÁTICO – PÁGINAS – A4 | E116: XEROX VERSALINK C505 | F116: 2 | G116: 983
A117: 62 | B117: =IFERROR(VLOOKUP($A117,EVENTO!$A$2:$C$4999,2,FALSE),"") -> APOSTILAMENTO | C117: =IFERROR(VLOOKUP($A117,EVENTO!$A$2:$C$4999,3,FALSE),"") -> COLEGIO MILITAR DE SÃO PAULO | D117: IMPRESSORA MONOCROMÁTICO – PÁGINAS A4 | E117: KYOCERA ECOSYS M2040dn | F117: 3 | G117: 427.5
A118: 62 | B118: =IFERROR(VLOOKUP($A118,EVENTO!$A$2:$C$4999,2,FALSE),"") -> APOSTILAMENTO | C118: =IFERROR(VLOOKUP($A118,EVENTO!$A$2:$C$4999,3,FALSE),"") -> COLEGIO MILITAR DE SÃO PAULO | D118: IMPRESSORA POLICROMÁTICO – PÁGINAS – A4 | E118: XEROX VERSALINK C505 | F118: 2 | G118: 1051.4
A119: 63 | B119: =IFERROR(VLOOKUP($A119,EVENTO!$A$2:$C$4999,2,FALSE),"") -> CADASTRO | C119: =IFERROR(VLOOKUP($A119,EVENTO!$A$2:$C$4999,3,FALSE),"") -> INCRA | D119: IMPRESSORA MONOCROMÁTICO – PÁGINAS A4 | E119: KYOCERA ECOSYSMA5500ifx | F119: 20
A120: 63 | B120: =IFERROR(VLOOKUP($A120,EVENTO!$A$2:$C$4999,2,FALSE),"") -> CADASTRO | C120: =IFERROR(VLOOKUP($A120,EVENTO!$A$2:$C$4999,3,FALSE),"") -> INCRA | D120: IMPRESSORA POLICROMÁTICO – PÁGINAS – A4 | E120: Epson WF-C5890 | F120: 3
A121: 65 | B121: =IFERROR(VLOOKUP($A121,EVENTO!$A$2:$C$4999,2,FALSE),"") -> CADASTRO | C121: =IFERROR(VLOOKUP($A121,EVENTO!$A$2:$C$4999,3,FALSE),"") -> SEGER | D121: NOTEBOOK TIPO II - CORE I5 | F121: 26 | G121: 344.75
A122: 65 | B122: =IFERROR(VLOOKUP($A122,EVENTO!$A$2:$C$4999,2,FALSE),"") -> CADASTRO | C122: =IFERROR(VLOOKUP($A122,EVENTO!$A$2:$C$4999,3,FALSE),"") -> SEGER | D122: MICRO TIPO II - CORE I5 | F122: 200 | G122: 221.78
A123: 65 | B123: =IFERROR(VLOOKUP($A123,EVENTO!$A$2:$C$4999,2,FALSE),"") -> CADASTRO | C123: =IFERROR(VLOOKUP($A123,EVENTO!$A$2:$C$4999,3,FALSE),"") -> SEGER | D123: IMPRESSORA TIPO VI - PLOTTER - COM FORNECIMENTO DE PAPEL | F123: 1 | G123: 1363.36
A124: 65 | B124: =IFERROR(VLOOKUP($A124,EVENTO!$A$2:$C$4999,2,FALSE),"") -> CADASTRO | C124: =IFERROR(VLOOKUP($A124,EVENTO!$A$2:$C$4999,3,FALSE),"") -> SEGER | D124: TV TIPO III - 40 POLEGADAS | F124: 25 | G124: 105.09
A125: 68 | B125: =IFERROR(VLOOKUP($A125,EVENTO!$A$2:$C$4999,2,FALSE),"") -> ADITIVO DE PRAZO | C125: =IFERROR(VLOOKUP($A125,EVENTO!$A$2:$C$4999,3,FALSE),"") -> CEGOR | D125: NOTEBOOK TIPO II - CORE I5 | F125: 26 | G125: 344.75
A126: 68 | B126: =IFERROR(VLOOKUP($A126,EVENTO!$A$2:$C$4999,2,FALSE),"") -> ADITIVO DE PRAZO | C126: =IFERROR(VLOOKUP($A126,EVENTO!$A$2:$C$4999,3,FALSE),"") -> CEGOR | D126: MICRO TIPO II - CORE I5 | F126: 200 | G126: 221.78
A127: 68 | B127: =IFERROR(VLOOKUP($A127,EVENTO!$A$2:$C$4999,2,FALSE),"") -> ADITIVO DE PRAZO | C127: =IFERROR(VLOOKUP($A127,EVENTO!$A$2:$C$4999,3,FALSE),"") -> CEGOR | D127: IMPRESSORA TIPO VI - PLOTTER - COM FORNECIMENTO DE PAPEL | F127: 1 | G127: 1363.36
A128: 68 | B128: =IFERROR(VLOOKUP($A128,EVENTO!$A$2:$C$4999,2,FALSE),"") -> ADITIVO DE PRAZO | C128: =IFERROR(VLOOKUP($A128,EVENTO!$A$2:$C$4999,3,FALSE),"") -> CEGOR | D128: TV TIPO III - 40 POLEGADAS | F128: 25 | G128: 105.09
A129: 69 | B129: =IFERROR(VLOOKUP($A129,EVENTO!$A$2:$C$4999,2,FALSE),"") -> CADASTRO | C129: =IFERROR(VLOOKUP($A129,EVENTO!$A$2:$C$4999,3,FALSE),"") -> DETRAN MA | D129: MICRO TIPO I | E129: Micro Tipo I – Micro Desktop I5 ou AMD Ryzen 5 mínimo 6ª geração, memória 8GB SSD 240GB monitor 19", Windows 11 Profissional ou superior. Aumento da capacidade do processamento (geração do processador), monitor, memória, HD ou tipo de HD, inclusão Webcam sem ônus para o contratante. Atenção: o CONTRATADO deverá dispor de equipamento de backup em estoque para troca em caso de pane com no máximo 4 (quatro) horas. Serviços integrados na locação do equipamento: Instalação/desinstalação de antivírus e softwares do contratante ou de terceiros, instalação e/ou configuração de redes/intranet/internet incluindo cabos (de rede ou fibra ótica) e conectores, impressoras, acessórios, estabilizador, placas, filtros de linha, extensões de energia sem ônus para o contratante. | F129: 300 | G129: 377
A130: 69 | B130: =IFERROR(VLOOKUP($A130,EVENTO!$A$2:$C$4999,2,FALSE),"") -> CADASTRO | C130: =IFERROR(VLOOKUP($A130,EVENTO!$A$2:$C$4999,3,FALSE),"") -> DETRAN MA | D130: NOTEBOOK TIPO II | E130: Notebook Tipo II – Notebook I5 ou AMD Ryzen 5 mínimo 6ª geração, memória 8GB HD SSD 240GB monitor 14", Windows 11 ou superior, acompanhado com a bolsa e seguro contra quebra. Aumento da capacidade do processamento (geração do processador), monitor, memória, HD ou tipo de SSD, qualidade da Webcam sem ônus para o contratante. Atenção: o CONTRATADO deverá dispor de equipamento de backup em estoque para troca em caso de pane com no máximo 4 (quatro) horas. Serviços integrados na locação do equipamento: Instalação/desinstalação de antivírus e softwares do contratante ou de terceiros, instalação e/ou configuração de redes/intranet/internet incluindo cabos (de rede ou fibra ótica) e conectores, impressoras, acessórios, estabilizador, placas, filtros de linha, extensões de energia sem ônus para o contratante. | F130: 70 | G130: 593.33
A131: 70 | B131: =IFERROR(VLOOKUP($A131,EVENTO!$A$2:$C$4999,2,FALSE),"") -> CADASTRO | C131: =IFERROR(VLOOKUP($A131,EVENTO!$A$2:$C$4999,3,FALSE),"") -> IPAM | D131: NOTEBOOK | E131: Notebook I3 ou AMD Ryzen3 mínimo 6º geração | F131: 10 | G131: R$ 270,3900
A132: 74 | B132: =IFERROR(VLOOKUP($A132,EVENTO!$A$2:$C$4999,2,FALSE),"") -> CADASTRO | C132: =IFERROR(VLOOKUP($A132,EVENTO!$A$2:$C$4999,3,FALSE),"") -> PCDF | D132: IMPRESSORA MONOCROMÁTICO – PÁGINAS A4 | E132: KYOCERA ECOSYS MA5500IF | F132: 140
A133: 74 | B133: =IFERROR(VLOOKUP($A133,EVENTO!$A$2:$C$4999,2,FALSE),"") -> CADASTRO | C133: =IFERROR(VLOOKUP($A133,EVENTO!$A$2:$C$4999,3,FALSE),"") -> PCDF | D133: IMPRESSORA POLICROMÁTICO – PÁGINAS – A4 | E133: Xerox® VersaLink® C415 + Wifi + Bandeja | F133: 350
A134: 74 | B134: =IFERROR(VLOOKUP($A134,EVENTO!$A$2:$C$4999,2,FALSE),"") -> CADASTRO | C134: =IFERROR(VLOOKUP($A134,EVENTO!$A$2:$C$4999,3,FALSE),"") -> PCDF | D134: IMPRESSORA MONO - POLI– PÁGINAS – A3 | E134: Xerox AltaLink C8245F | F134: 10
A135: 70 | B135: =IFERROR(VLOOKUP($A135,EVENTO!$A$2:$C$4999,2,FALSE),"") -> CADASTRO | C135: =IFERROR(VLOOKUP($A135,EVENTO!$A$2:$C$4999,3,FALSE),"") -> IPAM | D135: MICROCOMPUTADOR | F135: 30 | G135: R$ 173,9300
A136: 75 | B136: =IFERROR(VLOOKUP($A136,EVENTO!$A$2:$C$4999,2,FALSE),"") -> CADASTRO | C136: =IFERROR(VLOOKUP($A136,EVENTO!$A$2:$C$4999,3,FALSE),"") -> HEMOCENTRO PB | D136: IMPRESSORA POLICROMÁTICO – PÁGINAS – A4 | E136: KYOCERA ECOSYS MA3500cix | F136: 7 | G136: 308
...

Sheet SERVICOS
A1: EVENTO | B1: TIPO_EVENTO | C1: CONTRATO | D1: ITEM | E1: APELIDO | F1: DESCRICAO | G1: QUANTIDADE | H1: VALOR_UNITARIO
A2: 8 | B2: =IFERROR(VLOOKUP($A2,EVENTO!$A$2:$C$4999,2,FALSE),"") -> CADASTRO | C2: =IFERROR(VLOOKUP($A2,EVENTO!$A$2:$C$4999,3,FALSE),"") -> 10a REGIAO MILITAR | D2: IMPRESSORA MONOCROMÁTICO – PÁGINAS A4 | E2: OUTSOURCING DE IMPRESSÃO MONOCROMÁTICO – PÁGINAS A4 | F2: DENTRO DA FRANQUIA SEM PAPEL | G2: 47000 | H2: 0.049
A3: 8 | B3: =IFERROR(VLOOKUP($A3,EVENTO!$A$2:$C$4999,2,FALSE),"") -> CADASTRO | C3: =IFERROR(VLOOKUP($A3,EVENTO!$A$2:$C$4999,3,FALSE),"") -> 10a REGIAO MILITAR | D3: IMPRESSORA MONOCROMÁTICO – PÁGINAS A4 | E3: OUTSOURCING DE IMPRESSÃO MONOCROMÁTICO – PÁGINAS A4 | F3: EXCEDENTE A FRANQUIA SEM PAPEL | G3: 3000 | H3: 0.04
A4: 8 | B4: =IFERROR(VLOOKUP($A4,EVENTO!$A$2:$C$4999,2,FALSE),"") -> CADASTRO | C4: =IFERROR(VLOOKUP($A4,EVENTO!$A$2:$C$4999,3,FALSE),"") -> 10a REGIAO MILITAR | D4: IMPRESSORA POLICROMÁTICO – PÁGINAS – A4 | E4: OUTSOURCING DE IMPRESSÃO POLICROMÁTICO – PÁGINAS – A4 | F4: DENTRO DA FRANQUIA SEM PAPEL | G4: 800 | H4: 0.29
A5: 8 | B5: =IFERROR(VLOOKUP($A5,EVENTO!$A$2:$C$4999,2,FALSE),"") -> CADASTRO | C5: =IFERROR(VLOOKUP($A5,EVENTO!$A$2:$C$4999,3,FALSE),"") -> 10a REGIAO MILITAR | D5: IMPRESSORA POLICROMÁTICO – PÁGINAS – A4 | E5: OUTSOURCING DE IMPRESSÃO POLICROMÁTICO – PÁGINAS – A4 | F5: EXCEDENTE A FRANQUIA SEM PAPEL | G5: 200 | H5: 0.19
A6: 8 | B6: =IFERROR(VLOOKUP($A6,EVENTO!$A$2:$C$4999,2,FALSE),"") -> CADASTRO | C6: =IFERROR(VLOOKUP($A6,EVENTO!$A$2:$C$4999,3,FALSE),"") -> 10a REGIAO MILITAR | D6: IMPRESSORA MONOCROMÁTICO – PÁGINAS A3 | E6: OUTSOURCING DE IMPRESSÃO MONOCROMÁTICO – PÁGINAS A3 | F6: DENTRO DA FRANQUIA SEM PAPEL | G6: 800 | H6: 0.16
A7: 8 | B7: =IFERROR(VLOOKUP($A7,EVENTO!$A$2:$C$4999,2,FALSE),"") -> CADASTRO | C7: =IFERROR(VLOOKUP($A7,EVENTO!$A$2:$C$4999,3,FALSE),"") -> 10a REGIAO MILITAR | D7: IMPRESSORA MONOCROMÁTICO – PÁGINAS A3 | E7: OUTSOURCING DE IMPRESSÃO MONOCROMÁTICO – PÁGINAS A3 | F7: EXCEDENTE A FRANQUIA SEM PAPEL | G7: 200 | H7: 0.08
A8: 10 | B8: =IFERROR(VLOOKUP($A8,EVENTO!$A$2:$C$4999,2,FALSE),"") -> CADASTRO | C8: =IFERROR(VLOOKUP($A8,EVENTO!$A$2:$C$4999,3,FALSE),"") -> CMFOR | D8: SERVIÇO DE IMPRESSÃO CORPORATIVA OU OUTSOURCING DE IMPRESSÃO, COM O FORNECIMENTO DE EQUIPAMENTOS | E8: SERVIÇO DE IMPRESSÃO CORPORATIVA OU OUTSOURCING DE IMPRESSÃO, COM O FORNECIMENTO DE EQUIPAMENTOS | F8: SERVIÇO DE IMPRESSÃO CORPORATIVA OU OUTSOURCING DE IMPRESSÃO, COM O FORNECIMENTO DE EQUIPAMENTOS | G8: 98170 | H8: 0.03
A9: 9 | B9: =IFERROR(VLOOKUP($A9,EVENTO!$A$2:$C$4999,2,FALSE),"") -> ADITIVO DE REAJUSTE E PRAZO | C9: =IFERROR(VLOOKUP($A9,EVENTO!$A$2:$C$4999,3,FALSE),"") -> 10a REGIAO MILITAR | E9: OUTSOURCING DE IMPRESSÃO MONOCROMÁTICO – PÁGINAS A4 | F9: DENTRO DA FRANQUIA SEM PAPEL | G9: 47000 | H9: 0.051
A10: 9 | B10: =IFERROR(VLOOKUP($A10,EVENTO!$A$2:$C$4999,2,FALSE),"") -> ADITIVO DE REAJUSTE E PRAZO | C10: =IFERROR(VLOOKUP($A10,EVENTO!$A$2:$C$4999,3,FALSE),"") -> 10a REGIAO MILITAR | E10: OUTSOURCING DE IMPRESSÃO MONOCROMÁTICO – PÁGINAS A4 | F10: EXCEDENTE A FRANQUIA SEM PAPEL | G10: 3000 | H10: 0.041
A11: 9 | B11: =IFERROR(VLOOKUP($A11,EVENTO!$A$2:$C$4999,2,FALSE),"") -> ADITIVO DE REAJUSTE E PRAZO | C11: =IFERROR(VLOOKUP($A11,EVENTO!$A$2:$C$4999,3,FALSE),"") -> 10a REGIAO MILITAR | E11: OUTSOURCING DE IMPRESSÃO POLICROMÁTICO – PÁGINAS – A4 | F11: DENTRO DA FRANQUIA SEM PAPEL | G11: 800 | H11: 0.3
A12: 9 | B12: =IFERROR(VLOOKUP($A12,EVENTO!$A$2:$C$4999,2,FALSE),"") -> ADITIVO DE REAJUSTE E PRAZO | C12: =IFERROR(VLOOKUP($A12,EVENTO!$A$2:$C$4999,3,FALSE),"") -> 10a REGIAO MILITAR | E12: OUTSOURCING DE IMPRESSÃO POLICROMÁTICO – PÁGINAS – A4 | F12: EXCEDENTE A FRANQUIA SEM PAPEL | G12: 200 | H12: 0.19
A13: 9 | B13: =IFERROR(VLOOKUP($A13,EVENTO!$A$2:$C$4999,2,FALSE),"") -> ADITIVO DE REAJUSTE E PRAZO | C13: =IFERROR(VLOOKUP($A13,EVENTO!$A$2:$C$4999,3,FALSE),"") -> 10a REGIAO MILITAR | E13: OUTSOURCING DE IMPRESSÃO MONOCROMÁTICO – PÁGINAS A3 | F13: DENTRO DA FRANQUIA SEM PAPEL | G13: 800 | H13: 0.16
A14: 9 | B14: =IFERROR(VLOOKUP($A14,EVENTO!$A$2:$C$4999,2,FALSE),"") -> ADITIVO DE REAJUSTE E PRAZO | C14: =IFERROR(VLOOKUP($A14,EVENTO!$A$2:$C$4999,3,FALSE),"") -> 10a REGIAO MILITAR | E14: OUTSOURCING DE IMPRESSÃO MONOCROMÁTICO – PÁGINAS A3 | F14: EXCEDENTE A FRANQUIA SEM PAPEL | G14: 200 | H14: 0.083
A15: 11 | B15: =IFERROR(VLOOKUP($A15,EVENTO!$A$2:$C$4999,2,FALSE),"") -> ADITIVO DE REAJUSTE E PRAZO | C15: =IFERROR(VLOOKUP($A15,EVENTO!$A$2:$C$4999,3,FALSE),"") -> CMFOR | E15: SERVIÇO DE IMPRESSÃO CORPORATIVA OU OUTSOURCING DE IMPRESSÃO, COM O FORNECIMENTO DE EQUIPAMENTOS | F15: SERVIÇO DE IMPRESSÃO CORPORATIVA OU OUTSOURCING DE IMPRESSÃO, COM O FORNECIMENTO DE EQUIPAMENTOS | G15: 98170 | H15: 0.0312527
A16: 12 | B16: =IFERROR(VLOOKUP($A16,EVENTO!$A$2:$C$4999,2,FALSE),"") -> ADITIVO DE REAJUSTE E PRAZO | C16: =IFERROR(VLOOKUP($A16,EVENTO!$A$2:$C$4999,3,FALSE),"") -> CMFOR | E16: SERVIÇO DE IMPRESSÃO CORPORATIVA OU OUTSOURCING DE IMPRESSÃO, COM O FORNECIMENTO DE EQUIPAMENTOS | F16: SERVIÇO DE IMPRESSÃO CORPORATIVA OU OUTSOURCING DE IMPRESSÃO, COM O FORNECIMENTO DE EQUIPAMENTOS | G16: 98170 | H16: 0.0331497
A17: 13 | B17: =IFERROR(VLOOKUP($A17,EVENTO!$A$2:$C$4999,2,FALSE),"") -> CADASTRO | C17: =IFERROR(VLOOKUP($A17,EVENTO!$A$2:$C$4999,3,FALSE),"") -> ESCOLA DE APRENDIZEM DE MARINHEIROS DO CEARÁ | D17: IMPRESSORA POLICROMÁTICO – PÁGINAS – A4 | E17: OUTSOURCING DE IMPRESSÃO POLICROMÁTICO – PÁGINAS – A4 | F17: DENTRO DA FRANQUIA SEM PAPEL | G17: 1200 | H17: 0.29
A18: 13 | B18: =IFERROR(VLOOKUP($A18,EVENTO!$A$2:$C$4999,2,FALSE),"") -> CADASTRO | C18: =IFERROR(VLOOKUP($A18,EVENTO!$A$2:$C$4999,3,FALSE),"") -> ESCOLA DE APRENDIZEM DE MARINHEIROS DO CEARÁ | D18: IMPRESSORA POLICROMÁTICO – PÁGINAS – A4 | E18: OUTSOURCING DE IMPRESSÃO POLICROMÁTICO – PÁGINAS – A4 | F18: EXCEDENTE A FRANQUIA SEM PAPEL | G18: 800 | H18: 0.19
A19: 14 | B19: =IFERROR(VLOOKUP($A19,EVENTO!$A$2:$C$4999,2,FALSE),"") -> ADITIVO DE REAJUSTE E PRAZO | C19: =IFERROR(VLOOKUP($A19,EVENTO!$A$2:$C$4999,3,FALSE),"") -> ESCOLA DE APRENDIZEM DE MARINHEIROS DO CEARÁ | E19: OUTSOURCING DE IMPRESSÃO POLICROMÁTICO – PÁGINAS – A4 | F19: DENTRO DA FRANQUIA SEM PAPEL | G19: 1200 | H19: 0.31
A20: 14 | B20: =IFERROR(VLOOKUP($A20,EVENTO!$A$2:$C$4999,2,FALSE),"") -> ADITIVO DE REAJUSTE E PRAZO | C20: =IFERROR(VLOOKUP($A20,EVENTO!$A$2:$C$4999,3,FALSE),"") -> ESCOLA DE APRENDIZEM DE MARINHEIROS DO CEARÁ | E20: OUTSOURCING DE IMPRESSÃO POLICROMÁTICO – PÁGINAS – A4 | F20: EXCEDENTE A FRANQUIA SEM PAPEL | G20: 800 | H20: 0.2
A21: 15 | B21: =IFERROR(VLOOKUP($A21,EVENTO!$A$2:$C$4999,2,FALSE),"") -> CADASTRO | C21: =IFERROR(VLOOKUP($A21,EVENTO!$A$2:$C$4999,3,FALSE),"") -> UFC | D21: IMPRESSORA MONOCROMÁTICO – PÁGINAS A4 | E21: OUTSOURCING DE IMPRESSÃO MONOCROMÁTICO – PÁGINAS A4 | F21: DENTRO DA FRANQUIA SEM PAPEL | G21: 1905840 | H21: 0.049
A22: 15 | B22: =IFERROR(VLOOKUP($A22,EVENTO!$A$2:$C$4999,2,FALSE),"") -> CADASTRO | C22: =IFERROR(VLOOKUP($A22,EVENTO!$A$2:$C$4999,3,FALSE),"") -> UFC | D22: IMPRESSORA MONOCROMÁTICO – PÁGINAS A4 | E22: OUTSOURCING DE IMPRESSÃO MONOCROMÁTICO – PÁGINAS A4 | F22: EXCEDENTE A FRANQUIA SEM PAPEL | G22: 1270560 | H22: 0.04
A23: 15 | B23: =IFERROR(VLOOKUP($A23,EVENTO!$A$2:$C$4999,2,FALSE),"") -> CADASTRO | C23: =IFERROR(VLOOKUP($A23,EVENTO!$A$2:$C$4999,3,FALSE),"") -> UFC | D23: IMPRESSORA POLICROMÁTICO – PÁGINAS – A4 | E23: OUTSOURCING DE IMPRESSÃO POLICROMÁTICO – PÁGINAS – A4 | F23: DENTRO DA FRANQUIA SEM PAPEL | G23: 14400 | H23: 0.29
A24: 15 | B24: =IFERROR(VLOOKUP($A24,EVENTO!$A$2:$C$4999,2,FALSE),"") -> CADASTRO | C24: =IFERROR(VLOOKUP($A24,EVENTO!$A$2:$C$4999,3,FALSE),"") -> UFC | D24: IMPRESSORA POLICROMÁTICO – PÁGINAS – A4 | E24: OUTSOURCING DE IMPRESSÃO POLICROMÁTICO – PÁGINAS – A4 | F24: EXCEDENTE A FRANQUIA SEM PAPEL | G24: 9600 | H24: 0.19
A25: 15 | B25: =IFERROR(VLOOKUP($A25,EVENTO!$A$2:$C$4999,2,FALSE),"") -> CADASTRO | C25: =IFERROR(VLOOKUP($A25,EVENTO!$A$2:$C$4999,3,FALSE),"") -> UFC | D25: IMPRESSORA MONOCROMÁTICO – PÁGINAS A3 | E25: OUTSOURCING DE IMPRESSÃO MONOCROMÁTICO – PÁGINAS A3 | F25: DENTRO DA FRANQUIA SEM PAPEL | G25: 152652 | H25: 0.16
A26: 15 | B26: =IFERROR(VLOOKUP($A26,EVENTO!$A$2:$C$4999,2,FALSE),"") -> CADASTRO | C26: =IFERROR(VLOOKUP($A26,EVENTO!$A$2:$C$4999,3,FALSE),"") -> UFC | D26: IMPRESSORA MONOCROMÁTICO – PÁGINAS A3 | E26: OUTSOURCING DE IMPRESSÃO MONOCROMÁTICO – PÁGINAS A3 | F26: EXCEDENTE A FRANQUIA SEM PAPEL | G26: 101760 | H26: 0.08
A27: 17 | B27: =IFERROR(VLOOKUP($A27,EVENTO!$A$2:$C$4999,2,FALSE),"") -> APOSTILAMENTO | C27: =IFERROR(VLOOKUP($A27,EVENTO!$A$2:$C$4999,3,FALSE),"") -> UFC | E27: OUTSOURCING DE IMPRESSÃO MONOCROMÁTICO – PÁGINAS A4 | F27: DENTRO DA FRANQUIA SEM PAPEL | G27: 1905840 | H27: 0.05134
A28: 17 | B28: =IFERROR(VLOOKUP($A28,EVENTO!$A$2:$C$4999,2,FALSE),"") -> APOSTILAMENTO | C28: =IFERROR(VLOOKUP($A28,EVENTO!$A$2:$C$4999,3,FALSE),"") -> UFC | E28: OUTSOURCING DE IMPRESSÃO MONOCROMÁTICO – PÁGINAS A4 | F28: EXCEDENTE A FRANQUIA SEM PAPEL | G28: 1270560 | H28: 0.04196
A29: 17 | B29: =IFERROR(VLOOKUP($A29,EVENTO!$A$2:$C$4999,2,FALSE),"") -> APOSTILAMENTO | C29: =IFERROR(VLOOKUP($A29,EVENTO!$A$2:$C$4999,3,FALSE),"") -> UFC | E29: OUTSOURCING DE IMPRESSÃO POLICROMÁTICO – PÁGINAS – A4 | F29: DENTRO DA FRANQUIA SEM PAPEL | G29: 14400 | H29: 0.30524
A30: 17 | B30: =IFERROR(VLOOKUP($A30,EVENTO!$A$2:$C$4999,2,FALSE),"") -> APOSTILAMENTO | C30: =IFERROR(VLOOKUP($A30,EVENTO!$A$2:$C$4999,3,FALSE),"") -> UFC | E30: OUTSOURCING DE IMPRESSÃO POLICROMÁTICO – PÁGINAS – A4 | F30: EXCEDENTE A FRANQUIA SEM PAPEL | G30: 9600 | H30: 0.19918
A31: 17 | B31: =IFERROR(VLOOKUP($A31,EVENTO!$A$2:$C$4999,2,FALSE),"") -> APOSTILAMENTO | C31: =IFERROR(VLOOKUP($A31,EVENTO!$A$2:$C$4999,3,FALSE),"") -> UFC | E31: OUTSOURCING DE IMPRESSÃO MONOCROMÁTICO – PÁGINAS A3 | F31: DENTRO DA FRANQUIA SEM PAPEL | G31: 152652 | H31: 0.16773
A32: 17 | B32: =IFERROR(VLOOKUP($A32,EVENTO!$A$2:$C$4999,2,FALSE),"") -> APOSTILAMENTO | C32: =IFERROR(VLOOKUP($A32,EVENTO!$A$2:$C$4999,3,FALSE),"") -> UFC | E32: OUTSOURCING DE IMPRESSÃO MONOCROMÁTICO – PÁGINAS A3 | F32: EXCEDENTE A FRANQUIA SEM PAPEL | G32: 101760 | H32: 0.08386
A33: 18 | B33: =IFERROR(VLOOKUP($A33,EVENTO!$A$2:$C$4999,2,FALSE),"") -> CADASTRO | C33: =IFERROR(VLOOKUP($A33,EVENTO!$A$2:$C$4999,3,FALSE),"") -> IFCE CAMOCIM | D33: IMPRESSORA MONOCROMÁTICO – PÁGINAS A4 | E33: OUTSOURCING DE IMPRESSÃO MONOCROMÁTICO – PÁGINAS A4 | F33: DENTRO DA FRANQUIA SEM PAPEL | G33: 6000 | H33: 0.049
A34: 18 | B34: =IFERROR(VLOOKUP($A34,EVENTO!$A$2:$C$4999,2,FALSE),"") -> CADASTRO | C34: =IFERROR(VLOOKUP($A34,EVENTO!$A$2:$C$4999,3,FALSE),"") -> IFCE CAMOCIM | D34: IMPRESSORA MONOCROMÁTICO – PÁGINAS A4 | E34: OUTSOURCING DE IMPRESSÃO MONOCROMÁTICO – PÁGINAS A4 | F34: EXCEDENTE A FRANQUIA SEM PAPEL | G34: 3000 | H34: 0.04
A35: 18 | B35: =IFERROR(VLOOKUP($A35,EVENTO!$A$2:$C$4999,2,FALSE),"") -> CADASTRO | C35: =IFERROR(VLOOKUP($A35,EVENTO!$A$2:$C$4999,3,FALSE),"") -> IFCE CAMOCIM | D35: IMPRESSORA POLICROMÁTICO – PÁGINAS – A4 | E35: OUTSOURCING DE IMPRESSÃO POLICROMÁTICO – PÁGINAS – A4 | F35: DENTRO DA FRANQUIA SEM PAPEL | G35: 2000 | H35: 0.29
A36: 18 | B36: =IFERROR(VLOOKUP($A36,EVENTO!$A$2:$C$4999,2,FALSE),"") -> CADASTRO | C36: =IFERROR(VLOOKUP($A36,EVENTO!$A$2:$C$4999,3,FALSE),"") -> IFCE CAMOCIM | D36: IMPRESSORA POLICROMÁTICO – PÁGINAS – A4 | E36: OUTSOURCING DE IMPRESSÃO POLICROMÁTICO – PÁGINAS – A4 | F36: EXCEDENTE A FRANQUIA SEM PAPEL | G36: 300 | H36: 0.19
A37: 19 | B37: =IFERROR(VLOOKUP($A37,EVENTO!$A$2:$C$4999,2,FALSE),"") -> ADITIVO DE REAJUSTE E PRAZO | C37: =IFERROR(VLOOKUP($A37,EVENTO!$A$2:$C$4999,3,FALSE),"") -> IFCE CAMOCIM | E37: OUTSOURCING DE IMPRESSÃO MONOCROMÁTICO – PÁGINAS A4 | F37: DENTRO DA FRANQUIA SEM PAPEL | G37: 6000 | H37: 0.052
A38: 19 | B38: =IFERROR(VLOOKUP($A38,EVENTO!$A$2:$C$4999,2,FALSE),"") -> ADITIVO DE REAJUSTE E PRAZO | C38: =IFERROR(VLOOKUP($A38,EVENTO!$A$2:$C$4999,3,FALSE),"") -> IFCE CAMOCIM | E38: OUTSOURCING DE IMPRESSÃO MONOCROMÁTICO – PÁGINAS A4 | F38: EXCEDENTE A FRANQUIA SEM PAPEL | G38: 3000 | H38: 0.042
A39: 19 | B39: =IFERROR(VLOOKUP($A39,EVENTO!$A$2:$C$4999,2,FALSE),"") -> ADITIVO DE REAJUSTE E PRAZO | C39: =IFERROR(VLOOKUP($A39,EVENTO!$A$2:$C$4999,3,FALSE),"") -> IFCE CAMOCIM | E39: OUTSOURCING DE IMPRESSÃO POLICROMÁTICO – PÁGINAS – A4 | F39: DENTRO DA FRANQUIA SEM PAPEL | G39: 2000 | H39: 0.3
A40: 19 | B40: =IFERROR(VLOOKUP($A40,EVENTO!$A$2:$C$4999,2,FALSE),"") -> ADITIVO DE REAJUSTE E PRAZO | C40: =IFERROR(VLOOKUP($A40,EVENTO!$A$2:$C$4999,3,FALSE),"") -> IFCE CAMOCIM | E40: OUTSOURCING DE IMPRESSÃO POLICROMÁTICO – PÁGINAS – A4 | F40: EXCEDENTE A FRANQUIA SEM PAPEL | G40: 300 | H40: 0.2
A41: 20 | B41: =IFERROR(VLOOKUP($A41,EVENTO!$A$2:$C$4999,2,FALSE),"") -> CADASTRO | C41: =IFERROR(VLOOKUP($A41,EVENTO!$A$2:$C$4999,3,FALSE),"") -> IFCE CAUCAIA | D41: IMPRESSORA MONOCROMÁTICO – PÁGINAS A4 | E41: OUTSOURCING DE IMPRESSÃO MONOCROMÁTICO – PÁGINAS A4 | F41: DENTRO DA FRANQUIA SEM PAPEL | G41: 336000 | H41: 0.049
A42: 20 | B42: =IFERROR(VLOOKUP($A42,EVENTO!$A$2:$C$4999,2,FALSE),"") -> CADASTRO | C42: =IFERROR(VLOOKUP($A42,EVENTO!$A$2:$C$4999,3,FALSE),"") -> IFCE CAUCAIA | D42: IMPRESSORA MONOCROMÁTICO – PÁGINAS A4 | E42: OUTSOURCING DE IMPRESSÃO MONOCROMÁTICO – PÁGINAS A4 | F42: EXCEDENTE A FRANQUIA SEM PAPEL | G42: 60000 | H42: 0.04
A43: 21 | B43: =IFERROR(VLOOKUP($A43,EVENTO!$A$2:$C$4999,2,FALSE),"") -> APOSTILAMENTO | C43: =IFERROR(VLOOKUP($A43,EVENTO!$A$2:$C$4999,3,FALSE),"") -> IFCE CAUCAIA | E43: OUTSOURCING DE IMPRESSÃO MONOCROMÁTICO – PÁGINAS A4 | F43: DENTRO DA FRANQUIA SEM PAPEL | G43: 336000 | H43: 0.051
A44: 21 | B44: =IFERROR(VLOOKUP($A44,EVENTO!$A$2:$C$4999,2,FALSE),"") -> APOSTILAMENTO | C44: =IFERROR(VLOOKUP($A44,EVENTO!$A$2:$C$4999,3,FALSE),"") -> IFCE CAUCAIA | E44: OUTSOURCING DE IMPRESSÃO MONOCROMÁTICO – PÁGINAS A4 | F44: EXCEDENTE A FRANQUIA SEM PAPEL | G44: 60000 | H44: 0.041
A45: 23 | B45: =IFERROR(VLOOKUP($A45,EVENTO!$A$2:$C$4999,2,FALSE),"") -> CADASTRO | C45: =IFERROR(VLOOKUP($A45,EVENTO!$A$2:$C$4999,3,FALSE),"") -> IFCE ITAPIPOCA | D45: IMPRESSORA MONOCROMÁTICO – PÁGINAS A4 | E45: OUTSOURCING DE IMPRESSÃO MONOCROMÁTICO – PÁGINAS A4 | F45: DENTRO DA FRANQUIA SEM PAPEL | G45: 60000 | H45: 0.049
A46: 23 | B46: =IFERROR(VLOOKUP($A46,EVENTO!$A$2:$C$4999,2,FALSE),"") -> CADASTRO | C46: =IFERROR(VLOOKUP($A46,EVENTO!$A$2:$C$4999,3,FALSE),"") -> IFCE ITAPIPOCA | D46: IMPRESSORA MONOCROMÁTICO – PÁGINAS A4 | E46: OUTSOURCING DE IMPRESSÃO MONOCROMÁTICO – PÁGINAS A4 | F46: EXCEDENTE A FRANQUIA SEM PAPEL | G46: 36000 | H46: 0.04
A47: 23 | B47: =IFERROR(VLOOKUP($A47,EVENTO!$A$2:$C$4999,2,FALSE),"") -> CADASTRO | C47: =IFERROR(VLOOKUP($A47,EVENTO!$A$2:$C$4999,3,FALSE),"") -> IFCE ITAPIPOCA | D47: IMPRESSORA POLICROMÁTICO – PÁGINAS – A4 | E47: OUTSOURCING DE IMPRESSÃO POLICROMÁTICO – PÁGINAS – A4 | F47: DENTRO DA FRANQUIA SEM PAPEL | G47: 36000 | H47: 0.29
A48: 23 | B48: =IFERROR(VLOOKUP($A48,EVENTO!$A$2:$C$4999,2,FALSE),"") -> CADASTRO | C48: =IFERROR(VLOOKUP($A48,EVENTO!$A$2:$C$4999,3,FALSE),"") -> IFCE ITAPIPOCA | D48: IMPRESSORA POLICROMÁTICO – PÁGINAS – A4 | E48: OUTSOURCING DE IMPRESSÃO POLICROMÁTICO – PÁGINAS – A4 | F48: EXCEDENTE A FRANQUIA SEM PAPEL | G48: 36000 | H48: 0.19
A49: 23 | B49: =IFERROR(VLOOKUP($A49,EVENTO!$A$2:$C$4999,2,FALSE),"") -> CADASTRO | C49: =IFERROR(VLOOKUP($A49,EVENTO!$A$2:$C$4999,3,FALSE),"") -> IFCE ITAPIPOCA | D49: IMPRESSORA MONOCROMÁTICO – PÁGINAS A3 | E49: OUTSOURCING DE IMPRESSÃO MONOCROMÁTICO – PÁGINAS A3 | F49: DENTRO DA FRANQUIA SEM PAPEL | G49: 18000 | H49: 0.16
A50: 24 | B50: =IFERROR(VLOOKUP($A50,EVENTO!$A$2:$C$4999,2,FALSE),"") -> ADITIVO DE REAJUSTE E PRAZO | C50: =IFERROR(VLOOKUP($A50,EVENTO!$A$2:$C$4999,3,FALSE),"") -> IFCE ITAPIPOCA | E50: OUTSOURCING DE IMPRESSÃO MONOCROMÁTICO – PÁGINAS A4 | F50: DENTRO DA FRANQUIA SEM PAPEL | G50: 60000 | H50: 0.052
A51: 24 | B51: =IFERROR(VLOOKUP($A51,EVENTO!$A$2:$C$4999,2,FALSE),"") -> ADITIVO DE REAJUSTE E PRAZO | C51: =IFERROR(VLOOKUP($A51,EVENTO!$A$2:$C$4999,3,FALSE),"") -> IFCE ITAPIPOCA | E51: OUTSOURCING DE IMPRESSÃO MONOCROMÁTICO – PÁGINAS A4 | F51: EXCEDENTE A FRANQUIA SEM PAPEL | G51: 36000 | H51: 0.04216
A52: 24 | B52: =IFERROR(VLOOKUP($A52,EVENTO!$A$2:$C$4999,2,FALSE),"") -> ADITIVO DE REAJUSTE E PRAZO | C52: =IFERROR(VLOOKUP($A52,EVENTO!$A$2:$C$4999,3,FALSE),"") -> IFCE ITAPIPOCA | E52: OUTSOURCING DE IMPRESSÃO POLICROMÁTICO – PÁGINAS – A4 | F52: DENTRO DA FRANQUIA SEM PAPEL | G52: 36000 | H52: 0.306
A53: 24 | B53: =IFERROR(VLOOKUP($A53,EVENTO!$A$2:$C$4999,2,FALSE),"") -> ADITIVO DE REAJUSTE E PRAZO | C53: =IFERROR(VLOOKUP($A53,EVENTO!$A$2:$C$4999,3,FALSE),"") -> IFCE ITAPIPOCA | E53: OUTSOURCING DE IMPRESSÃO POLICROMÁTICO – PÁGINAS – A4 | F53: EXCEDENTE A FRANQUIA SEM PAPEL | G53: 36000 | H53: 0.2003
A54: 24 | B54: =IFERROR(VLOOKUP($A54,EVENTO!$A$2:$C$4999,2,FALSE),"") -> ADITIVO DE REAJUSTE E PRAZO | C54: =IFERROR(VLOOKUP($A54,EVENTO!$A$2:$C$4999,3,FALSE),"") -> IFCE ITAPIPOCA | E54: OUTSOURCING DE IMPRESSÃO MONOCROMÁTICO – PÁGINAS A3 | F54: DENTRO DA FRANQUIA SEM PAPEL | G54: 18000 | H54: 0.1687
A55: 25 | B55: =IFERROR(VLOOKUP($A55,EVENTO!$A$2:$C$4999,2,FALSE),"") -> CADASTRO | C55: =IFERROR(VLOOKUP($A55,EVENTO!$A$2:$C$4999,3,FALSE),"") -> IFCE PARACURU | D55: IMPRESSORA MONOCROMÁTICO – PÁGINAS A4 | E55: OUTSOURCING DE IMPRESSÃO MONOCROMÁTICO – PÁGINAS A4 | F55: DENTRO DA FRANQUIA SEM PAPEL | G55: 12000 | H55: 0.049
A56: 25 | B56: =IFERROR(VLOOKUP($A56,EVENTO!$A$2:$C$4999,2,FALSE),"") -> CADASTRO | C56: =IFERROR(VLOOKUP($A56,EVENTO!$A$2:$C$4999,3,FALSE),"") -> IFCE PARACURU | D56: IMPRESSORA POLICROMÁTICO – PÁGINAS – A4 | E56: OUTSOURCING DE IMPRESSÃO POLICROMÁTICO – PÁGINAS – A4 | F56: DENTRO DA FRANQUIA SEM PAPEL | G56: 800 | H56: 0.29
A57: 27 | B57: =IFERROR(VLOOKUP($A57,EVENTO!$A$2:$C$4999,2,FALSE),"") -> CADASTRO | C57: =IFERROR(VLOOKUP($A57,EVENTO!$A$2:$C$4999,3,FALSE),"") -> IFCE JUAZEIRO DO NORTE | D57: IMPRESSORA MONOCROMÁTICO – PÁGINAS A4 | E57: OUTSOURCING DE IMPRESSÃO MONOCROMÁTICO – PÁGINAS A4 | F57: DENTRO DA FRANQUIA SEM PAPEL | G57: 30000 | H57: 0.049
A58: 27 | B58: =IFERROR(VLOOKUP($A58,EVENTO!$A$2:$C$4999,2,FALSE),"") -> CADASTRO | C58: =IFERROR(VLOOKUP($A58,EVENTO!$A$2:$C$4999,3,FALSE),"") -> IFCE JUAZEIRO DO NORTE | D58: IMPRESSORA MONOCROMÁTICO – PÁGINAS A4 | E58: OUTSOURCING DE IMPRESSÃO MONOCROMÁTICO – PÁGINAS A4 | F58: EXCEDENTE A FRANQUIA SEM PAPEL | G58: 18000 | H58: 0.04
A59: 27 | B59: =IFERROR(VLOOKUP($A59,EVENTO!$A$2:$C$4999,2,FALSE),"") -> CADASTRO | C59: =IFERROR(VLOOKUP($A59,EVENTO!$A$2:$C$4999,3,FALSE),"") -> IFCE JUAZEIRO DO NORTE | D59: IMPRESSORA POLICROMÁTICO – PÁGINAS – A4 | E59: OUTSOURCING DE IMPRESSÃO POLICROMÁTICO – PÁGINAS – A4 | F59: DENTRO DA FRANQUIA SEM PAPEL | G59: 1200 | H59: 0.29
A60: 27 | B60: =IFERROR(VLOOKUP($A60,EVENTO!$A$2:$C$4999,2,FALSE),"") -> CADASTRO | C60: =IFERROR(VLOOKUP($A60,EVENTO!$A$2:$C$4999,3,FALSE),"") -> IFCE JUAZEIRO DO NORTE | D60: IMPRESSORA POLICROMÁTICO – PÁGINAS – A4 | E60: OUTSOURCING DE IMPRESSÃO POLICROMÁTICO – PÁGINAS – A4 | F60: EXCEDENTE A FRANQUIA SEM PAPEL | G60: 800 | H60: 0.19
A61: 27 | B61: =IFERROR(VLOOKUP($A61,EVENTO!$A$2:$C$4999,2,FALSE),"") -> CADASTRO | C61: =IFERROR(VLOOKUP($A61,EVENTO!$A$2:$C$4999,3,FALSE),"") -> IFCE JUAZEIRO DO NORTE | D61: IMPRESSORA MONOCROMÁTICO – PÁGINAS A3 | E61: OUTSOURCING DE IMPRESSÃO MONOCROMÁTICO – PÁGINAS A3 | F61: DENTRO DA FRANQUIA SEM PAPEL | G61: 1000 | H61: 0.16
A62: 27 | B62: =IFERROR(VLOOKUP($A62,EVENTO!$A$2:$C$4999,2,FALSE),"") -> CADASTRO | C62: =IFERROR(VLOOKUP($A62,EVENTO!$A$2:$C$4999,3,FALSE),"") -> IFCE JUAZEIRO DO NORTE | D62: IMPRESSORA MONOCROMÁTICO – PÁGINAS A3 | E62: OUTSOURCING DE IMPRESSÃO MONOCROMÁTICO – PÁGINAS A3 | F62: EXCEDENTE A FRANQUIA SEM PAPEL | G62: 600 | H62: 0.08
A63: 28 | B63: =IFERROR(VLOOKUP($A63,EVENTO!$A$2:$C$4999,2,FALSE),"") -> ADITIVO DE REAJUSTE E PRAZO | C63: =IFERROR(VLOOKUP($A63,EVENTO!$A$2:$C$4999,3,FALSE),"") -> IFCE JUAZEIRO DO NORTE | E63: OUTSOURCING DE IMPRESSÃO MONOCROMÁTICO – PÁGINAS A4 | F63: DENTRO DA FRANQUIA SEM PAPEL | G63: 30000 | H63: 0.051534461
A64: 28 | B64: =IFERROR(VLOOKUP($A64,EVENTO!$A$2:$C$4999,2,FALSE),"") -> ADITIVO DE REAJUSTE E PRAZO | C64: =IFERROR(VLOOKUP($A64,EVENTO!$A$2:$C$4999,3,FALSE),"") -> IFCE JUAZEIRO DO NORTE | E64: OUTSOURCING DE IMPRESSÃO MONOCROMÁTICO – PÁGINAS A4 | F64: EXCEDENTE A FRANQUIA SEM PAPEL | G64: 18000 | H64: 0.042068948
A65: 28 | B65: =IFERROR(VLOOKUP($A65,EVENTO!$A$2:$C$4999,2,FALSE),"") -> ADITIVO DE REAJUSTE E PRAZO | C65: =IFERROR(VLOOKUP($A65,EVENTO!$A$2:$C$4999,3,FALSE),"") -> IFCE JUAZEIRO DO NORTE | E65: OUTSOURCING DE IMPRESSÃO POLICROMÁTICO – PÁGINAS – A4 | F65: DENTRO DA FRANQUIA SEM PAPEL | G65: 1200 | H65: 0.30499987
A66: 28 | B66: =IFERROR(VLOOKUP($A66,EVENTO!$A$2:$C$4999,2,FALSE),"") -> ADITIVO DE REAJUSTE E PRAZO | C66: =IFERROR(VLOOKUP($A66,EVENTO!$A$2:$C$4999,3,FALSE),"") -> IFCE JUAZEIRO DO NORTE | E66: OUTSOURCING DE IMPRESSÃO POLICROMÁTICO – PÁGINAS – A4 | F66: EXCEDENTE A FRANQUIA SEM PAPEL | G66: 800 | H66: 0.1998275
A67: 28 | B67: =IFERROR(VLOOKUP($A67,EVENTO!$A$2:$C$4999,2,FALSE),"") -> ADITIVO DE REAJUSTE E PRAZO | C67: =IFERROR(VLOOKUP($A67,EVENTO!$A$2:$C$4999,3,FALSE),"") -> IFCE JUAZEIRO DO NORTE | E67: OUTSOURCING DE IMPRESSÃO MONOCROMÁTICO – PÁGINAS A3 | F67: DENTRO DA FRANQUIA SEM PAPEL | G67: 1000 | H67: 0.16827579
A68: 28 | B68: =IFERROR(VLOOKUP($A68,EVENTO!$A$2:$C$4999,2,FALSE),"") -> ADITIVO DE REAJUSTE E PRAZO | C68: =IFERROR(VLOOKUP($A68,EVENTO!$A$2:$C$4999,3,FALSE),"") -> IFCE JUAZEIRO DO NORTE | E68: OUTSOURCING DE IMPRESSÃO MONOCROMÁTICO – PÁGINAS A3 | F68: EXCEDENTE A FRANQUIA SEM PAPEL | G68: 600 | H68: 0.084137896
A69: 29 | B69: =IFERROR(VLOOKUP($A69,EVENTO!$A$2:$C$4999,2,FALSE),"") -> CADASTRO | C69: =IFERROR(VLOOKUP($A69,EVENTO!$A$2:$C$4999,3,FALSE),"") -> MINISTÉRIO DA AGRICULTURA E PECUÁRIA/SUPERINTENDÊNCIA FEDERAL DE AGRICULTURA E PECUÁRIA NO PARANÁ (SFA-PR/MAPA) | D69: IMPRESSORA MONOCROMÁTICO – PÁGINAS A4 | E69: OUTSOURCING DE IMPRESSÃO MONOCROMÁTICO – PÁGINAS A4 | F69: DENTRO DA FRANQUIA SEM PAPEL ATÉ 500 PG/MÊS/EQUIPAMENTO | G69: 2000 | H69: 0.1538
A70: 29 | B70: =IFERROR(VLOOKUP($A70,EVENTO!$A$2:$C$4999,2,FALSE),"") -> CADASTRO | C70: =IFERROR(VLOOKUP($A70,EVENTO!$A$2:$C$4999,3,FALSE),"") -> MINISTÉRIO DA AGRICULTURA E PECUÁRIA/SUPERINTENDÊNCIA FEDERAL DE AGRICULTURA E PECUÁRIA NO PARANÁ (SFA-PR/MAPA) | D70: IMPRESSORA MONOCROMÁTICO – PÁGINAS A4 | E70: OUTSOURCING DE IMPRESSÃO MONOCROMÁTICO – PÁGINAS A4 | F70: EXCEDENTE A FRANQUIA SEM PAPEL ATÉ 500 PG/MÊS/EQUIPAMENTO | G70: 2000 | H70: 0.1329
A71: 29 | B71: =IFERROR(VLOOKUP($A71,EVENTO!$A$2:$C$4999,2,FALSE),"") -> CADASTRO | C71: =IFERROR(VLOOKUP($A71,EVENTO!$A$2:$C$4999,3,FALSE),"") -> MINISTÉRIO DA AGRICULTURA E PECUÁRIA/SUPERINTENDÊNCIA FEDERAL DE AGRICULTURA E PECUÁRIA NO PARANÁ (SFA-PR/MAPA) | D71: IMPRESSORA MONOCROMÁTICO – PÁGINAS A4 | E71: OUTSOURCING DE IMPRESSÃO MONOCROMÁTICO – PÁGINAS A4 | F71: DENTRO DA FRANQUIA SEM PAPEL ATÉ 5.000 PG/MÊS/EQUIPAMENTO | G71: 35000 | H71: 0.1538
A72: 29 | B72: =IFERROR(VLOOKUP($A72,EVENTO!$A$2:$C$4999,2,FALSE),"") -> CADASTRO | C72: =IFERROR(VLOOKUP($A72,EVENTO!$A$2:$C$4999,3,FALSE),"") -> MINISTÉRIO DA AGRICULTURA E PECUÁRIA/SUPERINTENDÊNCIA FEDERAL DE AGRICULTURA E PECUÁRIA NO PARANÁ (SFA-PR/MAPA) | D72: IMPRESSORA MONOCROMÁTICO – PÁGINAS A4 | E72: OUTSOURCING DE IMPRESSÃO MONOCROMÁTICO – PÁGINAS A4 | F72: EXCEDENTE A FRANQUIA SEM PAPEL ATÉ 5.000 PG/MÊS/EQUIPAMENTO | G72: 35000 | H72: 0.1329
A73: 30 | B73: =IFERROR(VLOOKUP($A73,EVENTO!$A$2:$C$4999,2,FALSE),"") -> CADASTRO | C73: =IFERROR(VLOOKUP($A73,EVENTO!$A$2:$C$4999,3,FALSE),"") -> CAPITANIA DOS PORTOS DE SERGIPE | D73: IMPRESSORA MONOCROMÁTICO – PÁGINAS A4 | E73: OUTSOURCING DE IMPRESSÃO MONOCROMÁTICO – PÁGINAS A3 | F73: DENTRO DA FRANQUIA SEM PAPEL | G73: 30000 | H73: 0.049
A74: 30 | B74: =IFERROR(VLOOKUP($A74,EVENTO!$A$2:$C$4999,2,FALSE),"") -> CADASTRO | C74: =IFERROR(VLOOKUP($A74,EVENTO!$A$2:$C$4999,3,FALSE),"") -> CAPITANIA DOS PORTOS DE SERGIPE | D74: IMPRESSORA MONOCROMÁTICO – PÁGINAS A4 | E74: OUTSOURCING DE IMPRESSÃO MONOCROMÁTICO – PÁGINAS A4 | F74: DENTRO DA FRANQUIA SEM PAPEL | G74: 8000 | H74: 0.04
A75: 31 | B75: =IFERROR(VLOOKUP($A75,EVENTO!$A$2:$C$4999,2,FALSE),"") -> ADITIVO DE REAJUSTE E PRAZO | C75: =IFERROR(VLOOKUP($A75,EVENTO!$A$2:$C$4999,3,FALSE),"") -> CAPITANIA DOS PORTOS DE SERGIPE | E75: OUTSOURCING DE IMPRESSÃO MONOCROMÁTICO – PÁGINAS A3 | F75: DENTRO DA FRANQUIA SEM PAPEL | G75: 30000 | H75: 0.0517
A76: 31 | B76: =IFERROR(VLOOKUP($A76,EVENTO!$A$2:$C$4999,2,FALSE),"") -> ADITIVO DE REAJUSTE E PRAZO | C76: =IFERROR(VLOOKUP($A76,EVENTO!$A$2:$C$4999,3,FALSE),"") -> CAPITANIA DOS PORTOS DE SERGIPE | E76: OUTSOURCING DE IMPRESSÃO MONOCROMÁTICO – PÁGINAS A4 | F76: DENTRO DA FRANQUIA SEM PAPEL | G76: 8000 | H76: 0.0422
A77: 32 | B77: =IFERROR(VLOOKUP($A77,EVENTO!$A$2:$C$4999,2,FALSE),"") -> CADASTRO | C77: =IFERROR(VLOOKUP($A77,EVENTO!$A$2:$C$4999,3,FALSE),"") -> IFRN CAMPUS CEARÁ-MIRIM | D77: IMPRESSORA MONOCROMÁTICO – PÁGINAS A4 | E77: OUTSOURCING DE IMPRESSÃO MONOCROMÁTICO – PÁGINAS A4 | F77: DENTRO DA FRANQUIA SEM PAPEL | G77: 192000 | H77: 0.049
A78: 32 | B78: =IFERROR(VLOOKUP($A78,EVENTO!$A$2:$C$4999,2,FALSE),"") -> CADASTRO | C78: =IFERROR(VLOOKUP($A78,EVENTO!$A$2:$C$4999,3,FALSE),"") -> IFRN CAMPUS CEARÁ-MIRIM | D78: IMPRESSORA MONOCROMÁTICO – PÁGINAS A4 | E78: OUTSOURCING DE IMPRESSÃO MONOCROMÁTICO – PÁGINAS A4 | F78: EXCEDENTE A FRANQUIA SEM PAPEL | G78: 96000 | H78: 0.04
A79: 32 | B79: =IFERROR(VLOOKUP($A79,EVENTO!$A$2:$C$4999,2,FALSE),"") -> CADASTRO | C79: =IFERROR(VLOOKUP($A79,EVENTO!$A$2:$C$4999,3,FALSE),"") -> IFRN CAMPUS CEARÁ-MIRIM | D79: IMPRESSORA POLICROMÁTICO – PÁGINAS – A4 | E79: OUTSOURCING DE IMPRESSÃO POLICROMÁTICO – PÁGINAS – A4 | F79: DENTRO DA FRANQUIA SEM PAPEL | G79: 6000 | H79: 0.29
A80: 32 | B80: =IFERROR(VLOOKUP($A80,EVENTO!$A$2:$C$4999,2,FALSE),"") -> CADASTRO | C80: =IFERROR(VLOOKUP($A80,EVENTO!$A$2:$C$4999,3,FALSE),"") -> IFRN CAMPUS CEARÁ-MIRIM | D80: IMPRESSORA POLICROMÁTICO – PÁGINAS – A4 | E80: OUTSOURCING DE IMPRESSÃO POLICROMÁTICO – PÁGINAS – A4 | F80: EXCEDENTE A FRANQUIA SEM PAPEL | G80: 3000 | H80: 0.19
A81: 32 | B81: =IFERROR(VLOOKUP($A81,EVENTO!$A$2:$C$4999,2,FALSE),"") -> CADASTRO | C81: =IFERROR(VLOOKUP($A81,EVENTO!$A$2:$C$4999,3,FALSE),"") -> IFRN CAMPUS CEARÁ-MIRIM | D81: IMPRESSORA MONOCROMÁTICO – PÁGINAS A3 | E81: OUTSOURCING DE IMPRESSÃO MONOCROMÁTICO – PÁGINAS A3 | F81: DENTRO DA FRANQUIA SEM PAPEL | G81: 1200 | H81: 0.16
A82: 32 | B82: =IFERROR(VLOOKUP($A82,EVENTO!$A$2:$C$4999,2,FALSE),"") -> CADASTRO | C82: =IFERROR(VLOOKUP($A82,EVENTO!$A$2:$C$4999,3,FALSE),"") -> IFRN CAMPUS CEARÁ-MIRIM | D82: IMPRESSORA MONOCROMÁTICO – PÁGINAS A3 | E82: OUTSOURCING DE IMPRESSÃO MONOCROMÁTICO – PÁGINAS A3 | F82: EXCEDENTE A FRANQUIA SEM PAPEL | G82: 600 | H82: 0.08
A83: 33 | B83: =IFERROR(VLOOKUP($A83,EVENTO!$A$2:$C$4999,2,FALSE),"") -> ADITIVO DE REAJUSTE E PRAZO | C83: =IFERROR(VLOOKUP($A83,EVENTO!$A$2:$C$4999,3,FALSE),"") -> IFRN CAMPUS CEARÁ-MIRIM | E83: OUTSOURCING DE IMPRESSÃO MONOCROMÁTICO – PÁGINAS A4 | F83: DENTRO DA FRANQUIA SEM PAPEL | G83: 192000 | H83: 0.052
A84: 33 | B84: =IFERROR(VLOOKUP($A84,EVENTO!$A$2:$C$4999,2,FALSE),"") -> ADITIVO DE REAJUSTE E PRAZO | C84: =IFERROR(VLOOKUP($A84,EVENTO!$A$2:$C$4999,3,FALSE),"") -> IFRN CAMPUS CEARÁ-MIRIM | E84: OUTSOURCING DE IMPRESSÃO MONOCROMÁTICO – PÁGINAS A4 | F84: EXCEDENTE A FRANQUIA SEM PAPEL | G84: 96000 | H84: 0.042
A85: 33 | B85: =IFERROR(VLOOKUP($A85,EVENTO!$A$2:$C$4999,2,FALSE),"") -> ADITIVO DE REAJUSTE E PRAZO | C85: =IFERROR(VLOOKUP($A85,EVENTO!$A$2:$C$4999,3,FALSE),"") -> IFRN CAMPUS CEARÁ-MIRIM | E85: OUTSOURCING DE IMPRESSÃO POLICROMÁTICO – PÁGINAS – A4 | F85: DENTRO DA FRANQUIA SEM PAPEL | G85: 6000 | H85: 0.306
A86: 33 | B86: =IFERROR(VLOOKUP($A86,EVENTO!$A$2:$C$4999,2,FALSE),"") -> ADITIVO DE REAJUSTE E PRAZO | C86: =IFERROR(VLOOKUP($A86,EVENTO!$A$2:$C$4999,3,FALSE),"") -> IFRN CAMPUS CEARÁ-MIRIM | E86: OUTSOURCING DE IMPRESSÃO POLICROMÁTICO – PÁGINAS – A4 | F86: EXCEDENTE A FRANQUIA SEM PAPEL | G86: 3000 | H86: 0.2
A87: 33 | B87: =IFERROR(VLOOKUP($A87,EVENTO!$A$2:$C$4999,2,FALSE),"") -> ADITIVO DE REAJUSTE E PRAZO | C87: =IFERROR(VLOOKUP($A87,EVENTO!$A$2:$C$4999,3,FALSE),"") -> IFRN CAMPUS CEARÁ-MIRIM | E87: OUTSOURCING DE IMPRESSÃO MONOCROMÁTICO – PÁGINAS A3 | F87: DENTRO DA FRANQUIA SEM PAPEL | G87: 1200 | H87: 0.169
A88: 33 | B88: =IFERROR(VLOOKUP($A88,EVENTO!$A$2:$C$4999,2,FALSE),"") -> ADITIVO DE REAJUSTE E PRAZO | C88: =IFERROR(VLOOKUP($A88,EVENTO!$A$2:$C$4999,3,FALSE),"") -> IFRN CAMPUS CEARÁ-MIRIM | E88: OUTSOURCING DE IMPRESSÃO MONOCROMÁTICO – PÁGINAS A3 | F88: EXCEDENTE A FRANQUIA SEM PAPEL | G88: 600 | H88: 0.084
A89: 34 | B89: =IFERROR(VLOOKUP($A89,EVENTO!$A$2:$C$4999,2,FALSE),"") -> CADASTRO | C89: =IFERROR(VLOOKUP($A89,EVENTO!$A$2:$C$4999,3,FALSE),"") -> IFRN CAMPUS NATAL | D89: IMPRESSORA MONOCROMÁTICO – PÁGINAS A4 | E89: OUTSOURCING DE IMPRESSÃO MONOCROMÁTICO – PÁGINAS A4 | F89: DENTRO DA FRANQUIA SEM PAPEL | G89: 360000 | H89: 0.049
A90: 34 | B90: =IFERROR(VLOOKUP($A90,EVENTO!$A$2:$C$4999,2,FALSE),"") -> CADASTRO | C90: =IFERROR(VLOOKUP($A90,EVENTO!$A$2:$C$4999,3,FALSE),"") -> IFRN CAMPUS NATAL | D90: IMPRESSORA MONOCROMÁTICO – PÁGINAS A4 | E90: OUTSOURCING DE IMPRESSÃO MONOCROMÁTICO – PÁGINAS A4 | F90: EXCEDENTE A FRANQUIA SEM PAPEL | G90: 60000 | H90: 0.04
A91: 34 | B91: =IFERROR(VLOOKUP($A91,EVENTO!$A$2:$C$4999,2,FALSE),"") -> CADASTRO | C91: =IFERROR(VLOOKUP($A91,EVENTO!$A$2:$C$4999,3,FALSE),"") -> IFRN CAMPUS NATAL | D91: IMPRESSORA POLICROMÁTICO – PÁGINAS – A4 | E91: OUTSOURCING DE IMPRESSÃO POLICROMÁTICO – PÁGINAS – A4 | F91: DENTRO DA FRANQUIA SEM PAPEL | G91: 12000 | H91: 0.29
A92: 34 | B92: =IFERROR(VLOOKUP($A92,EVENTO!$A$2:$C$4999,2,FALSE),"") -> CADASTRO | C92: =IFERROR(VLOOKUP($A92,EVENTO!$A$2:$C$4999,3,FALSE),"") -> IFRN CAMPUS NATAL | D92: IMPRESSORA POLICROMÁTICO – PÁGINAS – A4 | E92: OUTSOURCING DE IMPRESSÃO POLICROMÁTICO – PÁGINAS – A4 | F92: EXCEDENTE A FRANQUIA SEM PAPEL | G92: 6000 | H92: 0.19
A93: 34 | B93: =IFERROR(VLOOKUP($A93,EVENTO!$A$2:$C$4999,2,FALSE),"") -> CADASTRO | C93: =IFERROR(VLOOKUP($A93,EVENTO!$A$2:$C$4999,3,FALSE),"") -> IFRN CAMPUS NATAL | D93: IMPRESSORA MONOCROMÁTICO – PÁGINAS A3 | E93: OUTSOURCING DE IMPRESSÃO MONOCROMÁTICO – PÁGINAS A3 | F93: DENTRO DA FRANQUIA SEM PAPEL | G93: 1200 | H93: 0.16
A94: 35 | B94: =IFERROR(VLOOKUP($A94,EVENTO!$A$2:$C$4999,2,FALSE),"") -> ADITIVO DE REAJUSTE E PRAZO | C94: =IFERROR(VLOOKUP($A94,EVENTO!$A$2:$C$4999,3,FALSE),"") -> IFRN CAMPUS NATAL | D94: IMPRESSORA MONOCROMÁTICO – PÁGINAS A3 | E94: OUTSOURCING DE IMPRESSÃO MONOCROMÁTICO – PÁGINAS A3 | F94: EXCEDENTE A FRANQUIA SEM PAPEL | G94: 600 | H94: 0.08
A95: 35 | B95: =IFERROR(VLOOKUP($A95,EVENTO!$A$2:$C$4999,2,FALSE),"") -> ADITIVO DE REAJUSTE E PRAZO | C95: =IFERROR(VLOOKUP($A95,EVENTO!$A$2:$C$4999,3,FALSE),"") -> IFRN CAMPUS NATAL | E95: OUTSOURCING DE IMPRESSÃO MONOCROMÁTICO – PÁGINAS A4 | F95: DENTRO DA FRANQUIA SEM PAPEL | G95: 360000 | H95: 0.05134476
A96: 35 | B96: =IFERROR(VLOOKUP($A96,EVENTO!$A$2:$C$4999,2,FALSE),"") -> ADITIVO DE REAJUSTE E PRAZO | C96: =IFERROR(VLOOKUP($A96,EVENTO!$A$2:$C$4999,3,FALSE),"") -> IFRN CAMPUS NATAL | E96: OUTSOURCING DE IMPRESSÃO MONOCROMÁTICO – PÁGINAS A4 | F96: EXCEDENTE A FRANQUIA SEM PAPEL | G96: 60000 | H96: 0.04191409
A97: 35 | B97: =IFERROR(VLOOKUP($A97,EVENTO!$A$2:$C$4999,2,FALSE),"") -> ADITIVO DE REAJUSTE E PRAZO | C97: =IFERROR(VLOOKUP($A97,EVENTO!$A$2:$C$4999,3,FALSE),"") -> IFRN CAMPUS NATAL | E97: OUTSOURCING DE IMPRESSÃO POLICROMÁTICO – PÁGINAS – A4 | F97: DENTRO DA FRANQUIA SEM PAPEL | G97: 12000 | H97: 0.30387714
A98: 35 | B98: =IFERROR(VLOOKUP($A98,EVENTO!$A$2:$C$4999,2,FALSE),"") -> ADITIVO DE REAJUSTE E PRAZO | C98: =IFERROR(VLOOKUP($A98,EVENTO!$A$2:$C$4999,3,FALSE),"") -> IFRN CAMPUS NATAL | E98: OUTSOURCING DE IMPRESSÃO POLICROMÁTICO – PÁGINAS – A4 | F98: EXCEDENTE A FRANQUIA SEM PAPEL | G98: 6000 | H98: 0.19909192
A99: 35 | B99: =IFERROR(VLOOKUP($A99,EVENTO!$A$2:$C$4999,2,FALSE),"") -> ADITIVO DE REAJUSTE E PRAZO | C99: =IFERROR(VLOOKUP($A99,EVENTO!$A$2:$C$4999,3,FALSE),"") -> IFRN CAMPUS NATAL | E99: OUTSOURCING DE IMPRESSÃO MONOCROMÁTICO – PÁGINAS A3 | F99: DENTRO DA FRANQUIA SEM PAPEL | G99: 1200 | H99: 0.16765635
A100: 35 | B100: =IFERROR(VLOOKUP($A100,EVENTO!$A$2:$C$4999,2,FALSE),"") -> ADITIVO DE REAJUSTE E PRAZO | C100: =IFERROR(VLOOKUP($A100,EVENTO!$A$2:$C$4999,3,FALSE),"") -> IFRN CAMPUS NATAL | E100: OUTSOURCING DE IMPRESSÃO MONOCROMÁTICO – PÁGINAS A3 | F100: EXCEDENTE A FRANQUIA SEM PAPEL | G100: 600 | H100: 0.08382818
...

Sheet FILTRO_ITENS
A1: =IFERROR(__xludf.DUMMYFUNCTION("TRANSPOSE(FILTER(ITENS!$D:$D, ITENS!$A:$A = SERVICOS!$A2))"),"IMPRESSORA MONOCROMÁTICO – PÁGINAS A4 ") -> IMPRESSORA MONOCROMÁTICO – PÁGINAS A4 | B1: =IFERROR(__xludf.DUMMYFUNCTION("""COMPUTED_VALUE"""),"IMPRESSORA POLICROMÁTICO – PÁGINAS – A4 ") -> IMPRESSORA POLICROMÁTICO – PÁGINAS – A4 | C1: =IFERROR(__xludf.DUMMYFUNCTION("""COMPUTED_VALUE"""),"IMPRESSORA MONOCROMÁTICO – PÁGINAS A3 ") -> IMPRESSORA MONOCROMÁTICO – PÁGINAS A3
A2: =IFERROR(__xludf.DUMMYFUNCTION("TRANSPOSE(FILTER(ITENS!$D:$D, ITENS!$A:$A = SERVICOS!$A3))"),"IMPRESSORA MONOCROMÁTICO – PÁGINAS A4 ") -> IMPRESSORA MONOCROMÁTICO – PÁGINAS A4 | B2: =IFERROR(__xludf.DUMMYFUNCTION("""COMPUTED_VALUE"""),"IMPRESSORA POLICROMÁTICO – PÁGINAS – A4 ") -> IMPRESSORA POLICROMÁTICO – PÁGINAS – A4 | C2: =IFERROR(__xludf.DUMMYFUNCTION("""COMPUTED_VALUE"""),"IMPRESSORA MONOCROMÁTICO – PÁGINAS A3 ") -> IMPRESSORA MONOCROMÁTICO – PÁGINAS A3
A3: =IFERROR(__xludf.DUMMYFUNCTION("TRANSPOSE(FILTER(ITENS!$D:$D, ITENS!$A:$A = SERVICOS!$A4))"),"IMPRESSORA MONOCROMÁTICO – PÁGINAS A4 ") -> IMPRESSORA MONOCROMÁTICO – PÁGINAS A4 | B3: =IFERROR(__xludf.DUMMYFUNCTION("""COMPUTED_VALUE"""),"IMPRESSORA POLICROMÁTICO – PÁGINAS – A4 ") -> IMPRESSORA POLICROMÁTICO – PÁGINAS – A4 | C3: =IFERROR(__xludf.DUMMYFUNCTION("""COMPUTED_VALUE"""),"IMPRESSORA MONOCROMÁTICO – PÁGINAS A3 ") -> IMPRESSORA MONOCROMÁTICO – PÁGINAS A3
A4: =IFERROR(__xludf.DUMMYFUNCTION("TRANSPOSE(FILTER(ITENS!$D:$D, ITENS!$A:$A = SERVICOS!$A5))"),"IMPRESSORA MONOCROMÁTICO – PÁGINAS A4 ") -> IMPRESSORA MONOCROMÁTICO – PÁGINAS A4 | B4: =IFERROR(__xludf.DUMMYFUNCTION("""COMPUTED_VALUE"""),"IMPRESSORA POLICROMÁTICO – PÁGINAS – A4 ") -> IMPRESSORA POLICROMÁTICO – PÁGINAS – A4 | C4: =IFERROR(__xludf.DUMMYFUNCTION("""COMPUTED_VALUE"""),"IMPRESSORA MONOCROMÁTICO – PÁGINAS A3 ") -> IMPRESSORA MONOCROMÁTICO – PÁGINAS A3
A5: =IFERROR(__xludf.DUMMYFUNCTION("TRANSPOSE(FILTER(ITENS!$D:$D, ITENS!$A:$A = SERVICOS!$A6))"),"IMPRESSORA MONOCROMÁTICO – PÁGINAS A4 ") -> IMPRESSORA MONOCROMÁTICO – PÁGINAS A4 | B5: =IFERROR(__xludf.DUMMYFUNCTION("""COMPUTED_VALUE"""),"IMPRESSORA POLICROMÁTICO – PÁGINAS – A4 ") -> IMPRESSORA POLICROMÁTICO – PÁGINAS – A4 | C5: =IFERROR(__xludf.DUMMYFUNCTION("""COMPUTED_VALUE"""),"IMPRESSORA MONOCROMÁTICO – PÁGINAS A3 ") -> IMPRESSORA MONOCROMÁTICO – PÁGINAS A3
A6: =IFERROR(__xludf.DUMMYFUNCTION("TRANSPOSE(FILTER(ITENS!$D:$D, ITENS!$A:$A = SERVICOS!$A7))"),"IMPRESSORA MONOCROMÁTICO – PÁGINAS A4 ") -> IMPRESSORA MONOCROMÁTICO – PÁGINAS A4 | B6: =IFERROR(__xludf.DUMMYFUNCTION("""COMPUTED_VALUE"""),"IMPRESSORA POLICROMÁTICO – PÁGINAS – A4 ") -> IMPRESSORA POLICROMÁTICO – PÁGINAS – A4 | C6: =IFERROR(__xludf.DUMMYFUNCTION("""COMPUTED_VALUE"""),"IMPRESSORA MONOCROMÁTICO – PÁGINAS A3 ") -> IMPRESSORA MONOCROMÁTICO – PÁGINAS A3
A7: =IFERROR(__xludf.DUMMYFUNCTION("TRANSPOSE(FILTER(ITENS!$D:$D, ITENS!$A:$A = SERVICOS!$A8))")," IMPRESSÃO CORPORATIVA OU OUTSOURCING DE IMPRESSÃO, COM O FORNECIMENTO DE EQUIPAMENTOS ") -> IMPRESSÃO CORPORATIVA OU OUTSOURCING DE IMPRESSÃO, COM O FORNECIMENTO DE EQUIPAMENTOS | B7: =IFERROR(__xludf.DUMMYFUNCTION("""COMPUTED_VALUE"""),"IMPRESSÃO CORPORATIVA OU OUTSOURCING DE IMPRESSÃO, COM O FORNECIMENTO DE EQUIPAMENTOS ") -> IMPRESSÃO CORPORATIVA OU OUTSOURCING DE IMPRESSÃO, COM O FORNECIMENTO DE EQUIPAMENTOS
A8: =IFERROR(__xludf.DUMMYFUNCTION("TRANSPOSE(FILTER(ITENS!$D:$D, ITENS!$A:$A = SERVICOS!$A9))"),"#N/A") -> #N/A
A9: =IFERROR(__xludf.DUMMYFUNCTION("TRANSPOSE(FILTER(ITENS!$D:$D, ITENS!$A:$A = SERVICOS!$A10))"),"#N/A") -> #N/A
A10: =IFERROR(__xludf.DUMMYFUNCTION("TRANSPOSE(FILTER(ITENS!$D:$D, ITENS!$A:$A = SERVICOS!$A11))"),"#N/A") -> #N/A
A11: =IFERROR(__xludf.DUMMYFUNCTION("TRANSPOSE(FILTER(ITENS!$D:$D, ITENS!$A:$A = SERVICOS!$A12))"),"#N/A") -> #N/A
A12: =IFERROR(__xludf.DUMMYFUNCTION("TRANSPOSE(FILTER(ITENS!$D:$D, ITENS!$A:$A = SERVICOS!$A13))"),"#N/A") -> #N/A
A13: =IFERROR(__xludf.DUMMYFUNCTION("TRANSPOSE(FILTER(ITENS!$D:$D, ITENS!$A:$A = SERVICOS!$A14))"),"#N/A") -> #N/A
A14: =IFERROR(__xludf.DUMMYFUNCTION("TRANSPOSE(FILTER(ITENS!$D:$D, ITENS!$A:$A = SERVICOS!$A15))"),"#N/A") -> #N/A
A15: =IFERROR(__xludf.DUMMYFUNCTION("TRANSPOSE(FILTER(ITENS!$D:$D, ITENS!$A:$A = SERVICOS!$A16))"),"#N/A") -> #N/A
A16: =IFERROR(__xludf.DUMMYFUNCTION("TRANSPOSE(FILTER(ITENS!$D:$D, ITENS!$A:$A = SERVICOS!$A17))"),"IMPRESSORA POLICROMÁTICO – PÁGINAS – A4 ") -> IMPRESSORA POLICROMÁTICO – PÁGINAS – A4
A17: =IFERROR(__xludf.DUMMYFUNCTION("TRANSPOSE(FILTER(ITENS!$D:$D, ITENS!$A:$A = SERVICOS!$A18))"),"IMPRESSORA POLICROMÁTICO – PÁGINAS – A4 ") -> IMPRESSORA POLICROMÁTICO – PÁGINAS – A4
A18: =IFERROR(__xludf.DUMMYFUNCTION("TRANSPOSE(FILTER(ITENS!$D:$D, ITENS!$A:$A = SERVICOS!$A19))"),"#N/A") -> #N/A
A19: =IFERROR(__xludf.DUMMYFUNCTION("TRANSPOSE(FILTER(ITENS!$D:$D, ITENS!$A:$A = SERVICOS!$A20))"),"#N/A") -> #N/A
A20: =IFERROR(__xludf.DUMMYFUNCTION("TRANSPOSE(FILTER(ITENS!$D:$D, ITENS!$A:$A = SERVICOS!$A21))"),"IMPRESSORA MONOCROMÁTICO – PÁGINAS A4 ") -> IMPRESSORA MONOCROMÁTICO – PÁGINAS A4 | B20: =IFERROR(__xludf.DUMMYFUNCTION("""COMPUTED_VALUE"""),"IMPRESSORA POLICROMÁTICO – PÁGINAS – A4 ") -> IMPRESSORA POLICROMÁTICO – PÁGINAS – A4 | C20: =IFERROR(__xludf.DUMMYFUNCTION("""COMPUTED_VALUE"""),"IMPRESSORA MONOCROMÁTICO – PÁGINAS A3 ") -> IMPRESSORA MONOCROMÁTICO – PÁGINAS A3
A21: =IFERROR(__xludf.DUMMYFUNCTION("TRANSPOSE(FILTER(ITENS!$D:$D, ITENS!$A:$A = SERVICOS!$A22))"),"IMPRESSORA MONOCROMÁTICO – PÁGINAS A4 ") -> IMPRESSORA MONOCROMÁTICO – PÁGINAS A4 | B21: =IFERROR(__xludf.DUMMYFUNCTION("""COMPUTED_VALUE"""),"IMPRESSORA POLICROMÁTICO – PÁGINAS – A4 ") -> IMPRESSORA POLICROMÁTICO – PÁGINAS – A4 | C21: =IFERROR(__xludf.DUMMYFUNCTION("""COMPUTED_VALUE"""),"IMPRESSORA MONOCROMÁTICO – PÁGINAS A3 ") -> IMPRESSORA MONOCROMÁTICO – PÁGINAS A3
A22: =IFERROR(__xludf.DUMMYFUNCTION("TRANSPOSE(FILTER(ITENS!$D:$D, ITENS!$A:$A = SERVICOS!$A23))"),"IMPRESSORA MONOCROMÁTICO – PÁGINAS A4 ") -> IMPRESSORA MONOCROMÁTICO – PÁGINAS A4 | B22: =IFERROR(__xludf.DUMMYFUNCTION("""COMPUTED_VALUE"""),"IMPRESSORA POLICROMÁTICO – PÁGINAS – A4 ") -> IMPRESSORA POLICROMÁTICO – PÁGINAS – A4 | C22: =IFERROR(__xludf.DUMMYFUNCTION("""COMPUTED_VALUE"""),"IMPRESSORA MONOCROMÁTICO – PÁGINAS A3 ") -> IMPRESSORA MONOCROMÁTICO – PÁGINAS A3
A23: =IFERROR(__xludf.DUMMYFUNCTION("TRANSPOSE(FILTER(ITENS!$D:$D, ITENS!$A:$A = SERVICOS!$A24))"),"IMPRESSORA MONOCROMÁTICO – PÁGINAS A4 ") -> IMPRESSORA MONOCROMÁTICO – PÁGINAS A4 | B23: =IFERROR(__xludf.DUMMYFUNCTION("""COMPUTED_VALUE"""),"IMPRESSORA POLICROMÁTICO – PÁGINAS – A4 ") -> IMPRESSORA POLICROMÁTICO – PÁGINAS – A4 | C23: =IFERROR(__xludf.DUMMYFUNCTION("""COMPUTED_VALUE"""),"IMPRESSORA MONOCROMÁTICO – PÁGINAS A3 ") -> IMPRESSORA MONOCROMÁTICO – PÁGINAS A3
A24: =IFERROR(__xludf.DUMMYFUNCTION("TRANSPOSE(FILTER(ITENS!$D:$D, ITENS!$A:$A = SERVICOS!$A25))"),"IMPRESSORA MONOCROMÁTICO – PÁGINAS A4 ") -> IMPRESSORA MONOCROMÁTICO – PÁGINAS A4 | B24: =IFERROR(__xludf.DUMMYFUNCTION("""COMPUTED_VALUE"""),"IMPRESSORA POLICROMÁTICO – PÁGINAS – A4 ") -> IMPRESSORA POLICROMÁTICO – PÁGINAS – A4 | C24: =IFERROR(__xludf.DUMMYFUNCTION("""COMPUTED_VALUE"""),"IMPRESSORA MONOCROMÁTICO – PÁGINAS A3 ") -> IMPRESSORA MONOCROMÁTICO – PÁGINAS A3
A25: =IFERROR(__xludf.DUMMYFUNCTION("TRANSPOSE(FILTER(ITENS!$D:$D, ITENS!$A:$A = SERVICOS!$A26))"),"IMPRESSORA MONOCROMÁTICO – PÁGINAS A4 ") -> IMPRESSORA MONOCROMÁTICO – PÁGINAS A4 | B25: =IFERROR(__xludf.DUMMYFUNCTION("""COMPUTED_VALUE"""),"IMPRESSORA POLICROMÁTICO – PÁGINAS – A4 ") -> IMPRESSORA POLICROMÁTICO – PÁGINAS – A4 | C25: =IFERROR(__xludf.DUMMYFUNCTION("""COMPUTED_VALUE"""),"IMPRESSORA MONOCROMÁTICO – PÁGINAS A3 ") -> IMPRESSORA MONOCROMÁTICO – PÁGINAS A3
A26: =IFERROR(__xludf.DUMMYFUNCTION("TRANSPOSE(FILTER(ITENS!$D:$D, ITENS!$A:$A = SERVICOS!$A27))"),"#N/A") -> #N/A
A27: =IFERROR(__xludf.DUMMYFUNCTION("TRANSPOSE(FILTER(ITENS!$D:$D, ITENS!$A:$A = SERVICOS!$A28))"),"#N/A") -> #N/A
A28: =IFERROR(__xludf.DUMMYFUNCTION("TRANSPOSE(FILTER(ITENS!$D:$D, ITENS!$A:$A = SERVICOS!$A29))"),"#N/A") -> #N/A
A29: =IFERROR(__xludf.DUMMYFUNCTION("TRANSPOSE(FILTER(ITENS!$D:$D, ITENS!$A:$A = SERVICOS!$A30))"),"#N/A") -> #N/A
A30: =IFERROR(__xludf.DUMMYFUNCTION("TRANSPOSE(FILTER(ITENS!$D:$D, ITENS!$A:$A = SERVICOS!$A31))"),"#N/A") -> #N/A
A31: =IFERROR(__xludf.DUMMYFUNCTION("TRANSPOSE(FILTER(ITENS!$D:$D, ITENS!$A:$A = SERVICOS!$A32))"),"#N/A") -> #N/A
A32: =IFERROR(__xludf.DUMMYFUNCTION("TRANSPOSE(FILTER(ITENS!$D:$D, ITENS!$A:$A = SERVICOS!$A33))"),"IMPRESSORA MONOCROMÁTICO – PÁGINAS A4 ") -> IMPRESSORA MONOCROMÁTICO – PÁGINAS A4 | B32: =IFERROR(__xludf.DUMMYFUNCTION("""COMPUTED_VALUE"""),"IMPRESSORA POLICROMÁTICO – PÁGINAS – A4 ") -> IMPRESSORA POLICROMÁTICO – PÁGINAS – A4
A33: =IFERROR(__xludf.DUMMYFUNCTION("TRANSPOSE(FILTER(ITENS!$D:$D, ITENS!$A:$A = SERVICOS!$A34))"),"IMPRESSORA MONOCROMÁTICO – PÁGINAS A4 ") -> IMPRESSORA MONOCROMÁTICO – PÁGINAS A4 | B33: =IFERROR(__xludf.DUMMYFUNCTION("""COMPUTED_VALUE"""),"IMPRESSORA POLICROMÁTICO – PÁGINAS – A4 ") -> IMPRESSORA POLICROMÁTICO – PÁGINAS – A4
A34: =IFERROR(__xludf.DUMMYFUNCTION("TRANSPOSE(FILTER(ITENS!$D:$D, ITENS!$A:$A = SERVICOS!$A35))"),"IMPRESSORA MONOCROMÁTICO – PÁGINAS A4 ") -> IMPRESSORA MONOCROMÁTICO – PÁGINAS A4 | B34: =IFERROR(__xludf.DUMMYFUNCTION("""COMPUTED_VALUE"""),"IMPRESSORA POLICROMÁTICO – PÁGINAS – A4 ") -> IMPRESSORA POLICROMÁTICO – PÁGINAS – A4
A35: =IFERROR(__xludf.DUMMYFUNCTION("TRANSPOSE(FILTER(ITENS!$D:$D, ITENS!$A:$A = SERVICOS!$A36))"),"IMPRESSORA MONOCROMÁTICO – PÁGINAS A4 ") -> IMPRESSORA MONOCROMÁTICO – PÁGINAS A4 | B35: =IFERROR(__xludf.DUMMYFUNCTION("""COMPUTED_VALUE"""),"IMPRESSORA POLICROMÁTICO – PÁGINAS – A4 ") -> IMPRESSORA POLICROMÁTICO – PÁGINAS – A4
A36: =IFERROR(__xludf.DUMMYFUNCTION("TRANSPOSE(FILTER(ITENS!$D:$D, ITENS!$A:$A = SERVICOS!$A37))"),"#N/A") -> #N/A
A37: =IFERROR(__xludf.DUMMYFUNCTION("TRANSPOSE(FILTER(ITENS!$D:$D, ITENS!$A:$A = SERVICOS!$A38))"),"#N/A") -> #N/A
A38: =IFERROR(__xludf.DUMMYFUNCTION("TRANSPOSE(FILTER(ITENS!$D:$D, ITENS!$A:$A = SERVICOS!$A39))"),"#N/A") -> #N/A
A39: =IFERROR(__xludf.DUMMYFUNCTION("TRANSPOSE(FILTER(ITENS!$D:$D, ITENS!$A:$A = SERVICOS!$A40))"),"#N/A") -> #N/A
A40: =IFERROR(__xludf.DUMMYFUNCTION("TRANSPOSE(FILTER(ITENS!$D:$D, ITENS!$A:$A = SERVICOS!$A41))"),"IMPRESSORA MONOCROMÁTICO – PÁGINAS A4 ") -> IMPRESSORA MONOCROMÁTICO – PÁGINAS A4
A41: =IFERROR(__xludf.DUMMYFUNCTION("TRANSPOSE(FILTER(ITENS!$D:$D, ITENS!$A:$A = SERVICOS!$A42))"),"IMPRESSORA MONOCROMÁTICO – PÁGINAS A4 ") -> IMPRESSORA MONOCROMÁTICO – PÁGINAS A4
A42: =IFERROR(__xludf.DUMMYFUNCTION("TRANSPOSE(FILTER(ITENS!$D:$D, ITENS!$A:$A = SERVICOS!$A43))"),"#N/A") -> #N/A
A43: =IFERROR(__xludf.DUMMYFUNCTION("TRANSPOSE(FILTER(ITENS!$D:$D, ITENS!$A:$A = SERVICOS!$A44))"),"#N/A") -> #N/A
A44: =IFERROR(__xludf.DUMMYFUNCTION("TRANSPOSE(FILTER(ITENS!$D:$D, ITENS!$A:$A = SERVICOS!$A45))"),"IMPRESSORA MONOCROMÁTICO – PÁGINAS A4 ") -> IMPRESSORA MONOCROMÁTICO – PÁGINAS A4 | B44: =IFERROR(__xludf.DUMMYFUNCTION("""COMPUTED_VALUE"""),"IMPRESSORA POLICROMÁTICO – PÁGINAS – A4 ") -> IMPRESSORA POLICROMÁTICO – PÁGINAS – A4 | C44: =IFERROR(__xludf.DUMMYFUNCTION("""COMPUTED_VALUE"""),"IMPRESSORA MONOCROMÁTICO – PÁGINAS A3 ") -> IMPRESSORA MONOCROMÁTICO – PÁGINAS A3
A45: =IFERROR(__xludf.DUMMYFUNCTION("TRANSPOSE(FILTER(ITENS!$D:$D, ITENS!$A:$A = SERVICOS!$A46))"),"IMPRESSORA MONOCROMÁTICO – PÁGINAS A4 ") -> IMPRESSORA MONOCROMÁTICO – PÁGINAS A4 | B45: =IFERROR(__xludf.DUMMYFUNCTION("""COMPUTED_VALUE"""),"IMPRESSORA POLICROMÁTICO – PÁGINAS – A4 ") -> IMPRESSORA POLICROMÁTICO – PÁGINAS – A4 | C45: =IFERROR(__xludf.DUMMYFUNCTION("""COMPUTED_VALUE"""),"IMPRESSORA MONOCROMÁTICO – PÁGINAS A3 ") -> IMPRESSORA MONOCROMÁTICO – PÁGINAS A3
A46: =IFERROR(__xludf.DUMMYFUNCTION("TRANSPOSE(FILTER(ITENS!$D:$D, ITENS!$A:$A = SERVICOS!$A47))"),"IMPRESSORA MONOCROMÁTICO – PÁGINAS A4 ") -> IMPRESSORA MONOCROMÁTICO – PÁGINAS A4 | B46: =IFERROR(__xludf.DUMMYFUNCTION("""COMPUTED_VALUE"""),"IMPRESSORA POLICROMÁTICO – PÁGINAS – A4 ") -> IMPRESSORA POLICROMÁTICO – PÁGINAS – A4 | C46: =IFERROR(__xludf.DUMMYFUNCTION("""COMPUTED_VALUE"""),"IMPRESSORA MONOCROMÁTICO – PÁGINAS A3 ") -> IMPRESSORA MONOCROMÁTICO – PÁGINAS A3
A47: =IFERROR(__xludf.DUMMYFUNCTION("TRANSPOSE(FILTER(ITENS!$D:$D, ITENS!$A:$A = SERVICOS!$A48))"),"IMPRESSORA MONOCROMÁTICO – PÁGINAS A4 ") -> IMPRESSORA MONOCROMÁTICO – PÁGINAS A4 | B47: =IFERROR(__xludf.DUMMYFUNCTION("""COMPUTED_VALUE"""),"IMPRESSORA POLICROMÁTICO – PÁGINAS – A4 ") -> IMPRESSORA POLICROMÁTICO – PÁGINAS – A4 | C47: =IFERROR(__xludf.DUMMYFUNCTION("""COMPUTED_VALUE"""),"IMPRESSORA MONOCROMÁTICO – PÁGINAS A3 ") -> IMPRESSORA MONOCROMÁTICO – PÁGINAS A3
A48: =IFERROR(__xludf.DUMMYFUNCTION("TRANSPOSE(FILTER(ITENS!$D:$D, ITENS!$A:$A = SERVICOS!$A49))"),"IMPRESSORA MONOCROMÁTICO – PÁGINAS A4 ") -> IMPRESSORA MONOCROMÁTICO – PÁGINAS A4 | B48: =IFERROR(__xludf.DUMMYFUNCTION("""COMPUTED_VALUE"""),"IMPRESSORA POLICROMÁTICO – PÁGINAS – A4 ") -> IMPRESSORA POLICROMÁTICO – PÁGINAS – A4 | C48: =IFERROR(__xludf.DUMMYFUNCTION("""COMPUTED_VALUE"""),"IMPRESSORA MONOCROMÁTICO – PÁGINAS A3 ") -> IMPRESSORA MONOCROMÁTICO – PÁGINAS A3
A49: =IFERROR(__xludf.DUMMYFUNCTION("TRANSPOSE(FILTER(ITENS!$D:$D, ITENS!$A:$A = SERVICOS!$A50))"),"#N/A") -> #N/A
A50: =IFERROR(__xludf.DUMMYFUNCTION("TRANSPOSE(FILTER(ITENS!$D:$D, ITENS!$A:$A = SERVICOS!$A51))"),"#N/A") -> #N/A
A51: =IFERROR(__xludf.DUMMYFUNCTION("TRANSPOSE(FILTER(ITENS!$D:$D, ITENS!$A:$A = SERVICOS!$A52))"),"#N/A") -> #N/A
A52: =IFERROR(__xludf.DUMMYFUNCTION("TRANSPOSE(FILTER(ITENS!$D:$D, ITENS!$A:$A = SERVICOS!$A53))"),"#N/A") -> #N/A
A53: =IFERROR(__xludf.DUMMYFUNCTION("TRANSPOSE(FILTER(ITENS!$D:$D, ITENS!$A:$A = SERVICOS!$A54))"),"#N/A") -> #N/A
A54: =IFERROR(__xludf.DUMMYFUNCTION("TRANSPOSE(FILTER(ITENS!$D:$D, ITENS!$A:$A = SERVICOS!$A55))"),"IMPRESSORA MONOCROMÁTICO – PÁGINAS A4 ") -> IMPRESSORA MONOCROMÁTICO – PÁGINAS A4 | B54: =IFERROR(__xludf.DUMMYFUNCTION("""COMPUTED_VALUE"""),"IMPRESSORA POLICROMÁTICO – PÁGINAS – A4 ") -> IMPRESSORA POLICROMÁTICO – PÁGINAS – A4
A55: =IFERROR(__xludf.DUMMYFUNCTION("TRANSPOSE(FILTER(ITENS!$D:$D, ITENS!$A:$A = SERVICOS!$A56))"),"IMPRESSORA MONOCROMÁTICO – PÁGINAS A4 ") -> IMPRESSORA MONOCROMÁTICO – PÁGINAS A4 | B55: =IFERROR(__xludf.DUMMYFUNCTION("""COMPUTED_VALUE"""),"IMPRESSORA POLICROMÁTICO – PÁGINAS – A4 ") -> IMPRESSORA POLICROMÁTICO – PÁGINAS – A4
A56: =IFERROR(__xludf.DUMMYFUNCTION("TRANSPOSE(FILTER(ITENS!$D:$D, ITENS!$A:$A = SERVICOS!$A57))"),"IMPRESSORA MONOCROMÁTICO – PÁGINAS A4 ") -> IMPRESSORA MONOCROMÁTICO – PÁGINAS A4 | B56: =IFERROR(__xludf.DUMMYFUNCTION("""COMPUTED_VALUE"""),"IMPRESSORA MONOCROMÁTICO – PÁGINAS A4 ") -> IMPRESSORA MONOCROMÁTICO – PÁGINAS A4 | C56: =IFERROR(__xludf.DUMMYFUNCTION("""COMPUTED_VALUE"""),"IMPRESSORA MONOCROMÁTICO – PÁGINAS A3 ") -> IMPRESSORA MONOCROMÁTICO – PÁGINAS A3
A57: =IFERROR(__xludf.DUMMYFUNCTION("TRANSPOSE(FILTER(ITENS!$D:$D, ITENS!$A:$A = SERVICOS!$A58))"),"IMPRESSORA MONOCROMÁTICO – PÁGINAS A4 ") -> IMPRESSORA MONOCROMÁTICO – PÁGINAS A4 | B57: =IFERROR(__xludf.DUMMYFUNCTION("""COMPUTED_VALUE"""),"IMPRESSORA MONOCROMÁTICO – PÁGINAS A4 ") -> IMPRESSORA MONOCROMÁTICO – PÁGINAS A4 | C57: =IFERROR(__xludf.DUMMYFUNCTION("""COMPUTED_VALUE"""),"IMPRESSORA MONOCROMÁTICO – PÁGINAS A3 ") -> IMPRESSORA MONOCROMÁTICO – PÁGINAS A3
A58: =IFERROR(__xludf.DUMMYFUNCTION("TRANSPOSE(FILTER(ITENS!$D:$D, ITENS!$A:$A = SERVICOS!$A59))"),"IMPRESSORA MONOCROMÁTICO – PÁGINAS A4 ") -> IMPRESSORA MONOCROMÁTICO – PÁGINAS A4 | B58: =IFERROR(__xludf.DUMMYFUNCTION("""COMPUTED_VALUE"""),"IMPRESSORA MONOCROMÁTICO – PÁGINAS A4 ") -> IMPRESSORA MONOCROMÁTICO – PÁGINAS A4 | C58: =IFERROR(__xludf.DUMMYFUNCTION("""COMPUTED_VALUE"""),"IMPRESSORA MONOCROMÁTICO – PÁGINAS A3 ") -> IMPRESSORA MONOCROMÁTICO – PÁGINAS A3
A59: =IFERROR(__xludf.DUMMYFUNCTION("TRANSPOSE(FILTER(ITENS!$D:$D, ITENS!$A:$A = SERVICOS!$A60))"),"IMPRESSORA MONOCROMÁTICO – PÁGINAS A4 ") -> IMPRESSORA MONOCROMÁTICO – PÁGINAS A4 | B59: =IFERROR(__xludf.DUMMYFUNCTION("""COMPUTED_VALUE"""),"IMPRESSORA MONOCROMÁTICO – PÁGINAS A4 ") -> IMPRESSORA MONOCROMÁTICO – PÁGINAS A4 | C59: =IFERROR(__xludf.DUMMYFUNCTION("""COMPUTED_VALUE"""),"IMPRESSORA MONOCROMÁTICO – PÁGINAS A3 ") -> IMPRESSORA MONOCROMÁTICO – PÁGINAS A3
A60: =IFERROR(__xludf.DUMMYFUNCTION("TRANSPOSE(FILTER(ITENS!$D:$D, ITENS!$A:$A = SERVICOS!$A61))"),"IMPRESSORA MONOCROMÁTICO – PÁGINAS A4 ") -> IMPRESSORA MONOCROMÁTICO – PÁGINAS A4 | B60: =IFERROR(__xludf.DUMMYFUNCTION("""COMPUTED_VALUE"""),"IMPRESSORA MONOCROMÁTICO – PÁGINAS A4 ") -> IMPRESSORA MONOCROMÁTICO – PÁGINAS A4 | C60: =IFERROR(__xludf.DUMMYFUNCTION("""COMPUTED_VALUE"""),"IMPRESSORA MONOCROMÁTICO – PÁGINAS A3 ") -> IMPRESSORA MONOCROMÁTICO – PÁGINAS A3
A61: =IFERROR(__xludf.DUMMYFUNCTION("TRANSPOSE(FILTER(ITENS!$D:$D, ITENS!$A:$A = SERVICOS!$A62))"),"IMPRESSORA MONOCROMÁTICO – PÁGINAS A4 ") -> IMPRESSORA MONOCROMÁTICO – PÁGINAS A4 | B61: =IFERROR(__xludf.DUMMYFUNCTION("""COMPUTED_VALUE"""),"IMPRESSORA MONOCROMÁTICO – PÁGINAS A4 ") -> IMPRESSORA MONOCROMÁTICO – PÁGINAS A4 | C61: =IFERROR(__xludf.DUMMYFUNCTION("""COMPUTED_VALUE"""),"IMPRESSORA MONOCROMÁTICO – PÁGINAS A3 ") -> IMPRESSORA MONOCROMÁTICO – PÁGINAS A3
A62: =IFERROR(__xludf.DUMMYFUNCTION("TRANSPOSE(FILTER(ITENS!$D:$D, ITENS!$A:$A = SERVICOS!$A63))"),"#N/A") -> #N/A
A63: =IFERROR(__xludf.DUMMYFUNCTION("TRANSPOSE(FILTER(ITENS!$D:$D, ITENS!$A:$A = SERVICOS!$A64))"),"#N/A") -> #N/A
A64: =IFERROR(__xludf.DUMMYFUNCTION("TRANSPOSE(FILTER(ITENS!$D:$D, ITENS!$A:$A = SERVICOS!$A65))"),"#N/A") -> #N/A
A65: =IFERROR(__xludf.DUMMYFUNCTION("TRANSPOSE(FILTER(ITENS!$D:$D, ITENS!$A:$A = SERVICOS!$A66))"),"#N/A") -> #N/A
A66: =IFERROR(__xludf.DUMMYFUNCTION("TRANSPOSE(FILTER(ITENS!$D:$D, ITENS!$A:$A = SERVICOS!$A67))"),"#N/A") -> #N/A
A67: =IFERROR(__xludf.DUMMYFUNCTION("TRANSPOSE(FILTER(ITENS!$D:$D, ITENS!$A:$A = SERVICOS!$A68))"),"#N/A") -> #N/A
A68: =IFERROR(__xludf.DUMMYFUNCTION("TRANSPOSE(FILTER(ITENS!$D:$D, ITENS!$A:$A = SERVICOS!$A69))"),"IMPRESSORA MONOCROMÁTICO – PÁGINAS A4 ") -> IMPRESSORA MONOCROMÁTICO – PÁGINAS A4
A69: =IFERROR(__xludf.DUMMYFUNCTION("TRANSPOSE(FILTER(ITENS!$D:$D, ITENS!$A:$A = SERVICOS!$A70))"),"IMPRESSORA MONOCROMÁTICO – PÁGINAS A4 ") -> IMPRESSORA MONOCROMÁTICO – PÁGINAS A4
A70: =IFERROR(__xludf.DUMMYFUNCTION("TRANSPOSE(FILTER(ITENS!$D:$D, ITENS!$A:$A = SERVICOS!$A71))"),"IMPRESSORA MONOCROMÁTICO – PÁGINAS A4 ") -> IMPRESSORA MONOCROMÁTICO – PÁGINAS A4
A71: =IFERROR(__xludf.DUMMYFUNCTION("TRANSPOSE(FILTER(ITENS!$D:$D, ITENS!$A:$A = SERVICOS!$A72))"),"IMPRESSORA MONOCROMÁTICO – PÁGINAS A4 ") -> IMPRESSORA MONOCROMÁTICO – PÁGINAS A4
A72: =IFERROR(__xludf.DUMMYFUNCTION("TRANSPOSE(FILTER(ITENS!$D:$D, ITENS!$A:$A = SERVICOS!$A73))"),"IMPRESSORA MONOCROMÁTICO – PÁGINAS A4 ") -> IMPRESSORA MONOCROMÁTICO – PÁGINAS A4
A73: =IFERROR(__xludf.DUMMYFUNCTION("TRANSPOSE(FILTER(ITENS!$D:$D, ITENS!$A:$A = SERVICOS!$A74))"),"IMPRESSORA MONOCROMÁTICO – PÁGINAS A4 ") -> IMPRESSORA MONOCROMÁTICO – PÁGINAS A4
A74: =IFERROR(__xludf.DUMMYFUNCTION("TRANSPOSE(FILTER(ITENS!$D:$D, ITENS!$A:$A = SERVICOS!$A75))"),"#N/A") -> #N/A
A75: =IFERROR(__xludf.DUMMYFUNCTION("TRANSPOSE(FILTER(ITENS!$D:$D, ITENS!$A:$A = SERVICOS!$A76))"),"#N/A") -> #N/A
A76: =IFERROR(__xludf.DUMMYFUNCTION("TRANSPOSE(FILTER(ITENS!$D:$D, ITENS!$A:$A = SERVICOS!$A77))"),"IMPRESSORA MONOCROMÁTICO – PÁGINAS A4 ") -> IMPRESSORA MONOCROMÁTICO – PÁGINAS A4 | B76: =IFERROR(__xludf.DUMMYFUNCTION("""COMPUTED_VALUE"""),"IMPRESSORA POLICROMÁTICO – PÁGINAS – A4 ") -> IMPRESSORA POLICROMÁTICO – PÁGINAS – A4 | C76: =IFERROR(__xludf.DUMMYFUNCTION("""COMPUTED_VALUE"""),"IMPRESSORA MONOCROMÁTICO – PÁGINAS A3 ") -> IMPRESSORA MONOCROMÁTICO – PÁGINAS A3
A77: =IFERROR(__xludf.DUMMYFUNCTION("TRANSPOSE(FILTER(ITENS!$D:$D, ITENS!$A:$A = SERVICOS!$A78))"),"IMPRESSORA MONOCROMÁTICO – PÁGINAS A4 ") -> IMPRESSORA MONOCROMÁTICO – PÁGINAS A4 | B77: =IFERROR(__xludf.DUMMYFUNCTION("""COMPUTED_VALUE"""),"IMPRESSORA POLICROMÁTICO – PÁGINAS – A4 ") -> IMPRESSORA POLICROMÁTICO – PÁGINAS – A4 | C77: =IFERROR(__xludf.DUMMYFUNCTION("""COMPUTED_VALUE"""),"IMPRESSORA MONOCROMÁTICO – PÁGINAS A3 ") -> IMPRESSORA MONOCROMÁTICO – PÁGINAS A3
A78: =IFERROR(__xludf.DUMMYFUNCTION("TRANSPOSE(FILTER(ITENS!$D:$D, ITENS!$A:$A = SERVICOS!$A79))"),"IMPRESSORA MONOCROMÁTICO – PÁGINAS A4 ") -> IMPRESSORA MONOCROMÁTICO – PÁGINAS A4 | B78: =IFERROR(__xludf.DUMMYFUNCTION("""COMPUTED_VALUE"""),"IMPRESSORA POLICROMÁTICO – PÁGINAS – A4 ") -> IMPRESSORA POLICROMÁTICO – PÁGINAS – A4 | C78: =IFERROR(__xludf.DUMMYFUNCTION("""COMPUTED_VALUE"""),"IMPRESSORA MONOCROMÁTICO – PÁGINAS A3 ") -> IMPRESSORA MONOCROMÁTICO – PÁGINAS A3
A79: =IFERROR(__xludf.DUMMYFUNCTION("TRANSPOSE(FILTER(ITENS!$D:$D, ITENS!$A:$A = SERVICOS!$A80))"),"IMPRESSORA MONOCROMÁTICO – PÁGINAS A4 ") -> IMPRESSORA MONOCROMÁTICO – PÁGINAS A4 | B79: =IFERROR(__xludf.DUMMYFUNCTION("""COMPUTED_VALUE"""),"IMPRESSORA POLICROMÁTICO – PÁGINAS – A4 ") -> IMPRESSORA POLICROMÁTICO – PÁGINAS – A4 | C79: =IFERROR(__xludf.DUMMYFUNCTION("""COMPUTED_VALUE"""),"IMPRESSORA MONOCROMÁTICO – PÁGINAS A3 ") -> IMPRESSORA MONOCROMÁTICO – PÁGINAS A3
A80: =IFERROR(__xludf.DUMMYFUNCTION("TRANSPOSE(FILTER(ITENS!$D:$D, ITENS!$A:$A = SERVICOS!$A81))"),"IMPRESSORA MONOCROMÁTICO – PÁGINAS A4 ") -> IMPRESSORA MONOCROMÁTICO – PÁGINAS A4 | B80: =IFERROR(__xludf.DUMMYFUNCTION("""COMPUTED_VALUE"""),"IMPRESSORA POLICROMÁTICO – PÁGINAS – A4 ") -> IMPRESSORA POLICROMÁTICO – PÁGINAS – A4 | C80: =IFERROR(__xludf.DUMMYFUNCTION("""COMPUTED_VALUE"""),"IMPRESSORA MONOCROMÁTICO – PÁGINAS A3 ") -> IMPRESSORA MONOCROMÁTICO – PÁGINAS A3
A81: =IFERROR(__xludf.DUMMYFUNCTION("TRANSPOSE(FILTER(ITENS!$D:$D, ITENS!$A:$A = SERVICOS!$A82))"),"IMPRESSORA MONOCROMÁTICO – PÁGINAS A4 ") -> IMPRESSORA MONOCROMÁTICO – PÁGINAS A4 | B81: =IFERROR(__xludf.DUMMYFUNCTION("""COMPUTED_VALUE"""),"IMPRESSORA POLICROMÁTICO – PÁGINAS – A4 ") -> IMPRESSORA POLICROMÁTICO – PÁGINAS – A4 | C81: =IFERROR(__xludf.DUMMYFUNCTION("""COMPUTED_VALUE"""),"IMPRESSORA MONOCROMÁTICO – PÁGINAS A3 ") -> IMPRESSORA MONOCROMÁTICO – PÁGINAS A3
A82: =IFERROR(__xludf.DUMMYFUNCTION("TRANSPOSE(FILTER(ITENS!$D:$D, ITENS!$A:$A = SERVICOS!$A83))"),"#N/A") -> #N/A
A83: =IFERROR(__xludf.DUMMYFUNCTION("TRANSPOSE(FILTER(ITENS!$D:$D, ITENS!$A:$A = SERVICOS!$A84))"),"#N/A") -> #N/A
A84: =IFERROR(__xludf.DUMMYFUNCTION("TRANSPOSE(FILTER(ITENS!$D:$D, ITENS!$A:$A = SERVICOS!$A85))"),"#N/A") -> #N/A
A85: =IFERROR(__xludf.DUMMYFUNCTION("TRANSPOSE(FILTER(ITENS!$D:$D, ITENS!$A:$A = SERVICOS!$A86))"),"#N/A") -> #N/A
A86: =IFERROR(__xludf.DUMMYFUNCTION("TRANSPOSE(FILTER(ITENS!$D:$D, ITENS!$A:$A = SERVICOS!$A87))"),"#N/A") -> #N/A
A87: =IFERROR(__xludf.DUMMYFUNCTION("TRANSPOSE(FILTER(ITENS!$D:$D, ITENS!$A:$A = SERVICOS!$A88))"),"#N/A") -> #N/A
A88: =IFERROR(__xludf.DUMMYFUNCTION("TRANSPOSE(FILTER(ITENS!$D:$D, ITENS!$A:$A = SERVICOS!$A89))"),"IMPRESSORA MONOCROMÁTICO – PÁGINAS A4 ") -> IMPRESSORA MONOCROMÁTICO – PÁGINAS A4 | B88: =IFERROR(__xludf.DUMMYFUNCTION("""COMPUTED_VALUE"""),"IMPRESSORA POLICROMÁTICO – PÁGINAS – A4 ") -> IMPRESSORA POLICROMÁTICO – PÁGINAS – A4 | C88: =IFERROR(__xludf.DUMMYFUNCTION("""COMPUTED_VALUE"""),"IMPRESSORA MONOCROMÁTICO – PÁGINAS A3 ") -> IMPRESSORA MONOCROMÁTICO – PÁGINAS A3
A89: =IFERROR(__xludf.DUMMYFUNCTION("TRANSPOSE(FILTER(ITENS!$D:$D, ITENS!$A:$A = SERVICOS!$A90))"),"IMPRESSORA MONOCROMÁTICO – PÁGINAS A4 ") -> IMPRESSORA MONOCROMÁTICO – PÁGINAS A4 | B89: =IFERROR(__xludf.DUMMYFUNCTION("""COMPUTED_VALUE"""),"IMPRESSORA POLICROMÁTICO – PÁGINAS – A4 ") -> IMPRESSORA POLICROMÁTICO – PÁGINAS – A4 | C89: =IFERROR(__xludf.DUMMYFUNCTION("""COMPUTED_VALUE"""),"IMPRESSORA MONOCROMÁTICO – PÁGINAS A3 ") -> IMPRESSORA MONOCROMÁTICO – PÁGINAS A3
A90: =IFERROR(__xludf.DUMMYFUNCTION("TRANSPOSE(FILTER(ITENS!$D:$D, ITENS!$A:$A = SERVICOS!$A91))"),"IMPRESSORA MONOCROMÁTICO – PÁGINAS A4 ") -> IMPRESSORA MONOCROMÁTICO – PÁGINAS A4 | B90: =IFERROR(__xludf.DUMMYFUNCTION("""COMPUTED_VALUE"""),"IMPRESSORA POLICROMÁTICO – PÁGINAS – A4 ") -> IMPRESSORA POLICROMÁTICO – PÁGINAS – A4 | C90: =IFERROR(__xludf.DUMMYFUNCTION("""COMPUTED_VALUE"""),"IMPRESSORA MONOCROMÁTICO – PÁGINAS A3 ") -> IMPRESSORA MONOCROMÁTICO – PÁGINAS A3
A91: =IFERROR(__xludf.DUMMYFUNCTION("TRANSPOSE(FILTER(ITENS!$D:$D, ITENS!$A:$A = SERVICOS!$A92))"),"IMPRESSORA MONOCROMÁTICO – PÁGINAS A4 ") -> IMPRESSORA MONOCROMÁTICO – PÁGINAS A4 | B91: =IFERROR(__xludf.DUMMYFUNCTION("""COMPUTED_VALUE"""),"IMPRESSORA POLICROMÁTICO – PÁGINAS – A4 ") -> IMPRESSORA POLICROMÁTICO – PÁGINAS – A4 | C91: =IFERROR(__xludf.DUMMYFUNCTION("""COMPUTED_VALUE"""),"IMPRESSORA MONOCROMÁTICO – PÁGINAS A3 ") -> IMPRESSORA MONOCROMÁTICO – PÁGINAS A3
A92: =IFERROR(__xludf.DUMMYFUNCTION("TRANSPOSE(FILTER(ITENS!$D:$D, ITENS!$A:$A = SERVICOS!$A93))"),"IMPRESSORA MONOCROMÁTICO – PÁGINAS A4 ") -> IMPRESSORA MONOCROMÁTICO – PÁGINAS A4 | B92: =IFERROR(__xludf.DUMMYFUNCTION("""COMPUTED_VALUE"""),"IMPRESSORA POLICROMÁTICO – PÁGINAS – A4 ") -> IMPRESSORA POLICROMÁTICO – PÁGINAS – A4 | C92: =IFERROR(__xludf.DUMMYFUNCTION("""COMPUTED_VALUE"""),"IMPRESSORA MONOCROMÁTICO – PÁGINAS A3 ") -> IMPRESSORA MONOCROMÁTICO – PÁGINAS A3
A93: =IFERROR(__xludf.DUMMYFUNCTION("TRANSPOSE(FILTER(ITENS!$D:$D, ITENS!$A:$A = SERVICOS!$A94))"),"#N/A") -> #N/A
A94: =IFERROR(__xludf.DUMMYFUNCTION("TRANSPOSE(FILTER(ITENS!$D:$D, ITENS!$A:$A = SERVICOS!$A95))"),"#N/A") -> #N/A
A95: =IFERROR(__xludf.DUMMYFUNCTION("TRANSPOSE(FILTER(ITENS!$D:$D, ITENS!$A:$A = SERVICOS!$A96))"),"#N/A") -> #N/A
A96: =IFERROR(__xludf.DUMMYFUNCTION("TRANSPOSE(FILTER(ITENS!$D:$D, ITENS!$A:$A = SERVICOS!$A97))"),"#N/A") -> #N/A
A97: =IFERROR(__xludf.DUMMYFUNCTION("TRANSPOSE(FILTER(ITENS!$D:$D, ITENS!$A:$A = SERVICOS!$A98))"),"#N/A") -> #N/A
A98: =IFERROR(__xludf.DUMMYFUNCTION("TRANSPOSE(FILTER(ITENS!$D:$D, ITENS!$A:$A = SERVICOS!$A99))"),"#N/A") -> #N/A
A99: =IFERROR(__xludf.DUMMYFUNCTION("TRANSPOSE(FILTER(ITENS!$D:$D, ITENS!$A:$A = SERVICOS!$A100))"),"#N/A") -> #N/A
A100: =IFERROR(__xludf.DUMMYFUNCTION("TRANSPOSE(FILTER(ITENS!$D:$D, ITENS!$A:$A = SERVICOS!$A101))"),"MULTIFUNCIONAL POLICROMÁTICA") -> MULTIFUNCIONAL POLICROMÁTICA | B100: =IFERROR(__xludf.DUMMYFUNCTION("""COMPUTED_VALUE"""),"IMPRESSORA MONOCROMÁTICA") -> IMPRESSORA MONOCROMÁTICA | C100: =IFERROR(__xludf.DUMMYFUNCTION("""COMPUTED_VALUE"""),"IMPRESSORA POLICROMÁTICA ") -> IMPRESSORA POLICROMÁTICA | D100: =IFERROR(__xludf.DUMMYFUNCTION("""COMPUTED_VALUE""")," IMPRESSORA MONOCROMÁTICA (período eleitoral)") -> IMPRESSORA MONOCROMÁTICA (período eleitoral) | E100: =IFERROR(__xludf.DUMMYFUNCTION("""COMPUTED_VALUE""")," IMPRESSORA TÉRMICA DE CARTÕES") -> IMPRESSORA TÉRMICA DE CARTÕES
...
